Workbook

Sheet Dataset
A1: 1.Delay in delivering material to construction site | B1: ID | C1: 1.Delay in delivering material to construction site | D1: 2.Monopoly of material by some suppliers | E1: 3.Prices fluctuation | F1: 4.Types of material availability at local market | G1: 5.Lack of consultant’s knowledge of available materials | H1: 6.Low productivity | I1: 7.Poor work execution | J1: 8.Shortage of laborers | K1: 9.Mistakes happens during construction phase | L1: 10.Unavailability of equipment | M1: 11.Lack of engineering experience | N1: 12.Construction cost underestimation | O1: 13.Poor site management | P1: 14.Delayed payment for completed work | Q1: 15.Cash flow problem during construction | R1: 16.High rate of interest | S1: 17.Contractor’s financial difficulties | T1: 18.Increase in salaries of skilled laborers | U1: 19.Change design | V1: 20.Errors and omission in design | W1: 21.Incomplete design drawings and specifications at tendering stage | X1: 22.Delay in preparation and approval of drawing | Y1: 23.Inaccurate quantity take-off | Z1: 24.Long period from planning of project to construction | AA1: 25.Delays in issuing information to the contractor during construction stage | AB1: 26.No practical use of earned value management system | AC1: 27.Lack of cost planning/monitoring during pre and post contract stage | AD1: 28.Poor communication between client, consultant and contractor | AE1: 29.Insufficient coordination between local authority who is responsible about road projects and service authorities | AF1: 30.Delays in decisions making by the approval authorities | AG1: 31.Change schedule | AH1: 32.Stoppages because of work being rejected by consultant | AI1: 33.Lowest bid price | AJ1: 34.Insufficient time for preparation of contract documents | AK1: 35.Discrepancies in contract documents | AL1: 36.Underestimation of time for completion of project | AM1: 37.Extension of time with cost claims | AN1: 38.Scope and specification changes | AO1: 39.Changes in client requirements | AP1: 40.Frequency of variation orders and additional works | AQ1: 41.Rework due to error in execution | AR1: 42.Weather conditions | AS1: 43.Accidents during construction | AT1: 44.Delay in getting NOCs from different government authorities | AU1: Type of Organization | AV1: Respondents designation | AW1: Indicate the highest formal qualification | AX1: How often do you experience cost overrun | AY1: Location of organization | AZ1: Relevant working experience
A2: 2.Monopoly of material by some suppliers | B2: ID001 | C2: 1 | D2: 1 | E2: 1 | F2: 1 | G2: 1 | H2: 1 | I2: 1 | J2: 1 | K2: 1 | L2: 1 | M2: 1 | N2: 1 | O2: 1 | P2: 1 | Q2: 1 | R2: 1 | S2: 1 | T2: 1 | U2: 3 | V2: 3 | W2: 3 | X2: 4 | Y2: 4 | Z2: 3 | AA2: 3 | AB2: 2 | AC2: 1 | AD2: 2 | AE2: 4 | AF2: 4 | AG2: 1 | AH2: 1 | AI2: 2 | AJ2: 2 | AK2: 2 | AL2: 2 | AM2: 2 | AN2: 3 | AO2: 3 | AP2: 3 | AQ2: 1 | AR2: 2 | AS2: 2 | AT2: 3 | AU2: 1 | AV2: 2 | AW2: 2 | AX2: 2 | AY2: 3 | AZ2: 5
A3: 3.Prices fluctuation | B3: ID002 | C3: 2 | D3: 5 | E3: 3 | F3: 2 | G3: 3 | H3: 2 | I3: 2 | J3: 2 | K3: 3 | L3: 2 | M3: 2 | N3: 2 | O3: 2 | P3: 2 | Q3: 2 | R3: 1 | S3: 4 | T3: 1 | U3: 5 | V3: 5 | W3: 4 | X3: 4 | Y3: 4 | Z3: 5 | AA3: 3 | AB3: 3 | AC3: 3 | AD3: 4 | AE3: 4 | AF3: 3 | AG3: 4 | AH3: 4 | AI3: 5 | AJ3: 3 | AK3: 4 | AL3: 4 | AM3: 4 | AN3: 3 | AO3: 3 | AP3: 4 | AQ3: 3 | AR3: 1 | AS3: 1 | AT3: 4 | AU3: 1 | AV3: 3 | AW3: 2 | AX3: 3 | AY3: 3 | AZ3: 3
A4: 4.Types of material availability at local market | B4: ID003 | C4: 1 | D4: 2 | E4: 1 | F4: 1 | G4: 2 | H4: 2 | I4: 1 | J4: 2 | K4: 1 | L4: 1 | M4: 2 | N4: 1 | O4: 3 | P4: 3 | Q4: 3 | R4: 2 | S4: 2 | T4: 1 | U4: 2 | V4: 2 | W4: 2 | X4: 2 | Y4: 3 | Z4: 2 | AA4: 3 | AB4: 1 | AC4: 2 | AD4: 1 | AE4: 3 | AF4: 4 | AG4: 3 | AH4: 1 | AI4: 2 | AJ4: 2 | AK4: 2 | AL4: 2 | AM4: 4 | AN4: 2 | AO4: 2 | AP4: 2 | AQ4: 2 | AR4: 1 | AS4: 1 | AT4: 4 | AU4: 1 | AV4: 2 | AW4: 2 | AX4: 1 | AY4: 2 | AZ4: 4
A5: 5.Lack of consultant’s knowledge of available materials | B5: ID004 | C5: 2 | D5: 2 | E5: 3 | F5: 3 | G5: 2 | H5: 2 | I5: 3 | J5: 4 | K5: 4 | L5: 4 | M5: 2 | N5: 5 | O5: 2 | P5: 2 | Q5: 1 | R5: 1 | S5: 1 | T5: 1 | U5: 4 | V5: 4 | W5: 4 | X5: 4 | Y5: 4 | Z5: 3 | AA5: 2 | AB5: 2 | AC5: 2 | AD5: 2 | AE5: 3 | AF5: 3 | AG5: 2 | AH5: 2 | AI5: 2 | AJ5: 3 | AK5: 2 | AL5: 4 | AM5: 4 | AN5: 4 | AO5: 4 | AP5: 4 | AQ5: 3 | AR5: 4 | AS5: 3 | AT5: 3 | AU5: 1 | AV5: 3 | AW5: 1 | AX5: 1 | AY5: 3 | AZ5: 4
A6: 6.Low productivity | B6: ID005 | C6: 1 | D6: 2 | E6: 1 | F6: 1 | G6: 2 | H6: 2 | I6: 1 | J6: 2 | K6: 1 | L6: 1 | M6: 2 | N6: 1 | O6: 2 | P6: 4 | Q6: 4 | R6: 2 | S6: 2 | T6: 1 | U6: 2 | V6: 2 | W6: 2 | X6: 2 | Y6: 3 | Z6: 2 | AA6: 4 | AB6: 3 | AC6: 2 | AD6: 1 | AE6: 3 | AF6: 4 | AG6: 3 | AH6: 1 | AI6: 2 | AJ6: 2 | AK6: 2 | AL6: 2 | AM6: 4 | AN6: 2 | AO6: 2 | AP6: 2 | AQ6: 2 | AR6: 1 | AS6: 1 | AT6: 4 | AU6: 1 | AV6: 2 | AW6: 3 | AX6: 1 | AY6: 2 | AZ6: 4
A7: 7.Poor work execution | B7: ID006 | C7: 1 | D7: 1 | E7: 1 | F7: 1 | G7: 1 | H7: 2 | I7: 2 | J7: 2 | K7: 1 | L7: 1 | M7: 1 | N7: 2 | O7: 1 | P7: 4 | Q7: 4 | R7: 4 | S7: 4 | T7: 1 | U7: 4 | V7: 4 | W7: 4 | X7: 4 | Y7: 4 | Z7: 4 | AA7: 2 | AB7: 2 | AC7: 2 | AD7: 1 | AE7: 1 | AF7: 3 | AG7: 3 | AH7: 4 | AI7: 2 | AJ7: 2 | AK7: 2 | AL7: 2 | AM7: 2 | AN7: 3 | AO7: 2 | AP7: 3 | AQ7: 3 | AR7: 2 | AS7: 2 | AT7: 2 | AU7: 1 | AV7: 4 | AW7: 2 | AX7: 1 | AY7: 3 | AZ7: 5
A8: 8.Shortage of laborers | B8: ID007 | C8: 1 | D8: 1 | E8: 1 | F8: 1 | G8: 1 | H8: 1 | I8: 1 | J8: 1 | K8: 1 | L8: 1 | M8: 1 | N8: 1 | O8: 1 | P8: 4 | Q8: 4 | R8: 4 | S8: 4 | T8: 1 | U8: 4 | V8: 4 | W8: 4 | X8: 4 | Y8: 4 | Z8: 4 | AA8: 2 | AB8: 2 | AC8: 2 | AD8: 1 | AE8: 2 | AF8: 4 | AG8: 3 | AH8: 4 | AI8: 2 | AJ8: 2 | AK8: 2 | AL8: 2 | AM8: 4 | AN8: 4 | AO8: 3 | AP8: 4 | AQ8: 4 | AR8: 2 | AS8: 2 | AT8: 2 | AU8: 1 | AV8: 5 | AW8: 2 | AX8: 1 | AY8: 3 | AZ8: 5
A9: 9.Mistakes happens during construction phase | B9: ID008 | C9: 1 | D9: 1 | E9: 1 | F9: 1 | G9: 1 | H9: 1 | I9: 1 | J9: 1 | K9: 1 | L9: 1 | M9: 1 | N9: 1 | O9: 1 | P9: 3 | Q9: 3 | R9: 3 | S9: 4 | T9: 4 | U9: 4 | V9: 4 | W9: 4 | X9: 4 | Y9: 4 | Z9: 4 | AA9: 2 | AB9: 2 | AC9: 2 | AD9: 1 | AE9: 1 | AF9: 3 | AG9: 3 | AH9: 4 | AI9: 2 | AJ9: 2 | AK9: 2 | AL9: 2 | AM9: 2 | AN9: 3 | AO9: 2 | AP9: 3 | AQ9: 3 | AR9: 2 | AS9: 2 | AT9: 2 | AU9: 1 | AV9: 4 | AW9: 2 | AX9: 1 | AY9: 3 | AZ9: 5
A10: 10.Unavailability of equipment | B10: ID009 | C10: 1 | D10: 1 | E10: 1 | F10: 1 | G10: 1 | H10: 1 | I10: 1 | J10: 1 | K10: 1 | L10: 1 | M10: 1 | N10: 1 | O10: 1 | P10: 4 | Q10: 4 | R10: 4 | S10: 4 | T10: 3 | U10: 4 | V10: 4 | W10: 4 | X10: 4 | Y10: 4 | Z10: 4 | AA10: 2 | AB10: 2 | AC10: 2 | AD10: 1 | AE10: 2 | AF10: 4 | AG10: 3 | AH10: 4 | AI10: 2 | AJ10: 2 | AK10: 2 | AL10: 2 | AM10: 2 | AN10: 4 | AO10: 3 | AP10: 4 | AQ10: 4 | AR10: 2 | AS10: 2 | AT10: 2 | AU10: 1 | AV10: 4 | AW10: 2 | AX10: 1 | AY10: 3 | AZ10: 5
A11: 11.Lack of engineering experience | B11: ID010 | C11: 1 | D11: 1 | E11: 1 | F11: 1 | G11: 1 | H11: 1 | I11: 1 | J11: 1 | K11: 1 | L11: 1 | M11: 1 | N11: 1 | O11: 1 | P11: 4 | Q11: 4 | R11: 4 | S11: 4 | T11: 2 | U11: 4 | V11: 4 | W11: 4 | X11: 4 | Y11: 4 | Z11: 4 | AA11: 2 | AB11: 2 | AC11: 2 | AD11: 1 | AE11: 1 | AF11: 3 | AG11: 3 | AH11: 4 | AI11: 2 | AJ11: 2 | AK11: 2 | AL11: 2 | AM11: 2 | AN11: 3 | AO11: 2 | AP11: 3 | AQ11: 3 | AR11: 2 | AS11: 2 | AT11: 2 | AU11: 1 | AV11: 4 | AW11: 2 | AX11: 1 | AY11: 3 | AZ11: 5
A12: 12.Construction cost underestimation | B12: ID011 | C12: 2 | D12: 4 | E12: 4 | F12: 1 | G12: 1 | H12: 5 | I12: 1 | J12: 4 | K12: 5 | L12: 3 | M12: 2 | N12: 5 | O12: 2 | P12: 1 | Q12: 1 | R12: 1 | S12: 1 | T12: 3 | U12: 5 | V12: 2 | W12: 3 | X12: 4 | Y12: 3 | Z12: 2 | AA12: 2 | AB12: 1 | AC12: 2 | AD12: 1 | AE12: 5 | AF12: 1 | AG12: 1 | AH12: 1 | AI12: 1 | AJ12: 1 | AK12: 1 | AL12: 3 | AM12: 3 | AN12: 4 | AO12: 4 | AP12: 4 | AQ12: 1 | AR12: 1 | AS12: 1 | AT12: 1 | AU12: 1 | AV12: 5 | AW12: 3 | AX12: 2 | AY12: 3 | AZ12: 4
A13: 13.Poor site management | B13: ID012 | C13: 2 | D13: 1 | E13: 3 | F13: 4 | G13: 4 | H13: 3 | I13: 3 | J13: 4 | K13: 3 | L13: 4 | M13: 5 | N13: 4 | O13: 3 | P13: 3 | Q13: 4 | R13: 2 | S13: 4 | T13: 2 | U13: 4 | V13: 4 | W13: 5 | X13: 3 | Y13: 4 | Z13: 3 | AA13: 3 | AB13: 3 | AC13: 3 | AD13: 4 | AE13: 4 | AF13: 4 | AG13: 3 | AH13: 4 | AI13: 4 | AJ13: 3 | AK13: 3 | AL13: 4 | AM13: 4 | AN13: 4 | AO13: 4 | AP13: 4 | AQ13: 4 | AR13: 2 | AS13: 2 | AT13: 3 | AU13: 1 | AV13: 2 | AW13: 2 | AX13: 1 | AY13: 3 | AZ13: 5
... A44: 44.Delay in getting NOCs from different government authorities | B44: ID043 | C44: 4 | D44: 5 | E44: 3 | F44: 4 | G44: 4 | H44: 4 | I44: 5 | J44: 4 | K44: 4 | L44: 4 | M44: 4 | N44: 4 | O44: 4 | P44: 5 | Q44: 5 | R44: 5 | S44: 4 | T44: 3 | U44: 5 | V44: 4 | W44: 4 | X44: 4 | Y44: 4 | Z44: 3 | AA44: 4 | AB44: 3 | AC44: 4 | AD44: 4 | AE44: 4 | AF44: 4 | AG44: 4 | AH44: 4 | AI44: 1 | AJ44: 2 | AK44: 3 | AL44: 4 | AM44: 5 | AN44: 4 | AO44: 5 | AP44: 4 | AQ44: 4 | AR44: 3 | AS44: 3 | AT44: 5 | AU44: 1 | AV44: 3 | AW44: 3 | AX44: 1 | AY44: 2 | AZ44: 4
A45: Type of Organization | B45: ID044 | C45: 4 | D45: 5 | E45: 3 | F45: 4 | G45: 4 | H45: 4 | I45: 5 | J45: 4 | K45: 4 | L45: 5 | M45: 4 | N45: 4 | O45: 4 | P45: 5 | Q45: 5 | R45: 5 | S45: 4 | T45: 3 | U45: 5 | V45: 4 | W45: 4 | X45: 4 | Y45: 4 | Z45: 3 | AA45: 4 | AB45: 3 | AC45: 4 | AD45: 3 | AE45: 3 | AF45: 4 | AG45: 4 | AH45: 4 | AJ45: 5 | AK45: 4 | AL45: 3 | AM45: 4 | AN45: 5 | AO45: 4 | AP45: 5 | AQ45: 3 | AR45: 2 | AS45: 2 | AT45: 5 | AU45: 1 | AV45: 3 | AW45: 2 | AX45: 1 | AY45: 1 | AZ45: 4
A46: Respondents designation | B46: ID045 | C46: 4 | D46: 5 | E46: 3 | F46: 4 | G46: 4 | H46: 4 | I46: 5 | J46: 4 | K46: 4 | L46: 5 | M46: 4 | N46: 4 | O46: 4 | P46: 5 | Q46: 5 | R46: 5 | S46: 4 | T46: 3 | U46: 5 | V46: 4 | W46: 4 | X46: 4 | Y46: 4 | Z46: 3 | AA46: 4 | AB46: 3 | AC46: 4 | AD46: 3 | AE46: 3 | AF46: 4 | AG46: 4 | AH46: 4 | AI46: 5 | AJ46: 4 | AK46: 3 | AL46: 4 | AM46: 5 | AN46: 4 | AO46: 5 | AP46: 4 | AQ46: 4 | AR46: 3 | AS46: 3 | AT46: 5 | AU46: 2 | AV46: 3 | AW46: 3 | AX46: 1 | AY46: 1 | AZ46: 4
A47: Indicate the highest formal qualification | B47: ID046 | C47: 4 | D47: 5 | E47: 3 | F47: 4 | G47: 4 | H47: 4 | I47: 5 | J47: 4 | K47: 4 | L47: 5 | M47: 4 | N47: 4 | O47: 4 | P47: 5 | Q47: 5 | R47: 5 | S47: 4 | T47: 3 | U47: 5 | V47: 4 | W47: 4 | X47: 4 | Y47: 4 | Z47: 3 | AA47: 4 | AB47: 3 | AC47: 4 | AD47: 4 | AE47: 4 | AF47: 5 | AG47: 4 | AH47: 4 | AI47: 5 | AJ47: 4 | AK47: 3 | AL47: 4 | AM47: 5 | AN47: 4 | AO47: 5 | AP47: 4 | AQ47: 4 | AR47: 3 | AS47: 3 | AT47: 5 | AU47: 2 | AV47: 2 | AW47: 3 | AX47: 1 | AY47: 3 | AZ47: 4
A48: How often do you experience cost overrun | B48: ID047 | C48: 4 | D48: 3 | E48: 3 | F48: 3 | G48: 3 | H48: 5 | I48: 5 | J48: 5 | K48: 5 | L48: 5 | M48: 4 | N48: 4 | O48: 4 | P48: 4 | Q48: 4 | R48: 3 | S48: 3 | T48: 3 | U48: 3 | V48: 2 | W48: 2 | X48: 4 | Y48: 3 | Z48: 2 | AA48: 3 | AB48: 4 | AC48: 4 | AD48: 5 | AE48: 5 | AF48: 5 | AG48: 4 | AH48: 4 | AI48: 3 | AJ48: 4 | AK48: 4 | AL48: 5 | AM48: 4 | AN48: 5 | AO48: 3 | AP48: 3 | AQ48: 4 | AR48: 3 | AS48: 2 | AT48: 4 | AU48: 2 | AV48: 2 | AW48: 2 | AX48: 2 | AY48: 3 | AZ48: 4
A49: Location of organization | B49: ID048 | C49: 1 | D49: 1 | E49: 2 | F49: 2 | G49: 2 | H49: 4 | I49: 4 | J49: 3 | K49: 4 | L49: 4 | M49: 5 | N49: 5 | O49: 5 | P49: 5 | Q49: 5 | R49: 5 | S49: 4 | T49: 3 | U49: 3 | V49: 4 | W49: 3 | X49: 4 | Y49: 4 | Z49: 4 | AA49: 3 | AB49: 2 | AC49: 4 | AD49: 5 | AE49: 5 | AF49: 5 | AG49: 3 | AH49: 2 | AI49: 4 | AJ49: 5 | AK49: 5 | AL49: 4 | AM49: 5 | AN49: 5 | AO49: 5 | AP49: 4 | AQ49: 5 | AR49: 3 | AS49: 5 | AT49: 4 | AU49: 2 | AV49: 5 | AW49: 2 | AX49: 1 | AY49: 1 | AZ49: 5
A50: Relevant working experience | B50: ID049 | C50: 4 | D50: 2 | E50: 4 | F50: 4 | G50: 3 | H50: 4 | I50: 5 | J50: 3 | K50: 5 | L50: 3 | M50: 5 | N50: 5 | O50: 5 | P50: 4 | Q50: 4 | R50: 3 | S50: 2 | T50: 2 | U50: 4 | V50: 5 | W50: 4 | X50: 4 | Y50: 4 | Z50: 4 | AA50: 3 | AB50: 3 | AC50: 4 | AD50: 4 | AE50: 5 | AF50: 5 | AG50: 3 | AH50: 3 | AI50: 4 | AJ50: 3 | AK50: 4 | AL50: 4 | AM50: 3 | AN50: 4 | AO50: 4 | AP50: 4 | AQ50: 4 | AR50: 3 | AS50: 3 | AT50: 3 | AU50: 2 | AV50: 5 | AW50: 3 | AX50: 2 | AY50: 3 | AZ50: 3
B51: ID050 | C51: 5 | D51: 4 | E51: 4 | F51: 5 | G51: 2 | H51: 5 | I51: 5 | J51: 5 | K51: 4 | L51: 4 | M51: 4 | N51: 4 | O51: 5 | P51: 3 | Q51: 5 | R51: 4 | S51: 5 | T51: 3 | U51: 4 | V51: 4 | W51: 4 | X51: 4 | Y51: 4 | Z51: 4 | AA51: 5 | AB51: 4 | AC51: 5 | AD51: 5 | AE51: 4 | AF51: 5 | AG51: 5 | AH51: 4 | AI51: 4 | AJ51: 5 | AK51: 4 | AL51: 4 | AM51: 4 | AN51: 5 | AO51: 4 | AP51: 5 | AQ51: 4 | AR51: 4 | AS51: 4 | AT51: 4 | AU51: 2 | AV51: 5 | AW51: 3 | AX51: 1 | AY51: 1 | AZ51: 4
B52: ID051 | C52: 4 | D52: 2 | E52: 4 | F52: 3 | G52: 3 | H52: 4 | I52: 4 | J52: 3 | K52: 4 | L52: 3 | M52: 3 | N52: 5 | O52: 4 | P52: 2 | Q52: 2 | R52: 3 | S52: 3 | T52: 3 | U52: 4 | V52: 3 | W52: 2 | X52: 3 | Y52: 4 | Z52: 4 | AA52: 3 | AB52: 3 | AC52: 3 | AD52: 2 | AE52: 2 | AF52: 3 | AG52: 4 | AH52: 4 | AI52: 4 | AJ52: 3 | AK52: 3 | AL52: 4 | AM52: 3 | AN52: 4 | AO52: 4 | AP52: 3 | AQ52: 4 | AR52: 3 | AS52: 3 | AT52: 2 | AU52: 2 | AV52: 5 | AW52: 2 | AX52: 1 | AY52: 3 | AZ52: 4
B53: ID052 | C53: 5 | D53: 4 | E53: 4 | F53: 5 | G53: 2 | H53: 5 | I53: 5 | J53: 5 | K53: 4 | L53: 4 | M53: 4 | N53: 4 | O53: 5 | P53: 4 | Q53: 5 | R53: 4 | S53: 5 | T53: 3 | U53: 4 | V53: 4 | W53: 4 | X53: 4 | Y53: 4 | Z53: 4 | AA53: 5 | AB53: 4 | AC53: 5 | AD53: 5 | AE53: 4 | AF53: 5 | AG53: 5 | AH53: 4 | AI53: 4 | AJ53: 5 | AK53: 4 | AL53: 4 | AM53: 4 | AN53: 4 | AO53: 5 | AP53: 4 | AQ53: 5 | AR53: 4 | AS53: 4 | AT53: 4 | AU53: 2 | AV53: 4 | AW53: 2 | AX53: 1 | AY53: 3 | AZ53: 3
B54: ID053 | C54: 5 | D54: 4 | E54: 1 | F54: 3 | G54: 1 | H54: 4 | I54: 4 | J54: 4 | K54: 4 | L54: 4 | M54: 4 | N54: 3 | O54: 3 | P54: 3 | Q54: 3 | R54: 2 | S54: 4 | T54: 2 | U54: 3 | V54: 3 | W54: 1 | X54: 2 | Y54: 3 | Z54: 4 | AA54: 3 | AB54: 2 | AC54: 3 | AD54: 3 | AE54: 4 | AF54: 5 | AG54: 1 | AH54: 2 | AI54: 3 | AJ54: 2 | AK54: 3 | AL54: 5 | AM54: 4 | AN54: 2 | AO54: 3 | AP54: 3 | AQ54: 3 | AR54: 2 | AS54: 2 | AT54: 4 | AU54: 2 | AV54: 3 | AW54: 2 | AX54: 2 | AY54: 3 | AZ54: 5
B55: ID054 | C55: 4 | D55: 5 | E55: 3 | F55: 4 | G55: 4 | H55: 4 | I55: 5 | J55: 4 | K55: 4 | L55: 5 | M55: 4 | N55: 4 | O55: 4 | P55: 5 | Q55: 5 | R55: 5 | S55: 4 | T55: 3 | U55: 5 | V55: 4 | W55: 4 | X55: 4 | Y55: 4 | Z55: 3 | AA55: 4 | AB55: 3 | AC55: 4 | AD55: 4 | AE55: 4 | AF55: 5 | AG55: 4 | AH55: 4 | AI55: 5 | AJ55: 4 | AK55: 3 | AL55: 4 | AM55: 5 | AN55: 4 | AO55: 5 | AP55: 4 | AQ55: 4 | AR55: 3 | AS55: 3 | AT55: 5 | AU55: 2 | AV55: 2 | AW55: 3 | AX55: 1 | AY55: 3 | AZ55: 4
B56: ID055 | C56: 2 | D56: 3 | E56: 4 | F56: 2 | G56: 4 | H56: 3 | I56: 2 | J56: 3 | K56: 4 | L56: 3 | M56: 4 | N56: 5 | O56: 5 | P56: 3 | Q56: 5 | R56: 4 | S56: 5 | T56: 4 | U56: 5 | V56: 4 | W56: 5 | X56: 3 | Y56: 5 | Z56: 5 | AA56: 3 | AB56: 4 | AC56: 4 | AD56: 3 | AE56: 3 | AF56: 4 | AG56: 3 | AH56: 3 | AI56: 3 | AJ56: 4 | AK56: 3 | AL56: 4 | AM56: 4 | AN56: 4 | AO56: 5 | AP56: 4 | AQ56: 4 | AR56: 3 | AS56: 3 | AT56: 3 | AU56: 2 | AV56: 3 | AW56: 2 | AX56: 1 | AY56: 3 | AZ56: 5
B57: ID056 | C57: 1 | D57: 1 | E57: 1 | F57: 1 | G57: 1 | H57: 5 | I57: 5 | J57: 3 | K57: 2 | L57: 5 | M57: 5 | N57: 5 | O57: 4 | P57: 5 | Q57: 5 | R57: 5 | S57: 5 | T57: 3 | U57: 5 | V57: 4 | W57: 4 | X57: 3 | Y57: 1 | Z57: 1 | AA57: 2 | AB57: 2 | AC57: 5 | AD57: 5 | AE57: 5 | AF57: 5 | AG57: 2 | AH57: 2 | AI57: 3 | AJ57: 5 | AK57: 4 | AL57: 5 | AM57: 3 | AN57: 4 | AO57: 5 | AP57: 4 | AQ57: 5 | AR57: 2 | AS57: 1 | AT57: 5 | AU57: 2 | AV57: 3 | AW57: 2 | AX57: 1 | AY57: 1 | AZ57: 5
B58: ID057 | C58: 1 | D58: 1 | E58: 4 | F58: 3 | G58: 4 | H58: 4 | I58: 4 | J58: 4 | K58: 5 | L58: 3 | M58: 3 | N58: 5 | O58: 5 | P58: 4 | Q58: 2 | R58: 3 | S58: 2 | T58: 5 | U58: 5 | V58: 4 | W58: 3 | X58: 5 | Y58: 5 | Z58: 4 | AA58: 4 | AB58: 3 | AC58: 4 | AD58: 4 | AE58: 3 | AF58: 5 | AG58: 5 | AH58: 3 | AI58: 3 | AJ58: 2 | AK58: 2 | AL58: 5 | AM58: 3 | AN58: 4 | AO58: 5 | AP58: 4 | AQ58: 3 | AR58: 2 | AS58: 2 | AT58: 4 | AU58: 2 | AV58: 5 | AW58: 2 | AX58: 1 | AY58: 3 | AZ58: 4
B59: ID058 | C59: 1 | D59: 1 | E59: 4 | F59: 3 | G59: 4 | H59: 4 | I59: 4 | J59: 4 | K59: 5 | L59: 3 | M59: 3 | N59: 5 | O59: 5 | P59: 3 | Q59: 2 | R59: 4 | S59: 2 | T59: 5 | U59: 5 | V59: 4 | W59: 3 | X59: 5 | Y59: 5 | Z59: 3 | AA59: 3 | AB59: 5 | AC59: 3 | AD59: 4 | AE59: 4 | AF59: 5 | AG59: 5 | AH59: 3 | AI59: 3 | AJ59: 4 | AK59: 4 | AL59: 3 | AM59: 1 | AN59: 4 | AO59: 5 | AP59: 4 | AQ59: 3 | AR59: 2 | AS59: 2 | AT59: 4 | AU59: 2 | AV59: 5 | AW59: 2 | AX59: 1 | AY59: 3 | AZ59: 4
B60: ID059 | C60: 1 | D60: 1 | E60: 4 | F60: 3 | G60: 4 | H60: 4 | I60: 4 | J60: 4 | K60: 5 | L60: 3 | M60: 3 | N60: 5 | O60: 5 | P60: 3 | Q60: 2 | R60: 4 | S60: 2 | T60: 5 | U60: 5 | V60: 4 | W60: 3 | X60: 5 | Y60: 5 | Z60: 3 | AA60: 3 | AB60: 5 | AC60: 3 | AD60: 4 | AE60: 4 | AF60: 5 | AG60: 5 | AH60: 3 | AI60: 3 | AJ60: 4 | AK60: 4 | AL60: 5 | AM60: 3 | AN60: 4 | AO60: 5 | AP60: 4 | AQ60: 3 | AR60: 2 | AS60: 2 | AT60: 4 | AU60: 2 | AV60: 5 | AW60: 2 | AX60: 1 | AY60: 1 | AZ60: 4
B61: ID060 | C61: 4 | D61: 5 | E61: 3 | F61: 4 | G61: 4 | H61: 4 | I61: 5 | J61: 4 | K61: 4 | L61: 5 | M61: 4 | N61: 4 | O61: 4 | P61: 5 | Q61: 5 | R61: 5 | S61: 4 | T61: 3 | U61: 5 | V61: 4 | W61: 4 | X61: 4 | Y61: 4 | Z61: 3 | AA61: 4 | AB61: 3 | AC61: 4 | AD61: 3 | AE61: 3 | AF61: 4 | AG61: 4 | AH61: 4 | AI61: 5 | AJ61: 4 | AK61: 3 | AL61: 4 | AM61: 5 | AN61: 4 | AO61: 5 | AP61: 4 | AQ61: 4 | AR61: 3 | AS61: 3 | AT61: 5 | AU61: 2 | AV61: 3 | AW61: 3 | AX61: 1 | AY61: 1 | AZ61: 4
B62: ID061 | C62: 4 | D62: 5 | E62: 3 | F62: 4 | G62: 4 | H62: 4 | I62: 5 | J62: 4 | K62: 4 | L62: 5 | M62: 4 | N62: 4 | O62: 4 | P62: 5 | Q62: 5 | R62: 5 | S62: 4 | T62: 3 | U62: 5 | V62: 4 | W62: 4 | X62: 4 | Y62: 4 | Z62: 3 | AA62: 4 | AB62: 3 | AC62: 4 | AD62: 3 | AE62: 3 | AF62: 4 | AG62: 4 | AH62: 4 | AI62: 5 | AJ62: 4 | AK62: 3 | AL62: 4 | AM62: 5 | AN62: 4 | AO62: 5 | AP62: 4 | AQ62: 4 | AR62: 3 | AS62: 3 | AT62: 5 | AU62: 2 | AV62: 3 | AW62: 2 | AX62: 1 | AY62: 2 | AZ62: 4
... B72: ID071 | C72: 4 | D72: 4 | E72: 3 | F72: 4 | G72: 4 | H72: 4 | I72: 4 | J72: 4 | K72: 4 | L72: 4 | M72: 4 | N72: 4 | O72: 4 | P72: 4 | Q72: 4 | R72: 4 | S72: 4 | T72: 4 | U72: 4 | V72: 4 | W72: 4 | X72: 4 | Y72: 4 | Z72: 3 | AA72: 3 | AB72: 3 | AC72: 4 | AD72: 5 | AE72: 4 | AF72: 5 | AG72: 3 | AH72: 4 | AI72: 4 | AJ72: 5 | AK72: 4 | AL72: 4 | AM72: 4 | AN72: 4 | AO72: 4 | AP72: 5 | AQ72: 5 | AR72: 4 | AS72: 4 | AT72: 5 | AU72: 2 | AV72: 2 | AW72: 3 | AX72: 2 | AY72: 1 | AZ72: 5
B73: ID072 | C73: 3 | D73: 3 | E73: 3 | F73: 3 | G73: 3 | H73: 3 | I73: 2 | J73: 3 | K73: 2 | L73: 3 | M73: 3 | N73: 3 | O73: 4 | P73: 4 | Q73: 4 | R73: 4 | S73: 5 | T73: 4 | V73: 2 | W73: 2 | X73: 3 | Y73: 3 | Z73: 2 | AA73: 3 | AB73: 3 | AC73: 4 | AD73: 3 | AE73: 3 | AF73: 4 | AG73: 3 | AH73: 3 | AI73: 3 | AJ73: 2 | AK73: 2 | AL73: 4 | AM73: 5 | AN73: 4 | AO73: 5 | AP73: 5 | AQ73: 2 | AR73: 2 | AS73: 2 | AT73: 4 | AU73: 2 | AV73: 2 | AW73: 3 | AX73: 2 | AY73: 3 | AZ73: 5
B74: ID073 | C74: 1 | D74: 1 | E74: 5 | F74: 1 | G74: 1 | H74: 5 | I74: 5 | J74: 5 | K74: 5 | L74: 5 | M74: 5 | N74: 5 | O74: 5 | P74: 4 | Q74: 4 | R74: 4 | S74: 4 | T74: 4 | U74: 5 | V74: 5 | W74: 5 | X74: 5 | Y74: 5 | Z74: 5 | AA74: 5 | AB74: 3 | AC74: 3 | AD74: 3 | AE74: 5 | AF74: 5 | AG74: 3 | AH74: 3 | AI74: 1 | AJ74: 1 | AK74: 1 | AL74: 1 | AM74: 1 | AN74: 5 | AO74: 5 | AP74: 5 | AQ74: 5 | AR74: 1 | AS74: 1 | AT74: 1 | AU74: 2 | AV74: 4 | AW74: 3 | AX74: 2 | AY74: 3 | AZ74: 4
B75: ID074 | C75: 4 | D75: 4 | E75: 1 | F75: 3 | G75: 3 | H75: 4 | I75: 4 | J75: 5 | K75: 4 | L75: 5 | M75: 3 | N75: 5 | O75: 5 | P75: 3 | Q75: 5 | R75: 3 | S75: 4 | T75: 2 | U75: 5 | V75: 5 | W75: 4 | X75: 5 | Y75: 4 | Z75: 3 | AA75: 5 | AB75: 3 | AC75: 5 | AD75: 3 | AE75: 4 | AF75: 4 | AG75: 3 | AH75: 4 | AI75: 5 | AJ75: 5 | AK75: 5 | AL75: 3 | AM75: 2 | AN75: 5 | AO75: 5 | AP75: 5 | AQ75: 4 | AR75: 3 | AS75: 3 | AT75: 4 | AU75: 2 | AV75: 4 | AW75: 3 | AX75: 2 | AY75: 1 | AZ75: 4
B76: ID075 | C76: 4 | D76: 4 | E76: 1 | F76: 3 | G76: 3 | H76: 4 | I76: 4 | J76: 3 | K76: 4 | L76: 5 | M76: 3 | N76: 5 | O76: 5 | P76: 3 | Q76: 4 | R76: 2 | S76: 4 | T76: 2 | U76: 3 | V76: 3 | W76: 4 | X76: 5 | Y76: 4 | Z76: 3 | AA76: 5 | AB76: 3 | AC76: 5 | AD76: 4 | AE76: 4 | AF76: 4 | AG76: 4 | AH76: 5 | AI76: 2 | AJ76: 2 | AK76: 2 | AL76: 5 | AM76: 3 | AN76: 4 | AO76: 4 | AP76: 4 | AQ76: 4 | AR76: 3 | AS76: 3 | AT76: 4 | AU76: 2 | AV76: 5 | AW76: 2 | AX76: 2 | AY76: 3 | AZ76: 4
B77: ID076 | C77: 3 | D77: 1 | E77: 1 | F77: 2 | G77: 1 | H77: 1 | I77: 1 | J77: 3 | K77: 1 | L77: 5 | M77: 1 | N77: 3 | O77: 1 | P77: 5 | Q77: 4 | R77: 2 | S77: 5 | T77: 5 | U77: 1 | V77: 1 | W77: 3 | X77: 5 | Y77: 3 | Z77: 3 | AA77: 2 | AB77: 3 | AC77: 3 | AD77: 5 | AE77: 5 | AF77: 5 | AG77: 5 | AH77: 2 | AI77: 5 | AJ77: 2 | AK77: 2 | AL77: 1 | AM77: 4 | AN77: 5 | AO77: 5 | AP77: 5 | AQ77: 1 | AR77: 2 | AS77: 2 | AT77: 5 | AU77: 2 | AV77: 2 | AW77: 3 | AX77: 2 | AY77: 1 | AZ77: 3
B78: ID077 | C78: 5 | D78: 3 | E78: 3 | F78: 3 | G78: 2 | H78: 5 | I78: 4 | J78: 4 | K78: 4 | L78: 4 | M78: 4 | N78: 5 | O78: 4 | P78: 3 | Q78: 3 | R78: 2 | S78: 3 | T78: 1 | U78: 5 | V78: 5 | W78: 5 | X78: 5 | Y78: 5 | Z78: 5 | AA78: 5 | AB78: 4 | AC78: 5 | AD78: 4 | AE78: 4 | AF78: 5 | AG78: 5 | AH78: 4 | AI78: 5 | AJ78: 5 | AK78: 5 | AL78: 5 | AM78: 4 | AN78: 5 | AO78: 5 | AP78: 5 | AQ78: 5 | AR78: 3 | AS78: 3 | AT78: 4 | AU78: 2 | AV78: 4 | AW78: 2 | AX78: 2 | AY78: 2 | AZ78: 3
B79: ID078 | C79: 5 | D79: 3 | E79: 2 | F79: 3 | G79: 5 | H79: 3 | I79: 3 | J79: 3 | K79: 4 | L79: 4 | M79: 5 | N79: 4 | O79: 5 | P79: 4 | Q79: 3 | R79: 3 | S79: 3 | T79: 4 | U79: 5 | V79: 5 | W79: 5 | X79: 4 | Y79: 5 | Z79: 5 | AA79: 4 | AB79: 4 | AC79: 4 | AD79: 4 | AE79: 4 | AF79: 5 | AG79: 4 | AH79: 3 | AI79: 3 | AJ79: 3 | AK79: 5 | AL79: 5 | AM79: 5 | AN79: 4 | AO79: 4 | AP79: 4 | AQ79: 5 | AR79: 3 | AS79: 3 | AT79: 5 | AU79: 2 | AV79: 5 | AW79: 3 | AX79: 2 | AY79: 2 | AZ79: 5
B80: ID079 | C80: 2 | D80: 2 | E80: 2 | F80: 2 | G80: 1 | H80: 3 | I80: 3 | J80: 1 | K80: 1 | L80: 1 | M80: 1 | N80: 2 | O80: 3 | P80: 3 | Q80: 3 | R80: 1 | S80: 3 | T80: 1 | U80: 2 | V80: 1 | W80: 2 | X80: 3 | Y80: 3 | Z80: 4 | AA80: 2 | AB80: 1 | AC80: 2 | AD80: 1 | AE80: 3 | AF80: 4 | AG80: 2 | AH80: 1 | AI80: 2 | AJ80: 1 | AK80: 2 | AL80: 3 | AM80: 3 | AN80: 5 | AO80: 5 | AP80: 4 | AQ80: 4 | AR80: 1 | AS80: 2 | AT80: 3 | AU80: 2 | AV80: 4 | AW80: 2 | AX80: 2 | AY80: 1 | AZ80: 5
B81: ID080 | C81: 3 | D81: 4 | E81: 2 | F81: 2 | G81: 3 | H81: 4 | I81: 4 | J81: 4 | K81: 5 | L81: 3 | M81: 5 | N81: 4 | O81: 5 | P81: 5 | Q81: 5 | R81: 3 | S81: 2 | T81: 2 | U81: 4 | V81: 4 | W81: 4 | X81: 4 | Y81: 4 | Z81: 3 | AA81: 4 | AB81: 3 | AC81: 4 | AD81: 5 | AE81: 5 | AF81: 5 | AG81: 4 | AH81: 3 | AI81: 3 | AJ81: 3 | AK81: 3 | AL81: 3 | AM81: 3 | AN81: 3 | AO81: 4 | AP81: 5 | AQ81: 3 | AR81: 2 | AS81: 3 | AT81: 4 | AU81: 2 | AV81: 2 | AW81: 2 | AX81: 1 | AY81: 1 | AZ81: 5
B82: ID081 | C82: 2 | D82: 2 | E82: 3 | F82: 4 | G82: 5 | H82: 5 | I82: 5 | J82: 4 | K82: 5 | L82: 5 | M82: 4 | N82: 4 | O82: 5 | P82: 4 | Q82: 4 | R82: 4 | S82: 4 | T82: 3 | U82: 3 | V82: 4 | W82: 4 | X82: 2 | Y82: 4 | Z82: 4 | AA82: 4 | AB82: 4 | AC82: 5 | AD82: 5 | AE82: 5 | AF82: 4 | AG82: 5 | AH82: 5 | AI82: 5 | AJ82: 4 | AK82: 4 | AL82: 4 | AM82: 4 | AN82: 5 | AO82: 5 | AP82: 4 | AQ82: 4 | AR82: 2 | AS82: 2 | AT82: 3 | AU82: 2 | AV82: 1 | AW82: 3 | AX82: 2 | AY82: 1 | AZ82: 5
B83: ID082 | C83: 4 | D83: 1 | E83: 2 | F83: 3 | G83: 4 | H83: 5 | I83: 5 | J83: 5 | K83: 3 | L83: 3 | M83: 4 | N83: 5 | O83: 5 | P83: 4 | Q83: 1 | R83: 1 | S83: 1 | T83: 3 | U83: 5 | V83: 4 | W83: 5 | X83: 3 | Y83: 1 | Z83: 1 | AA83: 3 | AB83: 2 | AC83: 3 | AD83: 4 | AE83: 4 | AF83: 4 | AG83: 4 | AH83: 4 | AI83: 4 | AJ83: 3 | AK83: 2 | AL83: 1 | AM83: 1 | AN83: 5 | AO83: 5 | AP83: 5 | AQ83: 2 | AR83: 1 | AS83: 1 | AT83: 3 | AU83: 2 | AV83: 4 | AW83: 2 | AX83: 2 | AY83: 1 | AZ83: 5
B84: ID083 | C84: 4 | D84: 5 | E84: 3 | F84: 4 | G84: 4 | H84: 4 | I84: 4 | J84: 4 | K84: 4 | L84: 4 | M84: 4 | N84: 4 | O84: 4 | P84: 5 | Q84: 5 | R84: 5 | S84: 5 | T84: 3 | U84: 5 | V84: 5 | W84: 4 | X84: 4 | Y84: 5 | Z84: 4 | AA84: 5 | AB84: 3 | AC84: 4 | AD84: 4 | AE84: 4 | AF84: 4 | AG84: 5 | AH84: 5 | AI84: 4 | AJ84: 4 | AK84: 3 | AL84: 4 | AM84: 5 | AN84: 4 | AO84: 4 | AP84: 4 | AQ84: 2 | AR84: 4 | AS84: 3 | AT84: 3 | AU84: 2 | AV84: 2 | AW84: 2 | AX84: 1 | AY84: 3 | AZ84: 5
B85: ID084 | C85: 3 | D85: 4 | E85: 4 | F85: 3 | G85: 2 | H85: 4 | I85: 4 | J85: 4 | K85: 4 | L85: 4 | M85: 3 | N85: 3 | O85: 3 | P85: 3 | Q85: 2 | R85: 1 | S85: 4 | T85: 1 | U85: 4 | V85: 2 | W85: 3 | X85: 3 | Y85: 1 | Z85: 4 | AA85: 1 | AB85: 2 | AC85: 4 | AD85: 3 | AE85: 3 | AF85: 4 | AG85: 3 | AH85: 1 | AI85: 3 | AJ85: 3 | AK85: 4 | AL85: 4 | AM85: 4 | AN85: 4 | AO85: 5 | AP85: 4 | AQ85: 3 | AR85: 2 | AS85: 2 | AT85: 4 | AU85: 2 | AV85: 2 | AW85: 3 | AX85: 1 | AY85: 3 | AZ85: 4
... B115: ID114 | C115: 4 | D115: 5 | E115: 3 | F115: 3 | G115: 3 | H115: 4 | I115: 4 | J115: 5 | K115: 3 | L115: 2 | M115: 4 | N115: 5 | O115: 5 | P115: 4 | Q115: 1 | R115: 2 | S115: 1 | T115: 3 | U115: 4 | V115: 2 | W115: 2 | X115: 2 | Y115: 1 | Z115: 3 | AA115: 2 | AB115: 1 | AC115: 1 | AD115: 1 | AE115: 2 | AF115: 4 | AG115: 2 | AH115: 3 | AI115: 5 | AJ115: 2 | AK115: 2 | AL115: 4 | AM115: 4 | AN115: 4 | AO115: 4 | AP115: 4 | AQ115: 3 | AR115: 2 | AS115: 5 | AT115: 5 | AU115: 3 | AV115: 2 | AW115: 2 | AX115: 1 | AY115: 2 | AZ115: 2
B116: ID115 | C116: 3 | D116: 3 | E116: 3 | F116: 3 | G116: 3 | H116: 3 | I116: 2 | J116: 3 | K116: 2 | L116: 3 | M116: 3 | N116: 3 | O116: 4 | P116: 4 | Q116: 4 | R116: 4 | S116: 5 | T116: 4 | V116: 2 | W116: 2 | X116: 3 | Y116: 3 | Z116: 2 | AA116: 3 | AB116: 3 | AC116: 4 | AD116: 3 | AE116: 3 | AF116: 4 | AG116: 3 | AH116: 3 | AI116: 3 | AJ116: 2 | AK116: 2 | AL116: 4 | AM116: 5 | AN116: 4 | AO116: 5 | AP116: 5 | AQ116: 2 | AR116: 2 | AS116: 2 | AT116: 4 | AU116: 3 | AV116: 2 | AW116: 3 | AX116: 2 | AY116: 3 | AZ116: 5
B117: ID116 | C117: 4 | D117: 4 | E117: 4 | F117: 4 | G117: 3 | H117: 4 | I117: 4 | J117: 4 | K117: 3 | L117: 4 | M117: 4 | N117: 4 | O117: 4 | P117: 4 | Q117: 4 | R117: 3 | S117: 3 | T117: 3 | U117: 5 | V117: 5 | W117: 5 | X117: 3 | Y117: 3 | Z117: 3 | AA117: 4 | AB117: 3 | AC117: 4 | AD117: 4 | AE117: 4 | AF117: 4 | AG117: 4 | AH117: 4 | AI117: 3 | AJ117: 3 | AK117: 3 | AL117: 3 | AM117: 3 | AN117: 4 | AO117: 3 | AP117: 3 | AQ117: 3 | AR117: 4 | AS117: 4 | AT117: 5 | AU117: 3 | AV117: 5 | AW117: 2 | AX117: 1 | AY117: 3 | AZ117: 4
B118: ID117 | C118: 2 | D118: 4 | E118: 4 | F118: 3 | G118: 2 | H118: 4 | I118: 4 | J118: 3 | K118: 4 | L118: 4 | M118: 5 | N118: 5 | O118: 4 | P118: 2 | Q118: 2 | R118: 2 | S118: 4 | T118: 3 | U118: 2 | V118: 2 | W118: 2 | X118: 2 | Y118: 5 | Z118: 3 | AA118: 2 | AB118: 3 | AC118: 4 | AD118: 4 | AE118: 4 | AF118: 2 | AG118: 2 | AH118: 3 | AI118: 2 | AJ118: 2 | AK118: 3 | AL118: 5 | AM118: 2 | AN118: 2 | AO118: 2 | AP118: 2 | AQ118: 5 | AR118: 3 | AS118: 4 | AT118: 3 | AU118: 3 | AV118: 5 | AW118: 2 | AX118: 3 | AY118: 2 | AZ118: 5
B119: ID118 | C119: 1 | D119: 1 | E119: 1 | F119: 1 | G119: 2 | H119: 3 | I119: 3 | J119: 3 | K119: 3 | L119: 3 | M119: 4 | N119: 5 | O119: 5 | P119: 4 | Q119: 4 | R119: 5 | S119: 5 | T119: 2 | U119: 4 | V119: 4 | W119: 5 | X119: 4 | Y119: 5 | Z119: 5 | AA119: 4 | AB119: 4 | AC119: 4 | AD119: 4 | AE119: 4 | AF119: 5 | AG119: 4 | AH119: 2 | AI119: 1 | AJ119: 4 | AK119: 4 | AL119: 4 | AM119: 4 | AN119: 4 | AO119: 4 | AP119: 4 | AQ119: 4 | AR119: 3 | AS119: 3 | AT119: 4 | AU119: 3 | AV119: 2 | AW119: 2 | AX119: 2 | AY119: 1 | AZ119: 5
B120: ID119 | C120: 4 | D120: 5 | E120: 3 | F120: 5 | G120: 5 | H120: 4 | I120: 4 | J120: 4 | K120: 3 | L120: 4 | M120: 4 | N120: 4 | O120: 5 | P120: 5 | Q120: 5 | R120: 4 | S120: 5 | T120: 2 | U120: 4 | V120: 4 | W120: 5 | X120: 5 | Y120: 5 | Z120: 2 | AA120: 4 | AB120: 3 | AC120: 4 | AD120: 5 | AE120: 3 | AF120: 4 | AG120: 4 | AH120: 5 | AI120: 2 | AJ120: 4 | AK120: 4 | AL120: 4 | AM120: 5 | AN120: 4 | AO120: 4 | AP120: 4 | AQ120: 5 | AR120: 4 | AS120: 4 | AT120: 4 | AU120: 3 | AV120: 5 | AW120: 3 | AX120: 1 | AY120: 3 | AZ120: 5
B121: ID120 | C121: 1 | D121: 1 | E121: 1 | F121: 1 | G121: 2 | H121: 3 | I121: 3 | J121: 3 | K121: 3 | L121: 3 | M121: 4 | N121: 5 | O121: 5 | P121: 4 | Q121: 4 | R121: 5 | S121: 5 | T121: 2 | U121: 4 | V121: 4 | W121: 5 | X121: 4 | Y121: 5 | Z121: 5 | AA121: 4 | AB121: 4 | AC121: 4 | AD121: 4 | AE121: 4 | AF121: 5 | AG121: 4 | AH121: 2 | AI121: 1 | AJ121: 4 | AK121: 4 | AL121: 4 | AM121: 4 | AN121: 4 | AO121: 4 | AP121: 4 | AQ121: 4 | AR121: 3 | AS121: 3 | AT121: 4 | AU121: 3 | AV121: 2 | AW121: 2 | AX121: 2 | AY121: 1 | AZ121: 3
B122: ID121 | C122: 2 | D122: 2 | E122: 3 | F122: 3 | G122: 4 | H122: 4 | I122: 4 | J122: 3 | K122: 3 | L122: 3 | M122: 4 | N122: 4 | O122: 4 | P122: 3 | Q122: 3 | R122: 3 | S122: 4 | T122: 4 | U122: 4 | V122: 3 | W122: 4 | X122: 5 | Y122: 4 | Z122: 3 | AA122: 3 | AB122: 5 | AC122: 4 | AD122: 2 | AE122: 3 | AF122: 3 | AG122: 3 | AH122: 3 | AI122: 4 | AJ122: 5 | AK122: 5 | AL122: 4 | AM122: 4 | AN122: 5 | AO122: 5 | AP122: 5 | AQ122: 4 | AR122: 2 | AS122: 2 | AT122: 3 | AU122: 3 | AV122: 2 | AW122: 2 | AX122: 2 | AY122: 2 | AZ122: 4
B123: ID122 | C123: 4 | D123: 3 | E123: 3 | F123: 3 | G123: 3 | H123: 4 | I123: 4 | J123: 5 | K123: 4 | L123: 5 | M123: 4 | N123: 5 | O123: 4 | P123: 4 | Q123: 4 | R123: 3 | S123: 4 | T123: 3 | U123: 4 | V123: 3 | W123: 4 | X123: 4 | Y123: 3 | Z123: 2 | AA123: 1 | AB123: 5 | AC123: 3 | AD123: 4 | AE123: 2 | AF123: 3 | AG123: 4 | AH123: 3 | AI123: 4 | AJ123: 3 | AK123: 3 | AL123: 3 | AM123: 4 | AN123: 5 | AO123: 5 | AP123: 5 | AQ123: 5 | AR123: 1 | AS123: 2 | AT123: 3 | AU123: 3 | AV123: 2 | AW123: 2 | AX123: 1 | AY123: 1 | AZ123: 5
B124: ID123 | C124: 4 | D124: 5 | E124: 3 | F124: 3 | G124: 3 | H124: 4 | I124: 4 | J124: 5 | K124: 3 | L124: 2 | M124: 4 | N124: 5 | O124: 5 | P124: 4 | Q124: 1 | R124: 2 | S124: 1 | T124: 3 | U124: 4 | V124: 2 | W124: 2 | X124: 2 | Y124: 1 | Z124: 3 | AA124: 2 | AB124: 1 | AC124: 1 | AD124: 1 | AE124: 2 | AF124: 4 | AG124: 2 | AH124: 3 | AI124: 5 | AJ124: 2 | AK124: 2 | AL124: 4 | AM124: 4 | AN124: 4 | AO124: 4 | AP124: 4 | AQ124: 3 | AR124: 2 | AS124: 5 | AT124: 5 | AU124: 3 | AV124: 2 | AW124: 2 | AX124: 1 | AY124: 2 | AZ124: 5
B125: ID124 | C125: 4 | D125: 5 | E125: 3 | F125: 5 | G125: 4 | H125: 4 | I125: 4 | J125: 4 | K125: 3 | L125: 3 | M125: 5 | N125: 5 | O125: 4 | P125: 2 | Q125: 3 | R125: 4 | S125: 4 | T125: 3 | U125: 4 | V125: 5 | W125: 4 | X125: 4 | Y125: 5 | Z125: 5 | AA125: 4 | AB125: 3 | AC125: 4 | AD125: 3 | AE125: 4 | AF125: 5 | AG125: 4 | AH125: 5 | AI125: 5 | AJ125: 4 | AK125: 4 | AL125: 5 | AM125: 4 | AN125: 4 | AO125: 4 | AP125: 2 | AQ125: 4 | AR125: 5 | AS125: 5 | AT125: 4 | AU125: 3 | AV125: 2 | AW125: 3 | AX125: 2 | AY125: 2 | AZ125: 3
B126: ID125 | C126: 1 | D126: 1 | E126: 1 | F126: 1 | G126: 2 | H126: 3 | I126: 3 | J126: 3 | K126: 3 | L126: 3 | M126: 4 | N126: 5 | O126: 5 | P126: 4 | Q126: 4 | R126: 5 | S126: 5 | T126: 2 | U126: 4 | V126: 4 | W126: 5 | X126: 4 | Y126: 5 | Z126: 5 | AA126: 4 | AB126: 4 | AC126: 4 | AD126: 4 | AE126: 4 | AF126: 5 | AG126: 4 | AH126: 2 | AI126: 1 | AJ126: 4 | AK126: 4 | AL126: 4 | AM126: 4 | AN126: 4 | AO126: 4 | AP126: 4 | AQ126: 4 | AR126: 3 | AS126: 3 | AT126: 4 | AU126: 3 | AV126: 2 | AW126: 2 | AX126: 2 | AY126: 1 | AZ126: 5
B127: ID126 | C127: 4 | D127: 5 | E127: 3 | F127: 3 | G127: 3 | H127: 4 | I127: 4 | J127: 5 | K127: 3 | L127: 2 | M127: 4 | N127: 5 | O127: 5 | P127: 4 | Q127: 1 | R127: 2 | S127: 1 | T127: 3 | U127: 4 | V127: 2 | W127: 2 | X127: 2 | Y127: 1 | Z127: 3 | AA127: 2 | AB127: 1 | AC127: 1 | AD127: 1 | AE127: 2 | AF127: 4 | AG127: 2 | AH127: 3 | AI127: 5 | AJ127: 2 | AK127: 2 | AL127: 4 | AM127: 4 | AN127: 4 | AO127: 4 | AP127: 4 | AQ127: 3 | AR127: 2 | AS127: 5 | AT127: 5 | AU127: 3 | AV127: 2 | AW127: 2 | AX127: 1 | AY127: 2 | AZ127: 5
B128: ID127 | C128: 4 | D128: 3 | E128: 3 | F128: 3 | G128: 3 | H128: 4 | I128: 4 | J128: 5 | K128: 4 | L128: 5 | M128: 4 | N128: 5 | O128: 4 | P128: 4 | Q128: 4 | R128: 3 | S128: 4 | T128: 3 | U128: 4 | V128: 3 | W128: 4 | X128: 4 | Y128: 3 | Z128: 2 | AA128: 1 | AB128: 5 | AC128: 3 | AD128: 4 | AE128: 2 | AF128: 3 | AG128: 4 | AH128: 3 | AI128: 4 | AJ128: 3 | AK128: 3 | AL128: 3 | AM128: 4 | AN128: 5 | AO128: 5 | AP128: 5 | AQ128: 5 | AR128: 1 | AS128: 2 | AT128: 3 | AU128: 3 | AV128: 2 | AW128: 2 | AX128: 1 | AY128: 1 | AZ128: 4
B129: ID128 | C129: 3 | D129: 3 | E129: 3 | F129: 3 | G129: 3 | H129: 3 | I129: 2 | J129: 3 | K129: 2 | L129: 3 | M129: 3 | N129: 3 | O129: 4 | P129: 4 | Q129: 4 | R129: 4 | S129: 5 | T129: 4 | V129: 2 | W129: 2 | X129: 3 | Y129: 3 | Z129: 2 | AA129: 3 | AB129: 3 | AC129: 4 | AD129: 3 | AE129: 3 | AF129: 4 | AG129: 3 | AH129: 3 | AI129: 3 | AJ129: 2 | AK129: 2 | AL129: 4 | AM129: 5 | AN129: 4 | AO129: 5 | AP129: 5 | AQ129: 2 | AR129: 2 | AS129: 2 | AT129: 4 | AU129: 3 | AV129: 2 | AW129: 3 | AX129: 2 | AY129: 3 | AZ129: 4
B130: ID129 | C130: 4 | D130: 4 | E130: 3 | F130: 4 | G130: 4 | H130: 4 | I130: 4 | J130: 4 | K130: 4 | L130: 4 | M130: 4 | N130: 4 | O130: 4 | P130: 4 | Q130: 4 | R130: 4 | S130: 4 | T130: 4 | U130: 4 | V130: 4 | W130: 4 | X130: 4 | Y130: 4 | Z130: 3 | AA130: 3 | AB130: 3 | AC130: 4 | AD130: 5 | AE130: 4 | AF130: 5 | AG130: 3 | AH130: 4 | AI130: 4 | AJ130: 5 | AK130: 4 | AL130: 4 | AM130: 4 | AN130: 4 | AO130: 4 | AP130: 5 | AQ130: 5 | AR130: 4 | AS130: 4 | AT130: 5 | AU130: 3 | AV130: 2 | AW130: 3 | AX130: 2 | AY130: 3 | AZ130: 5
B131: ID130 | C131: 2 | D131: 2 | E131: 3 | F131: 3 | G131: 1 | H131: 2 | I131: 3 | J131: 3 | K131: 2 | L131: 2 | M131: 3 | N131: 2 | O131: 3 | P131: 4 | Q131: 4 | R131: 1 | S131: 4 | T131: 2 | U131: 3 | V131: 3 | W131: 3 | X131: 3 | Y131: 3 | Z131: 4 | AA131: 3 | AB131: 3 | AC131: 3 | AD131: 2 | AE131: 2 | AF131: 5 | AG131: 4 | AH131: 1 | AI131: 4 | AJ131: 3 | AK131: 3 | AL131: 3 | AM131: 4 | AN131: 4 | AO131: 4 | AP131: 3 | AQ131: 3 | AR131: 1 | AS131: 1 | AT131: 2 | AU131: 3 | AV131: 2 | AW131: 4 | AX131: 2 | AY131: 2 | AZ131: 3
B132: ID131 | C132: 3 | D132: 4 | E132: 2 | F132: 2 | G132: 3 | H132: 4 | I132: 4 | J132: 4 | K132: 5 | L132: 3 | M132: 5 | N132: 4 | O132: 5 | P132: 5 | Q132: 5 | R132: 3 | S132: 2 | T132: 2 | U132: 4 | V132: 4 | W132: 4 | X132: 4 | Y132: 4 | Z132: 3 | AA132: 4 | AB132: 3 | AC132: 4 | AD132: 5 | AE132: 5 | AF132: 5 | AG132: 4 | AH132: 3 | AI132: 3 | AJ132: 3 | AK132: 3 | AL132: 3 | AM132: 3 | AN132: 3 | AO132: 4 | AP132: 5 | AQ132: 3 | AR132: 2 | AS132: 3 | AT132: 4 | AU132: 3 | AV132: 2 | AW132: 2 | AX132: 2 | AY132: 1 | AZ132: 5
B133: ID132 | C133: 2 | D133: 2 | E133: 2 | F133: 2 | G133: 1 | H133: 3 | I133: 3 | J133: 1 | K133: 1 | L133: 1 | M133: 1 | N133: 2 | O133: 3 | P133: 3 | Q133: 3 | R133: 1 | S133: 3 | T133: 1 | U133: 2 | V133: 1 | W133: 2 | X133: 3 | Y133: 3 | Z133: 4 | AA133: 2 | AB133: 1 | AC133: 2 | AD133: 1 | AE133: 3 | AF133: 4 | AG133: 2 | AH133: 1 | AI133: 2 | AJ133: 1 | AK133: 2 | AL133: 3 | AM133: 3 | AN133: 5 | AO133: 5 | AP133: 4 | AQ133: 4 | AR133: 1 | AS133: 2 | AT133: 3 | AU133: 3 | AV133: 4 | AW133: 2 | AX133: 2 | AY133: 1 | AZ133: 2
B134: ID133 | C134: 3 | D134: 1 | E134: 1 | F134: 2 | G134: 1 | H134: 1 | I134: 1 | J134: 3 | K134: 1 | L134: 5 | M134: 1 | N134: 3 | O134: 1 | P134: 5 | Q134: 4 | R134: 2 | S134: 5 | T134: 5 | U134: 1 | V134: 1 | W134: 3 | X134: 5 | Y134: 3 | Z134: 3 | AA134: 2 | AB134: 3 | AC134: 3 | AD134: 5 | AE134: 5 | AF134: 5 | AG134: 5 | AH134: 2 | AI134: 5 | AJ134: 2 | AK134: 2 | AL134: 1 | AM134: 4 | AN134: 5 | AO134: 5 | AP134: 5 | AQ134: 1 | AR134: 2 | AS134: 2 | AT134: 5 | AU134: 3 | AV134: 2 | AW134: 3 | AX134: 2 | AY134: 1 | AZ134: 3
B135: ID134 | C135: 4 | D135: 4 | E135: 1 | F135: 3 | G135: 3 | H135: 4 | I135: 4 | J135: 5 | K135: 4 | L135: 5 | M135: 3 | N135: 5 | O135: 5 | P135: 3 | Q135: 5 | R135: 3 | S135: 4 | T135: 2 | U135: 5 | V135: 5 | W135: 4 | X135: 5 | Y135: 4 | Z135: 3 | AA135: 5 | AB135: 3 | AC135: 5 | AD135: 3 | AE135: 4 | AF135: 4 | AG135: 3 | AH135: 4 | AI135: 5 | AJ135: 5 | AK135: 5 | AL135: 3 | AM135: 2 | AN135: 5 | AO135: 5 | AP135: 5 | AQ135: 4 | AR135: 3 | AS135: 3 | AT135: 4 | AU135: 2 | AV135: 5 | AW135: 3 | AX135: 2 | AY135: 3 | AZ135: 4
B136: ID135 | C136: 3 | D136: 3 | E136: 3 | F136: 3 | G136: 3 | H136: 3 | I136: 2 | J136: 3 | K136: 2 | L136: 3 | M136: 3 | N136: 3 | O136: 4 | P136: 4 | Q136: 4 | R136: 4 | S136: 5 | T136: 4 | V136: 2 | W136: 2 | X136: 3 | Y136: 3 | Z136: 2 | AA136: 3 | AB136: 3 | AC136: 4 | AD136: 3 | AE136: 3 | AF136: 4 | AG136: 3 | AH136: 3 | AI136: 3 | AJ136: 2 | AK136: 2 | AL136: 4 | AM136: 5 | AN136: 4 | AO136: 5 | AP136: 5 | AQ136: 2 | AR136: 2 | AS136: 2 | AT136: 4 | AU136: 2 | AV136: 2 | AW136: 3 | AX136: 2 | AY136: 3 | AZ136: 5
B137: ID136 | C137: 4 | D137: 4 | E137: 3 | F137: 4 | G137: 4 | H137: 4 | I137: 4 | J137: 4 | K137: 4 | L137: 4 | M137: 4 | N137: 4 | O137: 4 | P137: 4 | Q137: 4 | R137: 4 | S137: 4 | T137: 4 | U137: 4 | V137: 4 | W137: 4 | X137: 4 | Y137: 4 | Z137: 3 | AA137: 3 | AB137: 3 | AC137: 4 | AD137: 5 | AE137: 4 | AF137: 5 | AG137: 3 | AH137: 4 | AI137: 4 | AJ137: 5 | AK137: 4 | AL137: 4 | AM137: 4 | AN137: 4 | AO137: 4 | AP137: 5 | AQ137: 5 | AR137: 4 | AS137: 4 | AT137: 5 | AU137: 2 | AV137: 2 | AW137: 3 | AX137: 3 | AY137: 2 | AZ137: 1
B138: ID137 | C138: 4 | D138: 5 | E138: 4 | F138: 3 | G138: 4 | H138: 4 | I138: 4 | J138: 4 | K138: 4 | L138: 4 | M138: 5 | N138: 5 | O138: 5 | P138: 3 | Q138: 4 | R138: 4 | S138: 5 | T138: 4 | U138: 4 | V138: 4 | W138: 4 | X138: 4 | Y138: 4 | Z138: 5 | AA138: 4 | AB138: 4 | AC138: 4 | AD138: 5 | AE138: 5 | AF138: 4 | AG138: 4 | AH138: 4 | AI138: 3 | AJ138: 4 | AK138: 4 | AL138: 5 | AM138: 4 | AN138: 4 | AO138: 5 | AP138: 5 | AQ138: 4 | AR138: 4 | AS138: 3 | AT138: 4 | AU138: 2 | AV138: 5 | AW138: 2 | AX138: 2 | AY138: 2 | AZ138: 3
B139: ID138 | C139: 2 | D139: 2 | E139: 3 | F139: 3 | G139: 1 | H139: 2 | I139: 3 | J139: 3 | K139: 2 | L139: 2 | M139: 3 | N139: 2 | O139: 3 | P139: 4 | Q139: 4 | R139: 1 | S139: 4 | T139: 2 | U139: 3 | V139: 3 | W139: 3 | X139: 3 | Y139: 3 | Z139: 4 | AA139: 3 | AB139: 3 | AC139: 3 | AD139: 2 | AE139: 2 | AF139: 5 | AG139: 4 | AH139: 1 | AI139: 4 | AJ139: 3 | AK139: 3 | AL139: 3 | AM139: 4 | AN139: 4 | AO139: 4 | AP139: 3 | AQ139: 3 | AR139: 1 | AS139: 1 | AT139: 2 | AU139: 2 | AV139: 2 | AW139: 4 | AX139: 2 | AY139: 2 | AZ139: 3
B140: ID139 | C140: 5 | D140: 3 | E140: 2 | F140: 3 | G140: 5 | H140: 5 | I140: 5 | J140: 5 | K140: 5 | L140: 4 | M140: 5 | N140: 5 | O140: 5 | P140: 5 | Q140: 5 | R140: 4 | S140: 4 | T140: 4 | U140: 5 | V140: 5 | W140: 5 | X140: 5 | Y140: 4 | Z140: 5 | AA140: 5 | AB140: 4 | AC140: 4 | AD140: 4 | AE140: 5 | AF140: 5 | AG140: 4 | AH140: 4 | AI140: 4 | AJ140: 5 | AK140: 5 | AL140: 4 | AM140: 5 | AN140: 5 | AO140: 5 | AP140: 5 | AQ140: 4 | AR140: 4 | AS140: 4 | AT140: 5 | AU140: 2 | AV140: 2 | AW140: 3 | AX140: 1 | AY140: 1 | AZ140: 5
B141: ID140 | C141: 3 | D141: 3 | E141: 3 | F141: 3 | G141: 3 | H141: 4 | I141: 4 | J141: 4 | K141: 4 | L141: 4 | M141: 4 | N141: 4 | O141: 4 | P141: 3 | Q141: 2 | R141: 4 | S141: 2 | T141: 2 | U141: 4 | V141: 4 | W141: 4 | X141: 4 | Y141: 4 | Z141: 4 | AA141: 5 | AB141: 4 | AC141: 4 | AD141: 3 | AE141: 3 | AF141: 3 | AG141: 4 | AH141: 4 | AI141: 4 | AJ141: 4 | AK141: 4 | AL141: 4 | AM141: 4 | AN141: 3 | AO141: 3 | AP141: 3 | AQ141: 3 | AR141: 3 | AS141: 3 | AT141: 3 | AU141: 2 | AV141: 5 | AW141: 3 | AX141: 1 | AY141: 2 | AZ141: 5
B142: ID141 | C142: 3 | D142: 2 | E142: 3 | F142: 3 | G142: 3 | H142: 4 | I142: 4 | J142: 3 | K142: 4 | L142: 3 | M142: 3 | N142: 5 | O142: 4 | P142: 2 | Q142: 2 | R142: 3 | S142: 2 | T142: 3 | U142: 4 | V142: 3 | W142: 2 | X142: 3 | Y142: 4 | Z142: 4 | AA142: 3 | AB142: 3 | AC142: 3 | AD142: 2 | AE142: 2 | AF142: 3 | AG142: 4 | AH142: 4 | AI142: 4 | AJ142: 3 | AK142: 3 | AL142: 4 | AM142: 3 | AN142: 4 | AO142: 4 | AP142: 3 | AQ142: 4 | AR142: 3 | AS142: 3 | AT142: 2 | AU142: 2 | AV142: 2 | AW142: 2 | AX142: 2 | AY142: 2 | AZ142: 4
B143: ID142 | C143: 3 | D143: 2 | E143: 3 | F143: 3 | G143: 3 | H143: 4 | I143: 4 | J143: 3 | K143: 4 | L143: 3 | M143: 3 | N143: 5 | O143: 4 | P143: 2 | Q143: 2 | R143: 3 | S143: 2 | T143: 3 | U143: 4 | V143: 3 | W143: 2 | X143: 3 | Y143: 4 | Z143: 4 | AA143: 3 | AB143: 3 | AC143: 3 | AD143: 2 | AE143: 2 | AF143: 3 | AG143: 4 | AH143: 4 | AI143: 4 | AJ143: 3 | AK143: 3 | AL143: 4 | AM143: 3 | AN143: 4 | AO143: 4 | AP143: 3 | AQ143: 4 | AR143: 3 | AS143: 3 | AT143: 2 | AU143: 2 | AV143: 5 | AW143: 2 | AX143: 1 | AY143: 2 | AZ143: 4
B144: ID143 | C144: 2 | D144: 2 | E144: 3 | F144: 2 | G144: 1 | H144: 2 | I144: 2 | J144: 3 | K144: 2 | L144: 3 | M144: 2 | N144: 3 | O144: 2 | P144: 4 | Q144: 4 | R144: 2 | S144: 3 | T144: 2 | U144: 2 | V144: 2 | W144: 2 | X144: 2 | Y144: 2 | Z144: 4 | AA144: 2 | AB144: 2 | AC144: 2 | AD144: 2 | AE144: 3 | AF144: 3 | AG144: 3 | AH144: 2 | AI144: 3 | AJ144: 4 | AK144: 2 | AL144: 4 | AM144: 3 | AN144: 4 | AO144: 4 | AP144: 3 | AQ144: 2 | AR144: 2 | AS144: 2 | AT144: 4 | AU144: 1 | AV144: 2 | AW144: 3 | AX144: 2 | AY144: 3 | AZ144: 5

Sheet PCA
A1: Factor Analysis - Principal Component Extraction
B5: 1.Delay in delivering material to construction site | C5: 2.Monopoly of material by some suppliers | D5: 3.Prices fluctuation | E5: 4.Types of material availability at local market | F5: 5.Lack of consultant’s knowledge of available materials | G5: 6.Low productivity | H5: 7.Poor work execution | I5: 8.Shortage of laborers | J5: 9.Mistakes happens during construction phase | K5: 10.Unavailability of equipment | L5: 11.Lack of engineering experience | M5: 12.Construction cost underestimation | N5: 13.Poor site management | O5: 14.Delayed payment for completed work | P5: 15.Cash flow problem during construction | Q5: 16.High rate of interest | R5: 17.Contractor’s financial difficulties | S5: 18.Increase in salaries of skilled laborers | T5: 19.Change design | U5: 20.Errors and omission in design | V5: 21.Incomplete design drawings and specifications at tendering stage | W5: 22.Delay in preparation and approval of drawing | X5: 23.Inaccurate quantity take-off | Y5: 24.Long period from planning of project to construction | Z5: 25.Delays in issuing information to the contractor during construction stage | AA5: 26.No practical use of earned value management system | AB5: 27.Lack of cost planning/monitoring during pre and post contract stage | AC5: 28.Poor communication between client, consultant and contractor | AD5: 29.Insufficient coordination between local authority who is responsible about road projects and service authorities | AE5: 30.Delays in decisions making by the approval authorities | AF5: 31.Change schedule | AG5: 32.Stoppages because of work being rejected by consultant | AH5: 33.Lowest bid price | AI5: 34.Insufficient time for preparation of contract documents | AJ5: 35.Discrepancies in contract documents | AK5: 36.Underestimation of time for completion of project | AL5: 37.Extension of time with cost claims | AM5: 38.Scope and specification changes | AN5: 39.Changes in client requirements | AO5: 40.Frequency of variation orders and additional works | AP5: 41.Rework due to error in execution | AQ5: 42.Weather conditions | AR5: 43.Accidents during construction | AS5: 44.Delay in getting NOCs from different government authorities | AT5: Type of Organization | AU5: Respondents designation | AV5: Indicate the highest formal qualification | AW5: Location of organization | AX5: Relevant working experience
A6: Mean | B6: 3.08 | C6: 2.99 | D6: 2.74 | E6: 2.92 | F6: 2.83 | G6: 3.45 | H6: 3.53 | I6: 3.41 | J6: 3.33 | K6: 3.42 | L6: 3.51 | M6: 3.79 | N6: 3.77 | O6: 3.61 | P6: 3.63 | Q6: 3.17 | R6: 3.58 | S6: 2.76 | T6: 3.81 | U6: 3.47 | V6: 3.52 | W6: 3.62 | X6: 3.64 | Y6: 3.48 | Z6: 3.25 | AA6: 3.06 | AB6: 3.46 | AC6: 3.32 | AD6: 3.55 | AE6: 4.03 | AF6: 3.28 | AG6: 3.1 | AH6: 3.28 | AI6: 3.18 | AJ6: 3.19 | AK6: 3.66 | AL6: 3.65 | AM6: 3.94 | AN6: 4.07 | AO6: 3.91 | AP6: 3.56 | AQ6: 2.49 | AR6: 2.7 | AS6: 3.66 | AT6: 1.94 | AU6: 3.19 | AV6: 2.38 | AW6: 2.15 | AX6: 4.05
A7: Std dev | B7: 1.261996 | C7: 1.334781 | D7: 1.117803 | E7: 1.058144 | F7: 1.255893 | G7: 1.092402 | H7: 1.191544 | I7: 1.114803 | J7: 1.208982 | K7: 1.171328 | L7: 1.18004 | M7: 1.203593 | N7: 1.220092 | O7: 0.993181 | P7: 1.123866 | Q7: 1.227536 | R7: 1.1653 | S7: 1.095553 | T7: 1.00634 | U7: 1.143285 | V7: 1.073714 | W7: 0.991543 | X7: 0.996794 | Y7: 0.998965 | Z7: 1.010289 | AA7: 0.984215 | AB7: 0.976983 | AC7: 1.236769 | AD7: 1.066304 | AE7: 0.934051 | AF7: 1.030558 | AG7: 1.09874 | AH7: 1.22252 | AI7: 1.142251 | AJ7: 1.047808 | AK7: 0.992536 | AL7: 0.994766 | AM7: 0.902081 | AN7: 0.954237 | AO7: 0.910882 | AP7: 1.03884 | AQ7: 1.026872 | AR7: 1.132335 | AS7: 1.100218 | AT7: 0.752618 | AU7: 1.31058 | AV7: 0.580469 | AW7: 0.824858 | AX7: 1.121673
A8: Skewness | B8: -0.35981 | C8: 0.012937 | D8: -0.17796 | E8: -0.19224 | F8: -0.08853 | G8: -0.72048 | H8: -0.77222 | I8: -0.60971 | J8: -0.5607 | K8: -0.55018 | L8: -0.76867 | M8: -0.84061 | N8: -0.96303 | O8: -0.41448 | P8: -0.70587 | Q8: -0.23326 | R8: -0.72541 | S8: 0.175116 | T8: -0.72531 | U8: -0.56682 | V8: -0.46137 | W8: -0.45528 | X8: -0.64329 | Y8: -0.18765 | Z8: -0.15061 | AA8: -0.1132 | AB8: -0.44213 | AC8: -0.47709 | AD8: -0.45599 | AE8: -0.79229 | AF8: -0.35032 | AG8: -0.30751 | AH8: -0.2018 | AI8: -0.04753 | AJ8: -0.0886 | AK8: -0.72844 | AL8: -0.55498 | AM8: -0.82294 | AN8: -0.733 | AO8: -0.4986 | AP8: -0.52387 | AQ8: 0.285851 | AR8: 0.497504 | AS8: -0.68377 | AT8: 0.104247 | AU8: 0.25345 | AV8: 0.571734 | AW8: -0.29413 | AX8: -1.25133
A9: Kurtosis | B9: -1.08886 | C9: -1.14576 | D9: -0.71607 | E9: -0.40074 | F9: -1.02825 | G9: -0.18631 | H9: -0.2154 | I9: -0.10683 | J9: -0.57079 | K9: -0.34221 | L9: -0.19563 | M9: -0.13374 | N9: 0.028493 | O9: -0.15998 | P9: -0.20726 | Q9: -0.86994 | R9: -0.3229 | S9: -0.59223 | T9: 0.025995 | U9: -0.55378 | V9: -0.5538 | W9: -0.48209 | X9: 0.327286 | Y9: -0.52799 | Z9: -0.43982 | AA9: -0.09886 | AB9: -0.28377 | AC9: -0.70887 | AD9: -0.47317 | AE9: 0.308968 | AF9: -0.36556 | AG9: -0.73755 | AH9: -0.92286 | AI9: -0.87091 | AJ9: -0.75921 | AK9: 0.279245 | AL9: -0.05006 | AM9: 0.384649 | AN9: -0.44941 | AO9: -0.26897 | AP9: -0.13618 | AQ9: -0.4768 | AR9: -0.48746 | AS9: -0.14256 | AT9: -1.21779 | AU9: -1.47001 | AV9: -0.00278 | AW9: -1.47084 | AX9: 0.986304
A11: Correlation Matrix
B13: 1.Delay in delivering material to construction site | C13: 2.Monopoly of material by some suppliers | D13: 3.Prices fluctuation | E13: 4.Types of material availability at local market | F13: 5.Lack of consultant’s knowledge of available materials | G13: 6.Low productivity | H13: 7.Poor work execution | I13: 8.Shortage of laborers | J13: 9.Mistakes happens during construction phase | K13: 10.Unavailability of equipment | L13: 11.Lack of engineering experience | M13: 12.Construction cost underestimation | N13: 13.Poor site management | O13: 14.Delayed payment for completed work | P13: 15.Cash flow problem during construction | Q13: 16.High rate of interest | R13: 17.Contractor’s financial difficulties | S13: 18.Increase in salaries of skilled laborers | T13: 19.Change design | U13: 20.Errors and omission in design | V13: 21.Incomplete design drawings and specifications at tendering stage | W13: 22.Delay in preparation and approval of drawing | X13: 23.Inaccurate quantity take-off | Y13: 24.Long period from planning of project to construction | Z13: 25.Delays in issuing information to the contractor during construction stage | AA13: 26.No practical use of earned value management system | AB13: 27.Lack of cost planning/monitoring during pre and post contract stage | AC13: 28.Poor communication between client, consultant and contractor | AD13: 29.Insufficient coordination between local authority who is responsible about road projects and service authorities | AE13: 30.Delays in decisions making by the approval authorities | AF13: 31.Change schedule | AG13: 32.Stoppages because of work being rejected by consultant | AH13: 33.Lowest bid price | AI13: 34.Insufficient time for preparation of contract documents | AJ13: 35.Discrepancies in contract documents | AK13: 36.Underestimation of time for completion of project | AL13: 37.Extension of time with cost claims | AM13: 38.Scope and specification changes | AN13: 39.Changes in client requirements | AO13: 40.Frequency of variation orders and additional works | AP13: 41.Rework due to error in execution | AQ13: 42.Weather conditions | AR13: 43.Accidents during construction | AS13: 44.Delay in getting NOCs from different government authorities | AT13: Type of Organization | AU13: Respondents designation | AV13: Indicate the highest formal qualification | AW13: Location of organization | AX13: Relevant working experience
A14: 1.Delay in delivering material to construction site | B14: 1 | C14: 0.617447 | D14: 0.213695 | E14: 0.673332 | F14: 0.374378 | G14: 0.484591 | H14: 0.538329 | I14: 0.547602 | J14: 0.402341 | K14: 0.470701 | L14: 0.436309 | M14: 0.308012 | N14: 0.276926 | O14: 0.125762 | P14: 0.184925 | Q14: 0.058699 | R14: 0.086557 | S14: 0.243634 | T14: 0.15312 | U14: 0.074863 | V14: 0.029097 | W14: 0.088645 | X14: -0.13842 | Y14: -0.07117 | Z14: 0.263414 | AA14: 0.150097 | AB14: 0.273813 | AC14: 0.324388 | AD14: 0.186236 | AE14: 0.106013 | AF14: 0.022708 | AG14: 0.367218 | AH14: 0.400073 | AI14: 0.240698 | AJ14: 0.287874 | AK14: 0.313114 | AL14: 0.323179 | AM14: 0.103723 | AN14: 0.181608 | AO14: 0.159553 | AP14: 0.261497 | AQ14: 0.344058 | AR14: 0.42143 | AS14: 0.340472 | AT14: 0.164655 | AU14: 0.01621 | AV14: 0.120672 | AW14: -0.065 | AX14: -0.15217
A15: 2.Monopoly of material by some suppliers | B15: 0.617447 | C15: 1 | D15: 0.334336 | E15: 0.558668 | F15: 0.426873 | G15: 0.343882 | H15: 0.384931 | I15: 0.393506 | J15: 0.314199 | K15: 0.362904 | L15: 0.427641 | M15: 0.197617 | N15: 0.297861 | O15: 0.101421 | P15: 0.199332 | Q15: 0.146866 | R15: 0.147563 | S15: 0.084895 | T15: 0.303899 | U15: 0.221947 | V15: 0.044296 | W15: -0.04365 | X15: 0.015877 | Y15: -0.05185 | Z15: 0.231034 | AA15: -0.0423 | AB15: 0.209817 | AC15: 0.180847 | AD15: 0.073655 | AE15: -0.1077 | AF15: -0.07324 | AG15: 0.307204 | AH15: 0.300923 | AI15: 0.17474 | AJ15: 0.148534 | AK15: 0.322445 | AL15: 0.317957 | AM15: -0.13152 | AN15: 0.10813 | AO15: 0.033642 | AP15: 0.179366 | AQ15: 0.335591 | AR15: 0.421812 | AS15: 0.350091 | AT15: 0.077743 | AU15: -0.00134 | AV15: 0.122298 | AW15: 0.154389 | AX15: -0.18119
A16: 3.Prices fluctuation | B16: 0.213695 | C16: 0.334336 | D16: 1 | E16: 0.511606 | F16: 0.39448 | G16: 0.34846 | H16: 0.413956 | I16: 0.279592 | J16: 0.400803 | K16: 0.230993 | L16: 0.382316 | M16: 0.358718 | N16: 0.36283 | O16: -0.0595 | P16: 0.002948 | Q16: 0.061672 | R16: 0.004653 | S16: 0.267269 | T16: 0.265123 | U16: 0.089193 | V16: 0.131057 | W16: 0.023002 | X16: 0.045399 | Y16: 0.108239 | Z16: 0.039962 | AA16: 0.25724 | AB16: 0.18405 | AC16: 0.180387 | AD16: 0.076737 | AE16: -0.11429 | AF16: 0.051891 | AG16: 0.14818 | AH16: 0.174717 | AI16: 0.110398 | AJ16: 0.061732 | AK16: 0.251131 | AL16: 0.088153 | AM16: 0.144634 | AN16: 0.205128 | AO16: -0.0201 | AP16: 0.223326 | AQ16: 0.109573 | AR16: 0.178412 | AS16: -0.00079 | AT16: 0.105309 | AU16: 0.264537 | AV16: -0.02573 | AW16: 0.235288 | AX16: -0.25457
A17: 4.Types of material availability at local market | B17: 0.673332 | C17: 0.558668 | D17: 0.511606 | E17: 1 | F17: 0.55855 | G17: 0.527909 | H17: 0.625926 | I17: 0.531127 | J17: 0.392543 | K17: 0.462761 | L17: 0.515672 | M17: 0.360599 | N17: 0.448709 | O17: 0.099347 | P17: 0.17308 | Q17: 0.147487 | R17: 0.134703 | S17: 0.263145 | T17: 0.212299 | U17: 0.153376 | V17: 0.110675 | W17: 0.035865 | X17: 0.063933 | Y17: -0.02161 | Z17: 0.30702 | AA17: 0.269866 | AB17: 0.390218 | AC17: 0.374996 | AD17: 0.146989 | AE17: 0.160056 | AF17: 0.153899 | AG17: 0.404253 | AH17: 0.415851 | AI17: 0.303602 | AJ17: 0.278869 | AK17: 0.341506 | AL17: 0.248039 | AM17: 0.120219 | AN17: 0.231206 | AO17: 0.024896 | AP17: 0.312467 | AQ17: 0.389342 | AR17: 0.430293 | AS17: 0.222421 | AT17: 0.235994 | AU17: 0.04087 | AV17: 0.06802 | AW17: 0.05624 | AX17: -0.15982
A18: 5.Lack of consultant’s knowledge of available materials | B18: 0.374378 | C18: 0.426873 | D18: 0.39448 | E18: 0.55855 | F18: 1 | G18: 0.426822 | H18: 0.516328 | I18: 0.421754 | J18: 0.550363 | K18: 0.394762 | L18: 0.497702 | M18: 0.490624 | N18: 0.553822 | O18: 0.163971 | P18: 0.177539 | Q18: 0.433905 | R18: 0.051387 | S18: 0.355682 | T18: 0.467038 | U18: 0.437446 | V18: 0.410275 | W18: 0.285149 | X18: 0.348235 | Y18: 0.042098 | Z18: 0.426336 | AA18: 0.454197 | AB18: 0.45199 | AC18: 0.434222 | AD18: 0.228668 | AE18: 0.088695 | AF18: 0.235763 | AG18: 0.500686 | AH18: 0.357036 | AI18: 0.414392 | AJ18: 0.402695 | AK18: 0.2871 | AL18: 0.274633 | AM18: 0.227963 | AN18: 0.335344 | AO18: 0.188694 | AP18: 0.315329 | AQ18: 0.410886 | AR18: 0.380858 | AS18: 0.2323 | AT18: 0.153973 | AU18: -0.02774 | AV18: -0.00751 | AW18: 0.03796 | AX18: -0.18844
A19: 6.Low productivity | B19: 0.484591 | C19: 0.343882 | D19: 0.34846 | E19: 0.527909 | F19: 0.426822 | G19: 1 | H19: 0.82122 | I19: 0.724846 | J19: 0.702263 | K19: 0.546242 | L19: 0.65229 | M19: 0.660151 | N19: 0.675342 | O19: 0.08175 | P19: 0.098779 | Q19: 0.233492 | R19: 0.043609 | S19: 0.211196 | T19: 0.373471 | U19: 0.18297 | V19: 0.094957 | W19: 0.099699 | X19: 0.07354 | Y19: -0.05932 | Z19: 0.403001 | AA19: 0.258229 | AB19: 0.444134 | AC19: 0.370043 | AD19: 0.382941 | AE19: 0.111805 | AF19: 0.093861 | AG19: 0.327582 | AH19: 0.161801 | AI19: 0.359979 | AJ19: 0.366204 | AK19: 0.456326 | AL19: 0.167462 | AM19: 0.203022 | AN19: 0.242078 | AO19: 0.170312 | AP19: 0.374298 | AQ19: 0.281705 | AR19: 0.233685 | AS19: 0.217358 | AT19: 0.303712 | AU19: 0.053072 | AV19: -0.04144 | AW19: -0.1268 | AX19: 0.093833
A20: 7.Poor work execution | B20: 0.538329 | C20: 0.384931 | D20: 0.413956 | E20: 0.625926 | F20: 0.516328 | G20: 0.82122 | H20: 1 | I20: 0.606889 | J20: 0.681291 | K20: 0.54631 | L20: 0.67464 | M20: 0.594184 | N20: 0.692462 | O20: 0.199402 | P20: 0.18836 | Q20: 0.266013 | R20: 0.134551 | S20: 0.221247 | T20: 0.424654 | U20: 0.231783 | V20: 0.154811 | W20: 0.187002 | X20: 0.086875 | Y20: 0.029888 | Z20: 0.424424 | AA20: 0.324708 | AB20: 0.536029 | AC20: 0.458468 | AD20: 0.36675 | AE20: 0.265599 | AF20: 0.112323 | AG20: 0.428292 | AH20: 0.327125 | AI20: 0.38895 | AJ20: 0.463202 | AK20: 0.483567 | AL20: 0.192141 | AM20: 0.231245 | AN20: 0.346915 | AO20: 0.166011 | AP20: 0.482768 | AQ20: 0.306286 | AR20: 0.300448 | AS20: 0.332622 | AT20: 0.327317 | AU20: 0.091612 | AV20: 0.001858 | AW20: -0.08863 | AX20: -0.02331
A21: 8.Shortage of laborers | B21: 0.547602 | C21: 0.393506 | D21: 0.279592 | E21: 0.531127 | F21: 0.421754 | G21: 0.724846 | H21: 0.606889 | I21: 1 | J21: 0.637295 | K21: 0.692857 | L21: 0.610079 | M21: 0.660787 | N21: 0.543651 | O21: 0.24175 | P21: 0.160673 | Q21: 0.254432 | R21: 0.074707 | S21: 0.366163 | T21: 0.343841 | U21: 0.20507 | V21: 0.092432 | W21: 0.119919 | X21: -0.05228 | Y21: -0.0863 | Z21: 0.355575 | AA21: 0.332783 | AB21: 0.318246 | AC21: 0.435951 | AD21: 0.309141 | AE21: 0.15158 | AF21: 0.264405 | AG21: 0.290272 | AH21: 0.314764 | AI21: 0.428882 | AJ21: 0.331026 | AK21: 0.245979 | AL21: 0.198476 | AM21: 0.259149 | AN21: 0.272815 | AO21: 0.196012 | AP21: 0.19772 | AQ21: 0.359866 | AR21: 0.31944 | AS21: 0.331813 | AT21: 0.250174 | AU21: -0.15073 | AV21: 0.132628 | AW21: -0.12448 | AX21: 0.058905
A22: 9.Mistakes happens during construction phase | B22: 0.402341 | C22: 0.314199 | D22: 0.400803 | E22: 0.392543 | F22: 0.550363 | G22: 0.702263 | H22: 0.681291 | I22: 0.637295 | J22: 1 | K22: 0.602859 | L22: 0.640484 | M22: 0.716775 | N22: 0.57909 | O22: -0.06243 | P22: 0.05619 | Q22: 0.30667 | R22: -0.10843 | S22: 0.238233 | T22: 0.463957 | U22: 0.354787 | V22: 0.182947 | W22: 0.175382 | X22: 0.260035 | Y22: 0.04027 | Z22: 0.337708 | AA22: 0.380576 | AB22: 0.475915 | AC22: 0.486931 | AD22: 0.362106 | AE22: 0.041629 | AF22: 0.166739 | AG22: 0.389531 | AH22: 0.217027 | AI22: 0.38808 | AJ22: 0.440433 | AK22: 0.510131 | AL22: 0.101647 | AM22: 0.173653 | AN22: 0.276445 | AO22: 0.244472 | AP22: 0.358397 | AQ22: 0.346162 | AR22: 0.320782 | AS22: 0.107286 | AT22: 0.125707 | AU22: 0.072288 | AV22: 0.05749 | AW22: -0.03594 | AX22: -0.10373
A23: 10.Unavailability of equipment | B23: 0.470701 | C23: 0.362904 | D23: 0.230993 | E23: 0.462761 | F23: 0.394762 | G23: 0.546242 | H23: 0.54631 | I23: 0.692857 | J23: 0.602859 | K23: 1 | L23: 0.534699 | M23: 0.592702 | N23: 0.392132 | O23: 0.240034 | P23: 0.362282 | Q23: 0.338058 | R23: 0.334682 | S23: 0.329406 | T23: 0.201274 | U23: 0.231534 | V23: 0.19579 | W23: 0.196954 | X23: 0.135718 | Y23: -0.09845 | Z23: 0.278545 | AA23: 0.355037 | AB23: 0.526397 | AC23: 0.641276 | AD23: 0.418262 | AE23: 0.066973 | AF23: 0.263137 | AG23: 0.326977 | AH23: 0.329632 | AI23: 0.398407 | AJ23: 0.35683 | AK23: 0.255843 | AL23: 0.242508 | AM23: 0.248417 | AN23: 0.36385 | AO23: 0.263656 | AP23: 0.258042 | AQ23: 0.394698 | AR23: 0.264021 | AS23: 0.369401 | AT23: 0.157806 | AU23: -0.04228 | AV23: 0.154881 | AW23: -0.15021 | AX23: -0.07452
A24: 11.Lack of engineering experience | B24: 0.436309 | C24: 0.427641 | D24: 0.382316 | E24: 0.515672 | F24: 0.497702 | G24: 0.65229 | H24: 0.67464 | I24: 0.610079 | J24: 0.640484 | K24: 0.534699 | L24: 1 | M24: 0.673701 | N24: 0.742574 | O24: 0.15664 | P24: 0.231625 | Q24: 0.39417 | R24: 0.170229 | S24: 0.224811 | T24: 0.367693 | U24: 0.292584 | V24: 0.274944 | W24: -0.0177 | X24: 0.109076 | Y24: 0.129685 | Z24: 0.366931 | AA24: 0.309221 | AB24: 0.457121 | AC24: 0.50896 | AD24: 0.334607 | AE24: 0.159702 | AF24: 0.073713 | AG24: 0.260559 | AH24: 0.187557 | AI24: 0.442714 | AJ24: 0.486403 | AK24: 0.426793 | AL24: 0.192961 | AM24: 0.017981 | AN24: 0.209146 | AO24: 0.124185 | AP24: 0.466641 | AQ24: 0.383385 | AR24: 0.435719 | AS24: 0.23868 | AT24: 0.358892 | AU24: -0.03318 | AV24: -0.00639 | AW24: -0.10328 | AX24: 0.004912
A25: 12.Construction cost underestimation | B25: 0.308012 | C25: 0.197617 | D25: 0.358718 | E25: 0.360599 | F25: 0.490624 | G25: 0.660151 | H25: 0.594184 | I25: 0.660787 | J25: 0.716775 | K25: 0.592702 | L25: 0.673701 | M25: 1 | N25: 0.708867 | O25: 0.007546 | P25: 0.051844 | Q25: 0.37198 | R25: 0.010037 | S25: 0.304953 | T25: 0.439861 | U25: 0.249239 | V25: 0.302513 | W25: 0.224564 | X25: 0.195931 | Y25: 0.089976 | Z25: 0.301563 | AA25: 0.385961 | AB25: 0.439367 | AC25: 0.446511 | AD25: 0.331241 | AE25: 0.086707 | AF25: 0.208261 | AG25: 0.304288 | AH25: 0.229953 | AI25: 0.461196 | AJ25: 0.434186 | AK25: 0.411536 | AL25: 0.065903 | AM25: 0.369358 | AN25: 0.420076 | AO25: 0.276308 | AP25: 0.392301 | AQ25: 0.404163 | AR25: 0.433821 | AS25: 0.187331 | AT25: 0.471876 | AU25: 0.049303 | AV25: -0.10733 | AW25: -0.17828 | AX25: -0.03834
... A62: Relevant working experience | B62: -0.15217 | C62: -0.18119 | D62: -0.25457 | E62: -0.15982 | F62: -0.18844 | G62: 0.093833 | H62: -0.02331 | I62: 0.058905 | J62: -0.10373 | K62: -0.07452 | L62: 0.004912 | M62: -0.03834 | N62: 0.025722 | O62: 0.139253 | P62: -0.04215 | Q62: 0.075759 | R62: -0.0008 | S62: -0.05223 | T62: -0.02685 | U62: -0.10233 | V62: -0.10469 | W62: -0.10628 | X62: -0.12527 | Y62: -0.0794 | Z62: 0.031313 | AA62: -0.05293 | AB62: -0.1027 | AC62: -0.09904 | AD62: -0.04329 | AE62: -0.00079 | AF62: -0.01927 | AG62: -0.03121 | AH62: -0.21396 | AI62: 0.018106 | AJ62: 0.025474 | AK62: -0.06804 | AL62: -0.0748 | AM62: -0.1039 | AN62: -0.12221 | AO62: -0.07477 | AP62: -0.04059 | AQ62: -0.07443 | AR62: -0.22453 | AS62: -0.02073 | AT62: 0.06253 | AU62: -0.15101 | AV62: -0.0608 | AW62: -0.0357 | AX62: 1
B63: 4.348136 | C63: 3.348638 | D63: 2.408941 | E63: 5.351358 | F63: 6.323809 | G63: 6.498887 | H63: 7.656115 | I63: 6.335523 | J63: 6.771228 | K63: 6.268386 | L63: 7.033637 | M63: 7.071475 | N63: 6.614025 | O63: 2.699432 | P63: 3.585379 | Q63: 4.650366 | R63: 2.377934 | S63: 2.341553 | T63: 4.614693 | U63: 4.367207 | V63: 4.209673 | W63: 3.257338 | X63: 2.995288 | Y63: 0.940022 | Z63: 5.248997 | AA63: 4.993856 | AB63: 6.992916 | AC63: 6.152999 | AD63: 3.334434 | AE63: 2.206347 | AF63: 3.144117 | AG63: 4.620773 | AH63: 2.318871 | AI63: 5.819961 | AJ63: 5.46097 | AK63: 3.410198 | AL63: 2.259934 | AM63: 2.684595 | AN63: 3.352684 | AO63: 2.421389 | AP63: 3.6199 | AQ63: 5.095181 | AR63: 3.510625 | AS63: 3.222256 | AT63: 1.860852 | AU63: 0.682553 | AV63: 0.651404 | AW63: 0.892986 | AX63: 0.503585 | AY63: 196.5314
A65: Inverse of Correlation Matrix
B67: 1.Delay in delivering material to construction site | C67: 2.Monopoly of material by some suppliers | D67: 3.Prices fluctuation | E67: 4.Types of material availability at local market | F67: 5.Lack of consultant’s knowledge of available materials | G67: 6.Low productivity | H67: 7.Poor work execution | I67: 8.Shortage of laborers | J67: 9.Mistakes happens during construction phase | K67: 10.Unavailability of equipment | L67: 11.Lack of engineering experience | M67: 12.Construction cost underestimation | N67: 13.Poor site management | O67: 14.Delayed payment for completed work | P67: 15.Cash flow problem during construction | Q67: 16.High rate of interest | R67: 17.Contractor’s financial difficulties | S67: 18.Increase in salaries of skilled laborers | T67: 19.Change design | U67: 20.Errors and omission in design | V67: 21.Incomplete design drawings and specifications at tendering stage | W67: 22.Delay in preparation and approval of drawing | X67: 23.Inaccurate quantity take-off | Y67: 24.Long period from planning of project to construction | Z67: 25.Delays in issuing information to the contractor during construction stage | AA67: 26.No practical use of earned value management system | AB67: 27.Lack of cost planning/monitoring during pre and post contract stage | AC67: 28.Poor communication between client, consultant and contractor | AD67: 29.Insufficient coordination between local authority who is responsible about road projects and service authorities | AE67: 30.Delays in decisions making by the approval authorities | AF67: 31.Change schedule | AG67: 32.Stoppages because of work being rejected by consultant | AH67: 33.Lowest bid price | AI67: 34.Insufficient time for preparation of contract documents | AJ67: 35.Discrepancies in contract documents | AK67: 36.Underestimation of time for completion of project | AL67: 37.Extension of time with cost claims | AM67: 38.Scope and specification changes | AN67: 39.Changes in client requirements | AO67: 40.Frequency of variation orders and additional works | AP67: 41.Rework due to error in execution | AQ67: 42.Weather conditions | AR67: 43.Accidents during construction | AS67: 44.Delay in getting NOCs from different government authorities | AT67: Type of Organization | AU67: Respondents designation | AV67: Indicate the highest formal qualification | AW67: Location of organization | AX67: Relevant working experience
A68: 1.Delay in delivering material to construction site | B68: 5.647436 | C68: -2.67101 | D68: 1.477082 | E68: -1.75628 | F68: 0.720041 | G68: -1.16537 | H68: -0.41371 | I68: -0.31166 | J68: -1.63936 | K68: 0.52553 | L68: 0.240862 | M68: -1.31463 | N68: 1.694348 | O68: -0.17047 | P68: -1.00669 | Q68: 1.117167 | R68: 0.346376 | S68: -1.33589 | T68: 2.051066 | U68: 0.839972 | V68: -2.30245 | W68: 0.139233 | X68: 1.630809 | Y68: -0.18196 | Z68: -1.28393 | AA68: -0.60186 | AB68: 1.149882 | AC68: 0.064336 | AD68: 1.236751 | AE68: -0.62704 | AF68: 0.507504 | AG68: -0.50453 | AH68: -0.75937 | AI68: 1.459292 | AJ68: -1.97582 | AK68: 0.06686 | AL68: -0.52619 | AM68: 0.013363 | AN68: -0.01518 | AO68: -0.03696 | AP68: -0.48103 | AQ68: -0.51786 | AR68: 0.16314 | AS68: -0.04094 | AT68: 0.950375 | AU68: -0.7585 | AV68: 0.432416 | AW68: -0.01999 | AX68: 0.262861
A69: 2.Monopoly of material by some suppliers | B69: -2.67101 | C69: 5.899128 | D69: -1.0356 | E69: 0.093889 | F69: -1.36934 | G69: 1.409301 | H69: 0.282901 | I69: -1.91285 | J69: 1.352574 | K69: -0.17303 | L69: -0.94056 | M69: 3.095467 | N69: -1.04702 | O69: 1.59073 | P69: -0.60091 | Q69: -1.01967 | R69: -0.55797 | S69: 1.130508 | T69: -2.61518 | U69: -0.51872 | V69: 2.361373 | W69: -0.5996 | X69: -0.49339 | Y69: 0.256772 | Z69: 0.663733 | AA69: 1.124378 | AB69: -1.3285 | AC69: 0.503196 | AD69: -1.52593 | AE69: 2.158703 | AF69: -0.39774 | AG69: 0.225767 | AH69: 0.130892 | AI69: -0.10899 | AJ69: 2.054048 | AK69: -0.97483 | AL69: -0.09893 | AM69: 1.47633 | AN69: -0.99198 | AO69: -0.80754 | AP69: 0.181869 | AQ69: -0.0311 | AR69: -0.98345 | AS69: -0.75579 | AT69: -1.79622 | AU69: 0.476255 | AV69: -0.53644 | AW69: -0.23628 | AX69: 0.002804
A70: 3.Prices fluctuation | B70: 1.477082 | C70: -1.0356 | D70: 3.682232 | E70: -1.71427 | F70: 0.20592 | G70: -0.33351 | H70: -0.70129 | I70: 0.881674 | J70: -1.72162 | K70: 0.895146 | L70: -0.38904 | M70: -0.83438 | N70: -0.15421 | O70: 0.10347 | P70: -0.26655 | Q70: 0.380774 | R70: -0.29407 | S70: -0.44759 | T70: 0.641891 | U70: 0.125087 | V70: -0.93466 | W70: 0.131403 | X70: 0.833357 | Y70: -0.32367 | Z70: 0.52971 | AA70: -1.24702 | AB70: 1.095042 | AC70: 0.077556 | AD70: -0.02245 | AE70: 0.621948 | AF70: -0.33348 | AG70: 0.658458 | AH70: -0.62497 | AI70: -0.12854 | AJ70: 0.75711 | AK70: 0.275972 | AL70: -0.5019 | AM70: -0.59083 | AN70: 0.246151 | AO70: 0.519412 | AP70: -0.1676 | AQ70: -0.49851 | AR70: 0.579415 | AS70: -0.43139 | AT70: 0.250616 | AU70: -1.06997 | AV70: -0.16905 | AW70: -0.79878 | AX70: 0.261608
A71: 4.Types of material availability at local market | B71: -1.75628 | C71: 0.093889 | D71: -1.71427 | E71: 5.715597 | F71: -1.8185 | G71: -0.50317 | H71: -1.74368 | I71: -1.72523 | J71: 3.643406 | K71: -0.96095 | L71: -0.25759 | M71: 1.323138 | N71: 0.094894 | O71: 1.114553 | P71: -1.34562 | Q71: 0.399607 | R71: 1.121598 | S71: 0.011052 | T71: -0.42749 | U71: 0.712066 | V71: 0.241798 | W71: 0.325562 | X71: -1.14101 | Y71: -0.04348 | Z71: 0.412238 | AA71: 0.381628 | AB71: -0.67508 | AC71: -0.97044 | AD71: 0.742902 | AE71: -0.76691 | AF71: -0.39537 | AG71: 0.188135 | AH71: -0.49383 | AI71: 0.341102 | AJ71: 0.099448 | AK71: -1.09183 | AL71: 0.445062 | AM71: 0.309512 | AN71: 0.064072 | AO71: -0.33739 | AP71: 0.401603 | AQ71: -0.52014 | AR71: -0.65303 | AS71: 1.106821 | AT71: -0.36966 | AU71: 0.130188 | AV71: -0.28392 | AW71: -0.28419 | AX71: -0.31729
A72: 5.Lack of consultant’s knowledge of available materials | B72: 0.720041 | C72: -1.36934 | D72: 0.20592 | E72: -1.8185 | F72: 5.766082 | G72: -0.69744 | H72: 1.712937 | I72: 1.631987 | J72: -2.70322 | K72: 0.67808 | L72: 1.04383 | M72: -0.80378 | N72: -2.30218 | O72: -2.12624 | P72: 1.628767 | Q72: -0.18824 | R72: 0.326725 | S72: -0.89928 | T72: 0.941481 | U72: -0.17346 | V72: -1.43203 | W72: 0.214721 | X72: -0.29448 | Y72: 0.498635 | Z72: -0.93691 | AA72: -1.22075 | AB72: 1.014716 | AC72: -0.79189 | AD72: 0.704704 | AE72: 0.243813 | AF72: 2.06524 | AG72: -1.55656 | AH72: -0.83019 | AI72: 0.227065 | AJ72: -1.72519 | AK72: 1.538451 | AL72: -0.95426 | AM72: -0.29833 | AN72: -1.19592 | AO72: 1.828248 | AP72: -0.08951 | AQ72: -0.59064 | AR72: 0.989397 | AS72: -0.13378 | AT72: 1.035443 | AU72: 0.665108 | AV72: 0.498894 | AW72: 0.054297 | AX72: 0.835127
A73: 6.Low productivity | B73: -1.16537 | C73: 1.409301 | D73: -0.33351 | E73: -0.50317 | F73: -0.69744 | G73: 8.985356 | H73: -4.34322 | I73: -3.5193 | J73: -0.38764 | K73: 0.383197 | L73: -0.35554 | M73: 0.775473 | N73: -0.49994 | O73: 1.342058 | P73: 0.240716 | Q73: -0.86901 | R73: -0.86978 | S73: 0.27063 | T73: -0.89132 | U73: -0.63832 | V73: 1.27133 | W73: 0.129152 | X73: -0.29495 | Y73: 0.802811 | Z73: -0.00359 | AA73: 1.605502 | AB73: -1.94541 | AC73: 2.092233 | AD73: -2.61693 | AE73: 1.233791 | AF73: -0.75334 | AG73: 0.360004 | AH73: 1.399634 | AI73: -1.29327 | AJ73: 1.975446 | AK73: -0.74575 | AL73: -0.65139 | AM73: -0.25761 | AN73: 1.098501 | AO73: -1.24108 | AP73: 0.418348 | AQ73: 1.036602 | AR73: -0.21013 | AS73: 0.51481 | AT73: -1.42705 | AU73: -0.36933 | AV73: 0.381331 | AW73: 0.619021 | AX73: -0.63518
A74: 7.Poor work execution | B74: -0.41371 | C74: 0.282901 | D74: -0.70129 | E74: -1.74368 | F74: 1.712937 | G74: -4.34322 | H74: 9.815002 | I74: 2.974926 | J74: -3.53326 | K74: -0.89263 | L74: -0.63138 | M74: 1.33726 | N74: -1.59203 | O74: -2.81755 | P74: 2.729005 | Q74: 0.26272 | R74: -0.91794 | S74: 0.864901 | T74: -0.96683 | U74: 0.064079 | V74: 1.108265 | W74: -0.39093 | X74: 0.836058 | Y74: 0.33721 | Z74: -1.16199 | AA74: -1.12577 | AB74: 0.797739 | AC74: -0.4257 | AD74: 0.372693 | AE74: -0.74367 | AF74: 2.073979 | AG74: -2.3397 | AH74: -0.02895 | AI74: -0.55428 | AJ74: -0.62537 | AK74: 1.326819 | AL74: 0.205936 | AM74: -0.25939 | AN74: -2.42245 | AO74: 2.12043 | AP74: -1.33727 | AQ74: -0.58073 | AR74: 0.889806 | AS74: -0.70775 | AT74: -0.11575 | AU74: 0.536418 | AV74: 0.26072 | AW74: 0.577858 | AX74: 0.868215
A75: 8.Shortage of laborers | B75: -0.31166 | C75: -1.91285 | D75: 0.881674 | E75: -1.72523 | F75: 1.631987 | G75: -3.5193 | H75: 2.974926 | I75: 9.42749 | J75: -3.06174 | K75: -2.1964 | L75: -0.4656 | M75: -2.83949 | N75: -1.01301 | O75: -2.60896 | P75: 2.302824 | Q75: 1.564668 | R75: -0.84868 | S75: 0.017329 | T75: -0.53281 | U75: -1.00908 | V75: 1.365456 | W75: 0.091138 | X75: 1.167602 | Y75: 0.155935 | Z75: -0.8906 | AA75: -2.31248 | AB75: 2.455223 | AC75: -0.59138 | AD75: 0.731326 | AE75: -1.22791 | AF75: 0.687739 | AG75: -0.58751 | AH75: 0.42983 | AI75: -2.17214 | AJ75: 0.509295 | AK75: 2.76865 | AL75: -0.45676 | AM75: -1.79198 | AN75: 0.447539 | AO75: 1.795596 | AP75: -0.22095 | AQ75: -0.0353 | AR75: 0.352477 | AS75: -0.15798 | AT75: 1.175609 | AU75: 0.544724 | AV75: -0.15699 | AW75: 0.083305 | AX75: 0.146912
A76: 9.Mistakes happens during construction phase | B76: -1.63936 | C76: 1.352574 | D76: -1.72162 | E76: 3.643406 | F76: -2.70322 | G76: -0.38764 | H76: -3.53326 | I76: -3.06174 | J76: 11.68938 | K76: -2.43824 | L76: -0.58032 | M76: -0.27822 | N76: -0.1799 | O76: 2.635605 | P76: -3.02519 | Q76: -0.46159 | R76: 3.512277 | S76: 0.449685 | T76: -2.31911 | U76: 0.685597 | V76: 1.971696 | W76: -1.37624 | X76: -1.91398 | Y76: -1.07006 | Z76: 2.083658 | AA76: 0.912322 | AB76: -1.6296 | AC76: -1.85488 | AD76: -0.1926 | AE76: -0.03973 | AF76: -0.87244 | AG76: 0.31855 | AH76: 0.535254 | AI76: 1.017788 | AJ76: 0.13402 | AK76: -2.94903 | AL76: 0.802502 | AM76: 1.284074 | AN76: 1.327066 | AO76: -1.9145 | AP76: 1.086275 | AQ76: 1.097464 | AR76: -1.79606 | AS76: 2.061878 | AT76: 0.412083 | AU76: 1.215824 | AV76: -1.50885 | AW76: -0.5311 | AX76: -0.36411
A77: 10.Unavailability of equipment | B77: 0.52553 | C77: -0.17303 | D77: 0.895146 | E77: -0.96095 | F77: 0.67808 | G77: 0.383197 | H77: -0.89263 | I77: -2.1964 | J77: -2.43824 | K77: 7.081276 | L77: -0.37754 | M77: -2.69979 | N77: 1.528933 | O77: 0.073972 | P77: -0.41215 | Q77: -0.39607 | R77: -1.76276 | S77: -0.05795 | T77: 1.935416 | U77: -0.40454 | V77: -0.43721 | W77: 0.710437 | X77: -0.40885 | Y77: 0.815533 | Z77: 0.303768 | AA77: -0.00906 | AB77: -0.91631 | AC77: -0.91019 | AD77: 0.547003 | AE77: 1.21021 | AF77: 0.037556 | AG77: 0.355672 | AH77: -1.27279 | AI77: 1.063095 | AJ77: 0.093874 | AK77: 1.088695 | AL77: -0.44565 | AM77: 0.330836 | AN77: -0.7759 | AO77: -0.35762 | AP77: 0.051877 | AQ77: -1.22261 | AR77: 1.406534 | AS77: -1.4935 | AT77: 0.595652 | AU77: -1.05575 | AV77: -0.15831 | AW77: -0.04912 | AX77: -0.00144
A78: 11.Lack of engineering experience | B78: 0.240862 | C78: -0.94056 | D78: -0.38904 | E78: -0.25759 | F78: 1.04383 | G78: -0.35554 | H78: -0.63138 | I78: -0.4656 | J78: -0.58032 | K78: -0.37754 | L78: 6.864992 | M78: -1.22976 | N78: -2.16364 | O78: -0.92798 | P78: 0.289195 | Q78: -0.41682 | R78: 0.244643 | S78: -0.86035 | T78: 0.712622 | U78: 0.118274 | V78: -2.57599 | W78: 1.169481 | X78: 0.657137 | Y78: -0.50031 | Z78: -0.45574 | AA78: -0.21136 | AB78: 0.508585 | AC78: -0.76654 | AD78: -0.10885 | AE78: 0.016851 | AF78: 0.847491 | AG78: 0.681306 | AH78: -0.55669 | AI78: 1.053028 | AJ78: -1.71845 | AK78: -0.39116 | AL78: 0.050992 | AM78: 1.41047 | AN78: 0.483635 | AO78: 0.247053 | AP78: -0.96653 | AQ78: -0.30106 | AR78: -0.26615 | AS78: 0.760393 | AT78: 0.46567 | AU78: 0.847838 | AV78: -0.07286 | AW78: 0.154062 | AX78: 0.025512
A79: 12.Construction cost underestimation | B79: -1.31463 | C79: 3.095467 | D79: -0.83438 | E79: 1.323138 | F79: -0.80378 | G79: 0.775473 | H79: 1.33726 | I79: -2.83949 | J79: -0.27822 | K79: -2.69979 | L79: -1.22976 | M79: 10.76744 | N79: -2.58504 | O79: 1.720109 | P79: -0.04752 | Q79: -1.34463 | R79: 0.547632 | S79: 0.793047 | T79: -2.72284 | U79: 0.440179 | V79: 0.393219 | W79: -1.03041 | X79: 0.051212 | Y79: -0.1102 | Z79: 0.661964 | AA79: 0.696275 | AB79: -0.40007 | AC79: 1.126765 | AD79: -2.30284 | AE79: 1.832244 | AF79: -0.60697 | AG79: 0.748592 | AH79: -0.39424 | AI79: -0.48312 | AJ79: 1.785809 | AK79: -2.28482 | AL79: 0.979168 | AM79: -0.21403 | AN79: -1.47415 | AO79: 0.477591 | AP79: -0.28557 | AQ79: -0.89704 | AR79: -1.32709 | AS79: 0.178109 | AT79: -3.12516 | AU79: 0.29518 | AV79: 0.639152 | AW79: 0.304944 | AX79: -0.06003
... A116: Relevant working experience | B116: 0.262861 | C116: 0.002804 | D116: 0.261608 | E116: -0.31729 | F116: 0.835127 | G116: -0.63518 | H116: 0.868215 | I116: 0.146912 | J116: -0.36411 | K116: -0.00144 | L116: 0.025512 | M116: -0.06003 | N116: -0.27029 | O116: -1.19864 | P116: 0.743851 | Q116: -0.07021 | R116: 0.090355 | S116: -0.01847 | T116: -0.05637 | U116: 0.374427 | V116: -0.023 | W116: 0.338776 | X116: 0.064877 | Y116: -0.0031 | Z116: -0.36989 | AA116: -0.36146 | AB116: 0.219761 | AC116: 0.032299 | AD116: 0.191367 | AE116: 0.039357 | AF116: 0.741206 | AG116: -0.97279 | AH116: 0.382748 | AI116: -0.13526 | AJ116: -0.58131 | AK116: 0.407205 | AL116: -0.04743 | AM116: 0.254972 | AN116: -0.6695 | AO116: 0.399377 | AP116: -0.06536 | AQ116: -0.48027 | AR116: 0.811174 | AS116: 0.019793 | AT116: -0.07713 | AU116: 0.218084 | AV116: 0.084118 | AW116: -0.03352 | AX116: 1.826698
A118: Partial Correlation Matrix
B120: 1.Delay in delivering material to construction site | C120: 2.Monopoly of material by some suppliers | D120: 3.Prices fluctuation | E120: 4.Types of material availability at local market | F120: 5.Lack of consultant’s knowledge of available materials | G120: 6.Low productivity | H120: 7.Poor work execution | I120: 8.Shortage of laborers | J120: 9.Mistakes happens during construction phase | K120: 10.Unavailability of equipment | L120: 11.Lack of engineering experience | M120: 12.Construction cost underestimation | N120: 13.Poor site management | O120: 14.Delayed payment for completed work | P120: 15.Cash flow problem during construction | Q120: 16.High rate of interest | R120: 17.Contractor’s financial difficulties | S120: 18.Increase in salaries of skilled laborers | T120: 19.Change design | U120: 20.Errors and omission in design | V120: 21.Incomplete design drawings and specifications at tendering stage | W120: 22.Delay in preparation and approval of drawing | X120: 23.Inaccurate quantity take-off | Y120: 24.Long period from planning of project to construction | Z120: 25.Delays in issuing information to the contractor during construction stage | AA120: 26.No practical use of earned value management system | AB120: 27.Lack of cost planning/monitoring during pre and post contract stage | AC120: 28.Poor communication between client, consultant and contractor | AD120: 29.Insufficient coordination between local authority who is responsible about road projects and service authorities | AE120: 30.Delays in decisions making by the approval authorities | AF120: 31.Change schedule | AG120: 32.Stoppages because of work being rejected by consultant | AH120: 33.Lowest bid price | AI120: 34.Insufficient time for preparation of contract documents | AJ120: 35.Discrepancies in contract documents | AK120: 36.Underestimation of time for completion of project | AL120: 37.Extension of time with cost claims | AM120: 38.Scope and specification changes | AN120: 39.Changes in client requirements | AO120: 40.Frequency of variation orders and additional works | AP120: 41.Rework due to error in execution | AQ120: 42.Weather conditions | AR120: 43.Accidents during construction | AS120: 44.Delay in getting NOCs from different government authorities | AT120: Type of Organization | AU120: Respondents designation | AV120: Indicate the highest formal qualification | AW120: Location of organization | AX120: Relevant working experience
A121: 1.Delay in delivering material to construction site | B121: 1 | C121: 0.462761 | D121: -0.32391 | E121: 0.309128 | F121: -0.12618 | G121: 0.163595 | H121: 0.055568 | I121: 0.042712 | J121: 0.201769 | K121: -0.0831 | L121: -0.03868 | M121: 0.168586 | N121: -0.26334 | O121: 0.027151 | P121: 0.155106 | Q121: -0.23527 | R121: -0.06643 | S121: 0.303903 | T121: -0.33442 | U121: -0.15799 | V121: 0.326257 | W121: -0.02923 | X121: -0.331 | Y121: 0.05042 | Z121: 0.253004 | AA121: 0.111505 | AB121: -0.20052 | AC121: -0.01117 | AD121: -0.21877 | AE121: 0.137046 | AF121: -0.10324 | AG121: 0.088717 | AH121: 0.155263 | AI121: -0.21807 | AJ121: 0.292826 | AK121: -0.01201 | AL121: 0.122115 | AM121: -0.00263 | AN121: 0.002779 | AO121: 0.007891 | AP121: 0.111683 | AQ121: 0.079796 | AR121: -0.03151 | AS121: 0.008655 | AT121: -0.21116 | AU121: 0.19971 | AV121: -0.12687 | AW121: 0.005663 | AX121: -0.08184
A122: 2.Monopoly of material by some suppliers | B122: 0.462761 | C122: 1 | D122: 0.222199 | E122: -0.01617 | F122: 0.234789 | G122: -0.19357 | H122: -0.03718 | I122: 0.256501 | J122: -0.16288 | K122: 0.026771 | L122: 0.147799 | M122: -0.3884 | N122: 0.15922 | O122: -0.2479 | P122: 0.090588 | Q122: 0.210103 | R122: 0.104712 | S122: -0.25163 | T122: 0.417199 | U122: 0.095463 | V122: -0.32739 | W122: 0.123179 | X122: 0.097981 | Y122: -0.06962 | Z122: -0.12797 | AA122: -0.20382 | AB122: 0.226673 | AC122: -0.08545 | AD122: 0.264101 | AE122: -0.46163 | AF122: 0.07917 | AG122: -0.03884 | AH122: -0.02619 | AI122: 0.015937 | AJ122: -0.29785 | AK122: 0.171329 | AL122: 0.022464 | AM122: -0.28416 | AN122: 0.177604 | AO122: 0.168685 | AP122: -0.04131 | AQ122: 0.004689 | AR122: 0.185856 | AS122: 0.156318 | AT122: 0.390489 | AU122: -0.12269 | AV122: 0.153991 | AW122: 0.065489 | AX122: -0.00085
A123: 3.Prices fluctuation | B123: -0.32391 | C123: 0.222199 | D123: 1 | E123: 0.373673 | F123: -0.04469 | G123: 0.05798 | H123: 0.116654 | I123: -0.14964 | J123: 0.262414 | K123: -0.1753 | L123: 0.077377 | M123: 0.13251 | N123: 0.029683 | O123: -0.02041 | P123: 0.05086 | Q123: -0.09931 | R123: 0.06985 | S123: 0.126101 | T123: -0.12961 | U123: -0.02914 | V123: 0.164019 | W123: -0.03417 | X123: -0.20947 | Y123: 0.11107 | Z123: -0.12927 | AA123: 0.286116 | AB123: -0.23649 | AC123: -0.01667 | AD123: 0.004918 | AE123: -0.16834 | AF123: 0.084016 | AG123: -0.14339 | AH123: 0.15825 | AI123: 0.023789 | AJ123: -0.13896 | AK123: -0.06139 | AL123: 0.14425 | AM123: 0.143941 | AN123: -0.05578 | AO123: -0.13733 | AP123: 0.048189 | AQ123: 0.095128 | AR123: -0.1386 | AS123: 0.112932 | AT123: -0.06896 | AU123: 0.348887 | AV123: 0.061423 | AW123: 0.280229 | AX123: -0.10087
A124: 4.Types of material availability at local market | B124: 0.309128 | C124: -0.01617 | D124: 0.373673 | E124: 1 | F124: 0.316769 | G124: 0.070213 | H124: 0.232804 | I124: 0.235027 | J124: -0.44574 | K124: 0.151047 | L124: 0.041122 | M124: -0.16866 | N124: -0.01466 | O124: -0.17646 | P124: 0.206087 | Q124: -0.08365 | R124: -0.21384 | S124: -0.0025 | T124: 0.069284 | U124: -0.13313 | V124: -0.03406 | W124: -0.06795 | X124: 0.230201 | Y124: 0.011975 | Z124: -0.08075 | AA124: -0.07028 | AB124: 0.11702 | AC124: 0.167426 | AD124: -0.13063 | AE124: 0.166613 | AF124: 0.079952 | AG124: -0.03288 | AH124: 0.100367 | AI124: -0.05067 | AJ124: -0.01465 | AK124: 0.194948 | AL124: -0.10267 | AM124: -0.06052 | AN124: -0.01165 | AO124: 0.071599 | AP124: -0.09268 | AQ124: 0.079668 | AR124: 0.125378 | AS124: -0.23257 | AT124: 0.081642 | AU124: -0.03407 | AV124: 0.082801 | AW124: 0.080023 | AX124: 0.098195
A125: 5.Lack of consultant’s knowledge of available materials | B125: -0.12618 | C125: 0.234789 | D125: -0.04469 | E125: 0.316769 | F125: 1 | G125: 0.096895 | H125: -0.2277 | I125: -0.22135 | J125: 0.329265 | K125: -0.10612 | L125: -0.16591 | M125: 0.102009 | N125: 0.354106 | O125: 0.335155 | P125: -0.24836 | Q125: 0.039233 | R125: -0.06202 | S125: 0.202463 | T125: -0.15192 | U125: 0.03229 | V125: 0.20082 | W125: -0.04462 | X125: 0.059151 | Y125: -0.13674 | Z125: 0.182712 | AA125: 0.223826 | AB125: -0.17512 | AC125: 0.136022 | AD125: -0.12337 | AE125: -0.05274 | AF125: -0.4158 | AG125: 0.270875 | AH125: 0.167988 | AI125: -0.03358 | AJ125: 0.253038 | AK125: -0.27349 | AL125: 0.219168 | AM125: 0.058081 | AN125: 0.216573 | AO125: -0.38628 | AP125: 0.020566 | AQ125: 0.090068 | AR125: -0.18913 | AS125: 0.027986 | AT125: -0.22768 | AU125: -0.17331 | AV125: -0.14486 | AW125: -0.01522 | AX125: -0.25732
A126: 6.Low productivity | B126: 0.163595 | C126: -0.19357 | D126: 0.05798 | E126: 0.070213 | F126: 0.096895 | G126: 1 | H126: 0.462487 | I126: 0.382376 | J126: 0.037823 | K126: -0.04804 | L126: 0.045269 | M126: -0.07884 | N126: 0.061601 | O126: -0.16946 | P126: -0.0294 | Q126: 0.145085 | R126: 0.132255 | S126: -0.04881 | T126: 0.115212 | U126: 0.095185 | V126: -0.14282 | W126: -0.0215 | X126: 0.04746 | Y126: -0.17636 | Z126: 0.000561 | AA126: -0.23581 | AB126: 0.268953 | AC126: -0.28789 | AD126: 0.366989 | AE126: -0.21378 | AF126: 0.121499 | AG126: -0.05019 | AH126: -0.22688 | AI126: 0.153218 | AJ126: -0.23211 | AK126: 0.106199 | AL126: 0.119847 | AM126: 0.040176 | AN126: -0.15936 | AO126: 0.210056 | AP126: -0.077 | AQ126: -0.12663 | AR126: 0.032177 | AS126: -0.08627 | AT126: 0.251371 | AU126: 0.077092 | AV126: -0.0887 | AW126: -0.13902 | AX126: 0.156782
A127: 7.Poor work execution | B127: 0.055568 | C127: -0.03718 | D127: 0.116654 | E127: 0.232804 | F127: -0.2277 | G127: 0.462487 | H127: 1 | I127: -0.30927 | J127: 0.329864 | K127: 0.107071 | L127: 0.076918 | M127: -0.13008 | N127: 0.187691 | O127: 0.340407 | P127: -0.31895 | Q127: -0.04197 | R127: 0.13355 | S127: -0.14925 | T127: 0.119575 | U127: -0.00914 | V127: -0.11912 | W127: 0.062262 | X127: -0.12872 | Y127: -0.07088 | Z127: 0.173687 | AA127: 0.158209 | AB127: -0.10552 | AC127: 0.056045 | AD127: -0.05001 | AE127: 0.12329 | AF127: -0.32004 | AG127: 0.312075 | AH127: 0.004491 | AI127: 0.062831 | AJ127: 0.070304 | AK127: -0.18078 | AL127: -0.03625 | AM127: 0.038707 | AN127: 0.336244 | AO127: -0.34339 | AP127: 0.235512 | AQ127: 0.067877 | AR127: -0.13037 | AS127: 0.113483 | AT127: 0.019508 | AU127: -0.10713 | AV127: -0.05802 | AW127: -0.12417 | AX127: -0.20504
A128: 8.Shortage of laborers | B128: 0.042712 | C128: 0.256501 | D128: -0.14964 | E128: 0.235027 | F128: -0.22135 | G128: 0.382376 | H128: -0.30927 | I128: 1 | J128: 0.291659 | K128: 0.268817 | L128: 0.057875 | M128: 0.281829 | N128: 0.121857 | O128: 0.32162 | P128: -0.27461 | Q128: -0.25503 | R128: 0.125986 | S128: -0.00305 | T128: 0.067237 | U128: 0.146901 | V128: -0.14975 | W128: -0.01481 | X128: -0.18342 | Y128: -0.03344 | Z128: 0.13583 | AA128: 0.331593 | AB128: -0.33138 | AC128: 0.079443 | AD128: -0.10012 | AE128: 0.207713 | AF128: -0.10829 | AG128: 0.079958 | AH128: -0.06802 | AI128: 0.251234 | AJ128: -0.05842 | AK128: -0.38491 | AL128: 0.082042 | AM128: 0.272845 | AN128: -0.06338 | AO128: -0.2967 | AP128: 0.039704 | AQ128: 0.00421 | AR128: -0.05269 | AS128: 0.025846 | AT128: -0.20217 | AU128: -0.11101 | AV128: 0.035648 | AW128: -0.01826 | AX128: -0.0354
A129: 9.Mistakes happens during construction phase | B129: 0.201769 | C129: -0.16288 | D129: 0.262414 | E129: -0.44574 | F129: 0.329265 | G129: 0.037823 | H129: 0.329864 | I129: 0.291659 | J129: 1 | K129: 0.267994 | L129: 0.064782 | M129: 0.024799 | N129: 0.019434 | O129: -0.29178 | P129: 0.323977 | Q129: 0.067566 | R129: -0.46824 | S129: -0.07111 | T129: 0.262821 | U129: -0.08963 | V129: -0.1942 | W129: 0.200848 | X129: 0.270015 | Y129: 0.206096 | Z129: -0.28539 | AA129: -0.11748 | AB129: 0.197524 | AC129: 0.223771 | AD129: 0.02368 | AE129: 0.006036 | AF129: 0.123365 | AG129: -0.03893 | AH129: -0.07607 | AI129: -0.10572 | AJ129: -0.01381 | AK129: 0.368195 | AL129: -0.12945 | AM129: -0.17558 | AN129: -0.16879 | AO129: 0.284096 | AP129: -0.1753 | AQ129: -0.11754 | AR129: 0.241126 | AS129: -0.30295 | AT129: -0.06364 | AU129: -0.22251 | AV129: 0.307694 | AW129: 0.104572 | AX129: 0.078795
A130: 10.Unavailability of equipment | B130: -0.0831 | C130: 0.026771 | D130: -0.1753 | E130: 0.151047 | F130: -0.10612 | G130: -0.04804 | H130: 0.107071 | I130: 0.268817 | J130: 0.267994 | K130: 1 | L130: 0.054149 | M130: 0.309185 | N130: -0.21221 | O130: -0.01052 | P130: 0.056709 | Q130: 0.074488 | R130: 0.301933 | S130: 0.011774 | T130: -0.28181 | U130: 0.067952 | V130: 0.055326 | W130: -0.13321 | X130: 0.074106 | Y130: -0.20181 | Z130: -0.05346 | AA130: 0.001499 | AB130: 0.142699 | AC130: 0.141079 | AD130: -0.08641 | AE130: -0.23621 | AF130: -0.00682 | AG130: -0.05585 | AH130: 0.232404 | AI130: -0.14187 | AJ130: -0.01242 | AK130: -0.17464 | AL130: 0.092361 | AM130: -0.05812 | AN130: 0.126793 | AO130: 0.068183 | AP130: -0.01076 | AQ130: 0.168237 | AR130: -0.24261 | AS130: 0.281935 | AT130: -0.11819 | AU130: 0.248239 | AV130: 0.041478 | AW130: 0.012427 | AX130: 0.000399
A131: 11.Lack of engineering experience | B131: -0.03868 | C131: 0.147799 | D131: 0.077377 | E131: 0.041122 | F131: -0.16591 | G131: 0.045269 | H131: 0.076918 | I131: 0.057875 | J131: 0.064782 | K131: 0.054149 | L131: 1 | M131: 0.143035 | N131: 0.305 | O131: 0.134058 | P131: -0.04041 | Q131: 0.079615 | R131: -0.04256 | S131: 0.177519 | T131: -0.10538 | U131: -0.02018 | V131: 0.33107 | W131: -0.22271 | X131: -0.12097 | Y131: 0.12574 | Z131: 0.081454 | AA131: 0.035517 | AB131: -0.08044 | AC131: 0.12067 | AD131: 0.017463 | AE131: -0.00334 | AF131: -0.15637 | AG131: -0.10866 | AH131: 0.103238 | AI131: -0.14273 | AJ131: 0.230996 | AK131: 0.063728 | AL131: -0.01073 | AM131: -0.25167 | AN131: -0.08027 | AO131: -0.04784 | AP131: 0.203534 | AQ131: 0.042074 | AR131: 0.046626 | AS131: -0.14579 | AT131: -0.09384 | AU131: -0.20247 | AV131: 0.019389 | AW131: -0.03958 | AX131: -0.0072
A132: 12.Construction cost underestimation | B132: 0.168586 | C132: -0.3884 | D132: 0.13251 | E132: -0.16866 | F132: 0.102009 | G132: -0.07884 | H132: -0.13008 | I132: 0.281829 | J132: 0.024799 | K132: 0.309185 | L132: 0.143035 | M132: 1 | N132: 0.290969 | O132: -0.19841 | P132: 0.005303 | Q132: 0.205074 | R132: -0.07607 | S132: -0.13066 | T132: 0.321515 | U132: -0.05996 | V132: -0.04035 | W132: 0.156683 | X132: -0.00753 | Y132: 0.022115 | Z132: -0.09447 | AA132: -0.09342 | AB132: 0.050525 | AC132: -0.14163 | AD132: 0.295009 | AE132: -0.29002 | AF132: 0.089425 | AG132: -0.09533 | AH132: 0.058377 | AI132: 0.052286 | AJ132: -0.19168 | AK132: 0.297227 | AL132: -0.16457 | AM132: 0.030493 | AN132: 0.195357 | AO132: -0.07384 | AP132: 0.048018 | AQ132: 0.100103 | AR132: 0.185637 | AS132: -0.02727 | AT132: 0.502875 | AU132: -0.05629 | AV132: -0.13581 | AW132: -0.06256 | AX132: 0.013535
... A169: Relevant working experience | B169: -0.08184 | C169: -0.00085 | D169: -0.10087 | E169: 0.098195 | F169: -0.25732 | G169: 0.156782 | H169: -0.20504 | I169: -0.0354 | J169: 0.078795 | K169: 0.000399 | L169: -0.0072 | M169: 0.013535 | N169: 0.073864 | O169: 0.335682 | P169: -0.20152 | Q169: 0.025999 | R169: -0.03047 | S169: 0.007386 | T169: 0.01616 | U169: -0.12383 | V169: 0.005731 | W169: -0.12507 | X169: -0.02315 | Y169: 0.00151 | Z169: 0.128159 | AA169: 0.117747 | AB169: -0.06738 | AC169: -0.00986 | AD169: -0.05952 | AE169: -0.01512 | AF169: -0.26513 | AG169: 0.300766 | AH169: -0.1376 | AI169: 0.03554 | AJ169: 0.151481 | AK169: -0.12861 | AL169: 0.019354 | AM169: -0.08819 | AN169: 0.215409 | AO169: -0.14992 | AP169: 0.02668 | AQ169: 0.130119 | AR169: -0.27549 | AS169: -0.00736 | AT169: 0.030132 | AU169: -0.10096 | AV169: -0.04339 | AW169: 0.016698 | AX169: 1
B170: 1.643912 | C170: 2.080644 | D170: 1.18011 | E170: 1.201069 | F170: 1.902637 | G170: 1.390304 | H170: 1.650524 | I170: 1.80378 | J170: 2.276049 | K170: 1.116297 | L170: 0.79546 | M170: 1.535049 | N170: 1.220421 | O170: 1.972753 | P170: 1.974807 | Q170: 0.819315 | R170: 1.380094 | S170: 1.522469 | T170: 1.656053 | U170: 0.998144 | V170: 2.342563 | W170: 1.104848 | X170: 0.946246 | Y170: 0.727449 | Z170: 1.240928 | AA170: 1.406358 | AB170: 1.390035 | AC170: 1.071218 | AD170: 1.955531 | AE170: 1.382049 | AF170: 1.704501 | AG170: 1.69541 | AH170: 1.559634 | AI170: 2.024269 | AJ170: 2.264819 | AK170: 2.044762 | AL170: 1.043865 | AM170: 0.937157 | AN170: 1.217088 | AO170: 1.486073 | AP170: 0.759723 | AQ170: 1.456499 | AR170: 1.295175 | AS170: 0.801127 | AT170: 1.538246 | AU170: 1.017814 | AV170: 0.756316 | AW170: 0.575837 | AX170: 0.802283 | AY170: 68.66771
A172: KMO
B174: 1.Delay in delivering material to construction site | C174: 2.Monopoly of material by some suppliers | D174: 3.Prices fluctuation | E174: 4.Types of material availability at local market | F174: 5.Lack of consultant’s knowledge of available materials | G174: 6.Low productivity | H174: 7.Poor work execution | I174: 8.Shortage of laborers | J174: 9.Mistakes happens during construction phase | K174: 10.Unavailability of equipment | L174: 11.Lack of engineering experience | M174: 12.Construction cost underestimation | N174: 13.Poor site management | O174: 14.Delayed payment for completed work | P174: 15.Cash flow problem during construction | Q174: 16.High rate of interest | R174: 17.Contractor’s financial difficulties | S174: 18.Increase in salaries of skilled laborers | T174: 19.Change design | U174: 20.Errors and omission in design | V174: 21.Incomplete design drawings and specifications at tendering stage | W174: 22.Delay in preparation and approval of drawing | X174: 23.Inaccurate quantity take-off | Y174: 24.Long period from planning of project to construction | Z174: 25.Delays in issuing information to the contractor during construction stage | AA174: 26.No practical use of earned value management system | AB174: 27.Lack of cost planning/monitoring during pre and post contract stage | AC174: 28.Poor communication between client, consultant and contractor | AD174: 29.Insufficient coordination between local authority who is responsible about road projects and service authorities | AE174: 30.Delays in decisions making by the approval authorities | AF174: 31.Change schedule | AG174: 32.Stoppages because of work being rejected by consultant | AH174: 33.Lowest bid price | AI174: 34.Insufficient time for preparation of contract documents | AJ174: 35.Discrepancies in contract documents | AK174: 36.Underestimation of time for completion of project | AL174: 37.Extension of time with cost claims | AM174: 38.Scope and specification changes | AN174: 39.Changes in client requirements | AO174: 40.Frequency of variation orders and additional works | AP174: 41.Rework due to error in execution | AQ174: 42.Weather conditions | AR174: 43.Accidents during construction | AS174: 44.Delay in getting NOCs from different government authorities | AT174: Type of Organization | AU174: Respondents designation | AV174: Indicate the highest formal qualification | AW174: Location of organization | AX174: Relevant working experience
B175: 0.725651 | C175: 0.616774 | D175: 0.671192 | E175: 0.816699 | F175: 0.768717 | G175: 0.823771 | H175: 0.822651 | I175: 0.778386 | J175: 0.748427 | K175: 0.848836 | L175: 0.898397 | M175: 0.821641 | N175: 0.844224 | O175: 0.577767 | P175: 0.644831 | Q175: 0.850208 | R175: 0.632761 | S175: 0.605989 | T175: 0.735908 | U175: 0.813965 | V175: 0.642479 | W175: 0.746722 | X175: 0.75993 | Y175: 0.563741 | Z175: 0.808792 | AA175: 0.780264 | AB175: 0.834183 | AC175: 0.851718 | AD175: 0.630332 | AE175: 0.614856 | AF175: 0.648456 | AG175: 0.731577 | AH175: 0.597878 | AI175: 0.741942 | AJ175: 0.70685 | AK175: 0.625156 | AL175: 0.684041 | AM175: 0.741242 | AN175: 0.733665 | AO175: 0.619683 | AP175: 0.826532 | AQ175: 0.777691 | AR175: 0.730498 | AS175: 0.800882 | AT175: 0.547455 | AU175: 0.401415 | AV175: 0.462737 | AW175: 0.60796 | AX175: 0.385632 | AY175: 0.741071
A177: Eigenvalues and eigenvectors
B179: 13.52051 | C179: 4.14484 | D179: 3.309022 | E179: 2.615582 | F179: 2.135378 | G179: 1.818188 | H179: 1.636156 | I179: 1.558097 | J179: 1.481243 | K179: 1.380597 | L179: 1.262398 | M179: 1.141359 | N179: 1.099163 | O179: 0.939266 | P179: 0.926232 | Q179: 0.840425 | R179: 0.799267 | S179: 0.725951 | T179: 0.682676 | U179: 0.614188 | V179: 0.564199 | W179: 0.542997 | X179: 0.514985 | Y179: 0.459897 | Z179: 0.418323 | AA179: 0.385051 | AB179: 0.333591 | AC179: 0.306635 | AD179: 0.279655 | AE179: 0.26852 | AF179: 0.25092 | AG179: 0.231163 | AH179: 0.212454 | AI179: 0.17686 | AJ179: 0.170963 | AK179: 0.156615 | AL179: 0.150445 | AM179: 0.141817 | AN179: 0.123634 | AO179: 0.106014 | AP179: 0.097249 | AQ179: 0.089958 | AR179: 0.078891 | AS179: 0.074562 | AT179: 0.072752 | AU179: 0.050299 | AV179: 0.049791 | AW179: 0.033091 | AX179: 0.028133
B180: -0.14519 | C180: -0.20748 | D180: -0.12062 | E180: -0.18932 | F180: -0.15479 | G180: -0.04097 | H180: -0.05494 | I180: -0.02016 | J180: -0.02201 | K180: -0.00015 | L180: -0.01241 | M180: -0.26682 | N180: -0.01944 | O180: -0.04742 | P180: -0.03222 | Q180: -0.06375 | R180: -0.21758 | S180: -0.10293 | T180: -0.16832 | U180: -0.37565 | V180: -0.12848 | W180: -0.05683 | X180: -0.03854 | Y180: -0.07856 | Z180: -0.0938 | AA180: -0.06558 | AB180: -0.19001 | AC180: -0.06455 | AD180: -0.08673 | AE180: -0.04974 | AF180: -0.01729 | AG180: -0.10255 | AH180: -0.16129 | AI180: -0.26386 | AJ180: -0.26389 | AK180: -0.09673 | AL180: -0.08976 | AM180: -0.00478 | AN180: -0.07002 | AO180: -0.41633 | AP180: -0.07892 | AQ180: -0.06681 | AR180: -0.0963 | AS180: -0.07415 | AT180: -0.01087 | AU180: -0.04069 | AV180: -0.08932 | AW180: -0.16895 | AX180: -0.15229
B181: -0.11924 | C181: -0.20104 | D181: 0.011623 | E181: -0.30685 | F181: -0.21578 | G181: -0.06948 | H181: 0.124513 | I181: -0.02456 | J181: -0.0054 | K181: -0.02932 | L181: -0.08074 | M181: -0.00284 | N181: -0.04454 | O181: -0.05913 | P181: 0.104187 | Q181: 0.012323 | R181: -0.23795 | S181: 0.092896 | T181: -0.138 | U181: 0.135527 | V181: 0.179531 | W181: 0.157704 | X181: -0.14433 | Y181: 0.177163 | Z181: 0.032207 | AA181: 0.110907 | AB181: -0.21126 | AC181: -0.24377 | AD181: 0.172263 | AE181: -0.15455 | AF181: 0.22326 | AG181: -0.02641 | AH181: -0.13275 | AI181: 0.026985 | AJ181: 0.284617 | AK181: -0.13935 | AL181: -0.02879 | AM181: 0.13623 | AN181: -0.11691 | AO181: 0.159554 | AP181: -0.10013 | AQ181: -0.0653 | AR181: -0.07947 | AS181: 0.16285 | AT181: 0.038489 | AU181: -0.12936 | AV181: 0.141474 | AW181: 0.128754 | AX181: 0.21673
B182: -0.10023 | C182: -0.18703 | D182: 0.103919 | E182: 0.082163 | F182: -0.20981 | G182: -0.22657 | H182: 0.005065 | I182: -0.07835 | J182: -0.17136 | K182: 0.152625 | L182: 0.184129 | M182: 0.292086 | N182: 0.182054 | O182: 0.028571 | P182: -0.03363 | Q182: 0.163127 | R182: -0.0109 | S182: 0.127293 | T182: 0.281672 | U182: 0.035484 | V182: 0.135472 | W182: -0.10344 | X182: -0.05395 | Y182: -0.04721 | Z182: -0.21159 | AA182: 0.010102 | AB182: 0.367907 | AC182: -0.08743 | AD182: 0.087916 | AE182: -0.06871 | AF182: 0.200027 | AG182: 0.015653 | AH182: -0.17059 | AI182: 0.123943 | AJ182: -0.09855 | AK182: -0.15017 | AL182: 0.026164 | AM182: -0.10912 | AN182: -0.02631 | AO182: -0.18689 | AP182: -0.00919 | AQ182: -0.13947 | AR182: 0.045413 | AS182: -0.15564 | AT182: 0.197507 | AU182: -0.08742 | AV182: -0.08358 | AW182: -0.0173 | AX182: -0.07709
B183: -0.16721 | C183: -0.20519 | D183: -0.02465 | E183: -0.1409 | F183: -0.15216 | G183: -0.07389 | H183: -0.05004 | I183: -0.05967 | J183: -0.12169 | K183: 0.0606 | L183: 0.203836 | M183: -0.0366 | N183: 0.079465 | O183: -0.1947 | P183: -0.11737 | Q183: 0.056896 | R183: 0.070316 | S183: -0.15989 | T183: -0.13683 | U183: -0.17319 | V183: 0.027439 | W183: -0.08669 | X183: 0.025408 | Y183: 0.25202 | Z183: -0.00083 | AA183: 0.119828 | AB183: 0.246673 | AC183: 0.082189 | AD183: 0.015246 | AE183: -0.0914 | AF183: -0.1227 | AG183: 0.097267 | AH183: 0.005157 | AI183: -0.06962 | AJ183: 0.169306 | AK183: 0.474637 | AL183: -0.08536 | AM183: 0.044643 | AN183: 0.300865 | AO183: 0.021744 | AP183: 0.155342 | AQ183: 0.154138 | AR183: 0.005814 | AS183: 0.067189 | AT183: 0.04006 | AU183: 0.166248 | AV183: 0.115559 | AW183: -0.08725 | AX183: 0.154073
B184: -0.19253 | C184: -0.05312 | D184: 0.086341 | E184: 0.009821 | F184: -0.18026 | G184: 0.025315 | H184: -0.02628 | I184: 0.023382 | J184: -0.02482 | K184: -0.0817 | L184: 0.026345 | M184: 0.150412 | N184: 0.076155 | O184: -0.20937 | P184: 0.21665 | Q184: 0.145395 | R184: 0.112634 | S184: -0.15918 | T184: -0.27477 | U184: 0.193256 | V184: 0.140961 | W184: -0.14542 | X184: 0.031012 | Y184: -0.24154 | Z184: 0.164123 | AA184: -0.07624 | AB184: -0.03193 | AC184: 0.149167 | AD184: -0.03717 | AE184: -0.1476 | AF184: -0.31972 | AG184: -0.24543 | AH184: -0.01225 | AI184: 0.00114 | AJ184: 0.113566 | AK184: -0.03467 | AL184: 0.028332 | AM184: -0.20672 | AN184: -0.14884 | AO184: -0.00543 | AP184: 0.043515 | AQ184: -0.24069 | AR184: 0.215823 | AS184: 0.127223 | AT184: -0.11965 | AU184: -0.01593 | AV184: 0.084434 | AW184: 0.03131 | AX184: -0.22757
B185: -0.18524 | C185: -0.2243 | D185: -0.02674 | E185: 0.092213 | F185: 0.146315 | G185: -0.04882 | H185: 0.118247 | I185: 0.138124 | J185: 0.044868 | K185: -0.01575 | L185: -0.007 | M185: -0.07435 | N185: 0.140084 | O185: -0.02102 | P185: -0.10964 | Q185: -0.13814 | R185: -0.07584 | S185: -0.08268 | T185: 0.013626 | U185: 0.111324 | V185: -0.15195 | W185: -0.07507 | X185: -0.02501 | Y185: -0.01826 | Z185: -0.1687 | AA185: 0.260458 | AB185: 0.063233 | AC185: 0.058682 | AD185: 0.10758 | AE185: 0.107325 | AF185: 0.012883 | AG185: 0.01805 | AH185: 0.292468 | AI185: -0.07974 | AJ185: 0.067153 | AK185: -0.04036 | AL185: -0.15488 | AM185: -0.0173 | AN185: -0.29064 | AO185: -0.1055 | AP185: 0.235056 | AQ185: 0.082736 | AR185: 0.317721 | AS185: 0.076738 | AT185: -0.18707 | AU185: -0.26878 | AV185: -0.24695 | AW185: 0.068694 | AX185: 0.219846
B186: -0.20683 | C186: -0.18511 | D186: -0.03047 | E186: 0.040275 | F186: 0.080785 | G186: -0.12165 | H186: 0.092602 | I186: 0.009557 | J186: 0.053683 | K186: 0.014885 | L186: 0.098134 | M186: -0.16234 | N186: 0.120091 | O186: -0.01511 | P186: -0.02445 | Q186: -0.03074 | R186: 0.081473 | S186: -0.12312 | T186: 0.042569 | U186: 0.090522 | V186: -0.07202 | W186: 0.011428 | X186: 0.132834 | Y186: -0.11713 | Z186: 0.000266 | AA186: 0.050688 | AB186: 0.123323 | AC186: -0.08005 | AD186: 0.347569 | AE186: 0.144637 | AF186: -0.1683 | AG186: 0.261702 | AH186: 0.085003 | AI186: -0.11837 | AJ186: -0.22494 | AK186: -0.15537 | AL186: 0.056646 | AM186: 0.058831 | AN186: 0.013992 | AO186: 0.172663 | AP186: -0.10262 | AQ186: -0.03714 | AR186: -0.36361 | AS186: 0.107428 | AT186: -0.07972 | AU186: 0.024889 | AV186: 0.306432 | AW186: 0.230366 | AX186: -0.24832
B187: -0.18535 | C187: -0.17317 | D187: -0.14354 | E187: 0.020717 | F187: 0.008758 | G187: 0.072015 | H187: 0.043254 | I187: 0.254074 | J187: -0.0353 | K187: -0.08052 | L187: 0.042006 | M187: 0.098979 | N187: 0.012141 | O187: 0.033264 | P187: -0.14227 | Q187: -0.11262 | R187: -0.12796 | S187: 0.108711 | T187: 0.040334 | U187: -0.09248 | V187: -0.33716 | W187: 0.019619 | X187: -0.05305 | Y187: 0.036546 | Z187: 0.154721 | AA187: 0.004198 | AB187: -0.01034 | AC187: 0.182966 | AD187: -0.05909 | AE187: -0.21572 | AF187: 0.063695 | AG187: -0.04812 | AH187: -0.01004 | AI187: 0.098776 | AJ187: 0.251319 | AK187: 0.052783 | AL187: 0.130549 | AM187: 0.031016 | AN187: -0.22806 | AO187: 0.158101 | AP187: 0.009303 | AQ187: 0.044287 | AR187: -0.05559 | AS187: -0.3932 | AT187: 0.126972 | AU187: 0.225432 | AV187: -0.01007 | AW187: 0.208905 | AX187: -0.27876
B188: -0.19195 | C188: -0.18223 | D188: 0.083356 | E188: 0.143593 | F188: 0.02176 | G188: 0.004433 | H188: -0.0381 | I188: 0.190088 | J188: 0.128599 | K188: 0.070088 | L188: -0.13509 | M188: 0.101427 | N188: -0.01796 | O188: 0.062645 | P188: 0.050174 | Q188: -0.12927 | R188: -0.00539 | S188: -0.08858 | T188: 0.07342 | U188: 0.035613 | V188: -0.07314 | W188: 0.123853 | X188: 0.097772 | Y188: -0.08144 | Z188: -0.13319 | AA188: -0.35177 | AB188: 0.026713 | AC188: -0.18776 | AD188: 0.082039 | AE188: -0.14853 | AF188: -0.02304 | AG188: -0.11457 | AH188: 0.096278 | AI188: -0.0974 | AJ188: -0.00222 | AK188: -0.13388 | AL188: -0.00981 | AM188: -0.19626 | AN188: 0.07147 | AO188: -0.02052 | AP188: -0.18175 | AQ188: 0.148899 | AR188: 0.141055 | AS188: 0.039634 | AT188: 0.040284 | AU188: 0.435831 | AV188: 0.136801 | AW188: -0.14725 | AX188: 0.360637
B189: -0.18919 | C189: -0.07509 | D189: -0.13629 | E189: -0.01502 | F189: -0.01165 | G189: -0.00897 | H189: -0.01415 | I189: 0.211639 | J189: -0.14531 | K189: 0.20609 | L189: -0.20384 | M189: 0.013271 | N189: -0.13114 | O189: 0.036549 | P189: -0.06979 | Q189: -0.21879 | R189: 0.027739 | S189: 0.215855 | T189: -0.01559 | U189: 0.045551 | V189: -0.05074 | W189: -0.03344 | X189: 0.087816 | Y189: 0.186348 | Z189: 0.188582 | AA189: -0.21147 | AB189: 0.08276 | AC189: 0.169785 | AD189: 0.058124 | AE189: 0.135667 | AF189: -0.10724 | AG189: 0.019595 | AH189: -0.13492 | AI189: 0.096981 | AJ189: -0.14681 | AK189: 0.092837 | AL189: -0.16743 | AM189: -0.06908 | AN189: 0.02887 | AO189: 0.14885 | AP189: -0.15106 | AQ189: -0.12898 | AR189: 0.043771 | AS189: 0.371079 | AT189: 0.284244 | AU189: -0.19778 | AV189: -0.2215 | AW189: -0.07834 | AX189: -0.06917
B190: -0.19751 | C190: -0.17743 | D190: 0.013832 | E190: -0.00933 | F190: 0.172857 | G190: -0.00088 | H190: 0.18082 | I190: -0.03647 | J190: -0.03511 | K190: 0.016184 | L190: 0.008743 | M190: 0.20743 | N190: -0.14284 | O190: -0.02013 | P190: 0.075957 | Q190: 0.05681 | R190: 0.003122 | S190: -0.05332 | T190: 0.014691 | U190: -0.16405 | V190: 0.04862 | W190: 0.154245 | X190: -0.08265 | Y190: -0.11347 | Z190: 0.004823 | AA190: -0.08001 | AB190: 0.02486 | AC190: 0.072861 | AD190: -0.08367 | AE190: 0.262421 | AF190: 0.086179 | AG190: 0.020485 | AH190: -0.10121 | AI190: -0.02889 | AJ190: -0.073 | AK190: 0.047982 | AL190: 0.16831 | AM190: 0.523468 | AN190: 0.12416 | AO190: 0.099444 | AP190: -0.17074 | AQ190: -0.08165 | AR190: 0.408806 | AS190: -0.05855 | AT190: -0.20064 | AU190: -0.02312 | AV190: 0.087346 | AW190: -0.10805 | AX190: -0.0787
... B228: 0.028776 | C228: 0.021423 | D228: -0.05257 | E228: 0.020492 | F228: 0.317215 | G228: 0.192155 | H228: 0.271328 | I228: 0.244278 | J228: -0.01614 | K228: -0.15559 | L228: 0.119946 | M228: -0.10434 | N228: 0.308401 | O228: 0.108885 | P228: -0.15261 | Q228: 0.06797 | R228: -0.09915 | S228: 0.142351 | T228: -0.27572 | U228: -0.18719 | V228: 0.443686 | W228: -0.09545 | X228: 0.185174 | Y228: 0.150311 | Z228: -0.00839 | AA228: -0.18249 | AB228: 0.179541 | AC228: -0.02752 | AD228: -0.04055 | AE228: -0.08046 | AF228: 0.131084 | AG228: -0.07378 | AH228: -0.02027 | AI228: 0.007889 | AJ228: 0.00215 | AK228: -0.09762 | AL228: 0.066085 | AM228: -0.03326 | AN228: -0.01472 | AO228: -0.06199 | AP228: 0.004411 | AQ228: 0.041161 | AR228: 0.010068 | AS228: 0.0969 | AT228: -0.02998 | AU228: 0.006386 | AV228: 0.05336 | AW228: 0.024505 | AX228: -0.06182
A230: Full Load Matrix
B232: 1 | C232: 2 | D232: 3 | E232: 4 | F232: 5 | G232: 6 | H232: 7 | I232: 8 | J232: 9 | K232: 10 | L232: 11 | M232: 12 | N232: 13 | O232: 14 | P232: 15 | Q232: 16 | R232: 17 | S232: 18 | T232: 19 | U232: 20 | V232: 21 | W232: 22 | X232: 23 | Y232: 24 | Z232: 25 | AA232: 26 | AB232: 27 | AC232: 28 | AD232: 29 | AE232: 30 | AF232: 31 | AG232: 32 | AH232: 33 | AI232: 34 | AJ232: 35 | AK232: 36 | AL232: 37 | AM232: 38 | AN232: 39 | AO232: 40 | AP232: 41 | AQ232: 42 | AR232: 43 | AS232: 44 | AT232: 45 | AU232: 46 | AV232: 47 | AW232: 48 | AX232: 49
A233: 1.Delay in delivering material to construction site | B233: -0.53388 | C233: -0.42241 | D233: -0.21943 | E233: -0.30618 | F233: -0.22619 | G233: -0.05525 | H233: -0.07028 | I233: -0.02517 | J233: -0.02679 | K233: -0.00018 | L233: -0.01394 | M233: -0.28505 | N233: -0.02038 | O233: -0.04596 | P233: -0.03101 | Q233: -0.05845 | R233: -0.19452 | S233: -0.0877 | T233: -0.13907 | U233: -0.2944 | V233: -0.0965 | W233: -0.04188 | X233: -0.02766 | Y233: -0.05327 | Z233: -0.06067 | AA233: -0.04069 | AB233: -0.10975 | AC233: -0.03575 | AD233: -0.04587 | AE233: -0.02578 | AF233: -0.00866 | AG233: -0.04931 | AH233: -0.07434 | AI233: -0.11097 | AJ233: -0.10911 | AK233: -0.03828 | AL233: -0.03482 | AM233: -0.0018 | AN233: -0.02462 | AO233: -0.13556 | AP233: -0.02461 | AQ233: -0.02004 | AR233: -0.02705 | AS233: -0.02025 | AT233: -0.00293 | AU233: -0.00913 | AV233: -0.01993 | AW233: -0.03073 | AX233: -0.02554
A234: 2.Monopoly of material by some suppliers | B234: -0.43846 | C234: -0.4093 | D234: 0.021142 | E234: -0.49626 | F234: -0.31532 | G234: -0.09369 | H234: 0.159268 | I234: -0.03066 | J234: -0.00657 | K234: -0.03446 | L234: -0.09072 | M234: -0.00304 | N234: -0.0467 | O234: -0.0573 | P234: 0.100271 | Q234: 0.011297 | R234: -0.21274 | S234: 0.07915 | T234: -0.11402 | U234: 0.106213 | V234: 0.134852 | W234: 0.116209 | X234: -0.10357 | Y234: 0.120144 | Z234: 0.020831 | AA234: 0.06882 | AB234: -0.12202 | AC234: -0.13498 | AD234: 0.091097 | AE234: -0.08008 | AF234: 0.111835 | AG234: -0.0127 | AH234: -0.06119 | AI234: 0.011348 | AJ234: 0.117682 | AK234: -0.05515 | AL234: -0.01117 | AM234: 0.051302 | AN234: -0.04111 | AO234: 0.05195 | AP234: -0.03123 | AQ234: -0.01958 | AR234: -0.02232 | AS234: 0.044468 | AT234: 0.010382 | AU234: -0.02901 | AV234: 0.031568 | AW234: 0.023421 | AX234: 0.036352
A235: 3.Prices fluctuation | B235: -0.36854 | C235: -0.38077 | D235: 0.189035 | E235: 0.132881 | F235: -0.3066 | G235: -0.30551 | H235: 0.006479 | I235: -0.0978 | J235: -0.20855 | K235: 0.179333 | L235: 0.206881 | M235: 0.312048 | N235: 0.190868 | O235: 0.02769 | P235: -0.03236 | Q235: 0.149546 | R235: -0.00974 | S235: 0.108457 | T235: 0.232729 | U235: 0.027809 | V235: 0.101758 | W235: -0.07622 | X235: -0.03872 | Y235: -0.03202 | Z235: -0.13685 | AA235: 0.006269 | AB235: 0.212493 | AC235: -0.04841 | AD235: 0.046492 | AE235: -0.03561 | AF235: 0.100197 | AG235: 0.007526 | AH235: -0.07863 | AI235: 0.052124 | AJ235: -0.04075 | AK235: -0.05943 | AL235: 0.010148 | AM235: -0.04109 | AN235: -0.00925 | AO235: -0.06085 | AP235: -0.00287 | AQ235: -0.04183 | AR235: 0.012755 | AS235: -0.0425 | AT235: 0.053273 | AU235: -0.0196 | AV235: -0.01865 | AW235: -0.00315 | AX235: -0.01293
A236: 4.Types of material availability at local market | B236: -0.61483 | C236: -0.41775 | D236: -0.04485 | E236: -0.22788 | F236: -0.22234 | G236: -0.09964 | H236: -0.06401 | I236: -0.07448 | J236: -0.1481 | K236: 0.071205 | L236: 0.229023 | M236: -0.03911 | N236: 0.083312 | O236: -0.1887 | P236: -0.11295 | Q236: 0.052159 | R236: 0.062864 | S236: -0.13623 | T236: -0.11306 | U236: -0.13573 | V236: 0.02061 | W236: -0.06388 | X236: 0.018233 | Y236: 0.170909 | Z236: -0.00054 | AA236: 0.074356 | AB236: 0.142472 | AC236: 0.045512 | AD236: 0.008063 | AE236: -0.04736 | AF236: -0.06147 | AG236: 0.046765 | AH236: 0.002377 | AI236: -0.02928 | AJ236: 0.070004 | AK236: 0.187835 | AL236: -0.03311 | AM236: 0.016812 | AN236: 0.105789 | AO236: 0.00708 | AP236: 0.048443 | AQ236: 0.046231 | AR236: 0.001633 | AS236: 0.018347 | AT236: 0.010805 | AU236: 0.037285 | AV236: 0.025786 | AW236: -0.01587 | AX236: 0.025842
A237: 5.Lack of consultant’s knowledge of available materials | B237: -0.70795 | C237: -0.10815 | D237: 0.157061 | E237: 0.015884 | F237: -0.26342 | G237: 0.034134 | H237: -0.03362 | I237: 0.029186 | J237: -0.03021 | K237: -0.096 | L237: 0.0296 | M237: 0.160692 | N237: 0.079842 | O237: -0.20291 | P237: 0.208506 | Q237: 0.133291 | R237: 0.100696 | S237: -0.13562 | T237: -0.22703 | U237: 0.151455 | V237: 0.105881 | W237: -0.10716 | X237: 0.022255 | Y237: -0.1638 | Z237: 0.106151 | AA237: -0.04731 | AB237: -0.01844 | AC237: 0.082601 | AD237: -0.01966 | AE237: -0.07648 | AF237: -0.16015 | AG237: -0.118 | AH237: -0.00565 | AI237: 0.00048 | AJ237: 0.046957 | AK237: -0.01372 | AL237: 0.010989 | AM237: -0.07785 | AN237: -0.05234 | AO237: -0.00177 | AP237: 0.01357 | AQ237: -0.07219 | AR237: 0.060619 | AS237: 0.03474 | AT237: -0.03227 | AU237: -0.00357 | AV237: 0.01884 | AW237: 0.005696 | AX237: -0.03817
A238: 6.Low productivity | B238: -0.68112 | C238: -0.45665 | D238: -0.04863 | E238: 0.149134 | F238: 0.213809 | G238: -0.06583 | H238: 0.151253 | I238: 0.172412 | J238: 0.054607 | K238: -0.01851 | L238: -0.00786 | M238: -0.07943 | N238: 0.146865 | O238: -0.02037 | P238: -0.10552 | Q238: -0.12664 | R238: -0.0678 | S238: -0.07045 | T238: 0.011258 | U238: 0.087244 | V238: -0.11413 | W238: -0.05532 | X238: -0.01795 | Y238: -0.01238 | Z238: -0.10911 | AA238: 0.161621 | AB238: 0.036522 | AC238: 0.032495 | AD238: 0.056891 | AE238: 0.055614 | AF238: 0.006453 | AG238: 0.008678 | AH238: 0.134807 | AI238: -0.03354 | AJ238: 0.027766 | AK238: -0.01597 | AL238: -0.06007 | AM238: -0.00651 | AN238: -0.10219 | AO238: -0.03435 | AP238: 0.073302 | AQ238: 0.024815 | AR238: 0.08924 | AS238: 0.020954 | AT238: -0.05046 | AU238: -0.06028 | AV238: -0.0551 | AW238: 0.012496 | AX238: 0.036874
A239: 7.Poor work execution | B239: -0.76051 | C239: -0.37687 | D239: -0.05542 | E239: 0.065136 | F239: 0.118051 | G239: -0.16403 | H239: 0.118449 | I239: 0.01193 | J239: 0.065336 | K239: 0.01749 | L239: 0.11026 | M239: -0.17344 | N239: 0.125905 | O239: -0.01464 | P239: -0.02354 | Q239: -0.02818 | R239: 0.072838 | S239: -0.1049 | T239: 0.035173 | U239: 0.070942 | V239: -0.0541 | W239: 0.008421 | X239: 0.095325 | Y239: -0.07943 | Z239: 0.000172 | AA239: 0.031453 | AB239: 0.071228 | AC239: -0.04433 | AD239: 0.183803 | AE239: 0.07495 | AF239: -0.08431 | AG239: 0.125825 | AH239: 0.03918 | AI239: -0.04978 | AJ239: -0.09301 | AK239: -0.06149 | AL239: 0.021971 | AM239: 0.022155 | AN239: 0.00492 | AO239: 0.056219 | AP239: -0.032 | AQ239: -0.01114 | AR239: -0.10213 | AS239: 0.029334 | AT239: -0.0215 | AU239: 0.005582 | AV239: 0.068377 | AW239: 0.041905 | AX239: -0.04165
A240: 8.Shortage of laborers | B240: -0.68154 | C240: -0.35254 | D240: -0.26111 | E240: 0.033506 | F240: 0.012798 | G240: 0.097105 | H240: 0.055327 | I240: 0.317145 | J240: -0.04297 | K240: -0.09461 | L240: 0.047196 | M240: 0.105744 | N240: 0.012729 | O240: 0.032238 | P240: -0.13692 | Q240: -0.10324 | R240: -0.1144 | S240: 0.092625 | T240: 0.033326 | U240: -0.07247 | V240: -0.25325 | W240: 0.014457 | X240: -0.03807 | Y240: 0.024784 | Z240: 0.10007 | AA240: 0.002605 | AB240: -0.00597 | AC240: 0.101317 | AD240: -0.03125 | AE240: -0.11179 | AF240: 0.031906 | AG240: -0.02314 | AH240: -0.00463 | AI240: 0.04154 | AJ240: 0.103914 | AK240: 0.020889 | AL240: 0.050636 | AM240: 0.01168 | AN240: -0.08019 | AO240: 0.051478 | AP240: 0.002901 | AQ240: 0.013283 | AR240: -0.01561 | AS240: -0.10737 | AT240: 0.034248 | AU240: 0.050559 | AV240: -0.00225 | AW240: 0.038002 | AX240: -0.04676
A241: 9.Mistakes happens during construction phase | B241: -0.70581 | C241: -0.371 | D241: 0.151631 | E241: 0.23223 | F241: 0.031797 | G241: 0.005977 | H241: -0.04874 | I241: 0.237275 | J241: 0.156514 | K241: 0.082352 | L241: -0.15178 | M241: 0.108359 | N241: -0.01883 | O241: 0.060713 | P241: 0.048288 | Q241: -0.11851 | R241: -0.00482 | S241: -0.07547 | T241: 0.060663 | U241: 0.02791 | V241: -0.05494 | W241: 0.091266 | X241: 0.070164 | Y241: -0.05523 | Z241: -0.08614 | AA241: -0.21828 | AB241: 0.015429 | AC241: -0.10397 | AD241: 0.043384 | AE241: -0.07696 | AF241: -0.01154 | AG241: -0.05509 | AH241: 0.044377 | AI241: -0.04096 | AJ241: -0.00092 | AK241: -0.05298 | AL241: -0.0038 | AM241: -0.07391 | AN241: 0.02513 | AO241: -0.00668 | AP241: -0.05668 | AQ241: 0.044659 | AR241: 0.039619 | AS241: 0.010823 | AT241: 0.010866 | AU241: 0.097746 | AV241: 0.030526 | AW241: -0.02679 | AX241: 0.060489
A242: 10.Unavailability of equipment | B242: -0.69565 | C242: -0.15288 | D242: -0.24791 | E242: -0.02429 | F242: -0.01702 | G242: -0.01209 | H242: -0.01809 | I242: 0.264176 | J242: -0.17685 | K242: 0.242154 | L242: -0.22903 | M242: 0.014178 | N242: -0.13749 | O242: 0.035421 | P242: -0.06717 | Q242: -0.20057 | R242: 0.024799 | S242: 0.183915 | T242: -0.01288 | U242: 0.035699 | V242: -0.03811 | W242: -0.02464 | X242: 0.063019 | Y242: 0.126373 | Z242: 0.121971 | AA242: -0.13122 | AB242: 0.0478 | AC242: 0.094018 | AD242: 0.030737 | AE242: 0.070301 | AF242: -0.05372 | AG242: 0.009421 | AH242: -0.06219 | AI242: 0.040785 | AJ242: -0.0607 | AK242: 0.03674 | AL242: -0.06494 | AM242: -0.02602 | AN242: 0.010151 | AO242: 0.048465 | AP242: -0.04711 | AQ242: -0.03869 | AR242: 0.012294 | AS242: 0.101327 | AT242: 0.076668 | AU242: -0.04436 | AV242: -0.04943 | AW242: -0.01425 | AX242: -0.0116
A243: 11.Lack of engineering experience | B243: -0.72624 | C243: -0.36122 | D243: 0.025162 | E243: -0.01509 | F243: 0.252595 | G243: -0.00118 | H243: 0.231291 | I243: -0.04552 | J243: -0.04273 | K243: 0.019016 | L243: 0.009823 | M243: 0.221606 | N243: -0.14975 | O243: -0.01951 | P243: 0.073102 | Q243: 0.052081 | R243: 0.002791 | S243: -0.04543 | T243: 0.012138 | U243: -0.12857 | V243: 0.03652 | W243: 0.11366 | X243: -0.05931 | Y243: -0.07695 | Z243: 0.003119 | AA243: -0.04965 | AB243: 0.014358 | AC243: 0.040346 | AD243: -0.04424 | AE243: 0.135984 | AF243: 0.043169 | AG243: 0.009849 | AH243: -0.04665 | AI243: -0.01215 | AJ243: -0.03018 | AK243: 0.018989 | AL243: 0.065283 | AM243: 0.197131 | AN243: 0.043656 | AO243: 0.032379 | AP243: -0.05324 | AQ243: -0.02449 | AR243: 0.114823 | AS243: -0.01599 | AT243: -0.05412 | AU243: -0.00518 | AV243: 0.01949 | AW243: -0.01966 | AX243: -0.0132
A244: 12.Construction cost underestimation | B244: -0.72578 | C244: -0.29251 | D244: 0.029366 | E244: 0.391469 | F244: 0.128389 | G244: 0.109271 | H244: 0.018497 | I244: -0.04232 | J244: -0.01833 | K244: -0.11581 | L244: -0.06056 | M244: 0.133061 | N244: -0.1513 | O244: 0.0615 | P244: -0.07024 | Q244: -0.07207 | R244: -0.00453 | S244: 0.181928 | T244: 0.041998 | U244: 0.092659 | V244: -0.05643 | W244: -0.0528 | X244: 0.054004 | Y244: 0.039371 | Z244: -0.02383 | AA244: -0.04783 | AB244: -0.07793 | AC244: 0.031955 | AD244: -0.11869 | AE244: -0.0047 | AF244: 0.017401 | AG244: -0.05534 | AH244: -0.08273 | AI244: -0.02074 | AJ244: -0.03836 | AK244: 0.048703 | AL244: -0.00393 | AM244: -0.031 | AN244: 0.063168 | AO244: -0.04783 | AP244: 0.095764 | AQ244: -0.04981 | AR244: -0.05721 | AS244: -0.02229 | AT244: -0.03932 | AU244: -0.06231 | AV244: 0.093055 | AW244: 0.024056 | AX244: 0.036147
... A281: Relevant working experience | B281: 0.105812 | C281: 0.043615 | D281: -0.09563 | E281: 0.033141 | F281: 0.463544 | G281: 0.259102 | H281: 0.347062 | I281: 0.304916 | J281: -0.01964 | K281: -0.18282 | L281: 0.134767 | M281: -0.11148 | N281: 0.323331 | O281: 0.105527 | P281: -0.14687 | Q281: 0.062311 | R281: -0.08864 | S281: 0.121287 | T281: -0.22781 | U281: -0.1467 | V281: 0.333267 | W281: -0.07034 | X281: 0.132885 | Y281: 0.101935 | Z281: -0.00543 | AA281: -0.11324 | AB281: 0.103698 | AC281: -0.01524 | AD281: -0.02144 | AE281: -0.04169 | AF281: 0.065662 | AG281: -0.03547 | AH281: -0.00934 | AI281: 0.003318 | AJ281: 0.000889 | AK281: -0.03863 | AL281: 0.025633 | AM281: -0.01253 | AN281: -0.00518 | AO281: -0.02018 | AP281: 0.001375 | AQ281: 0.012346 | AR281: 0.002828 | AS281: 0.02646 | AT281: -0.00809 | AU281: 0.001432 | AV281: 0.011907 | AW281: 0.004458 | AX281: -0.01037
A283: Scree Plot
B285: eValue | C285: % | D285: Cum %
B286: 13.52051 | C286: 0.2759 | D286: 0.2759
B287: 4.14484 | C287: 0.0846 | D287: 0.3605
B288: 3.309022 | C288: 0.0675 | D288: 0.428
B289: 2.615582 | C289: 0.0534 | D289: 0.4814
B290: 2.135378 | C290: 0.0436 | D290: 0.525
B291: 1.818188 | C291: 0.0371 | D291: 0.5621
B292: 1.636156 | C292: 0.0334 | D292: 0.5955
B293: 1.558097 | C293: 0.0318 | D293: 0.6273
B294: 1.481243 | C294: 0.0302 | D294: 0.6575
B295: 1.380597 | C295: 0.0282 | D295: 0.6857
B296: 1.262398 | C296: 0.0258 | D296: 0.7115
B297: 1.141359 | C297: 0.0233 | D297: 0.7348
... B334: 0.028133 | C334: 0.0006 | D334: 1
...

Sheet Varimax
A1: Factor Matrix (rotated Varimax)
B3: Construction & Site Management Risk | C3: Design & Engineering Risk | D3: Financial Risk | E3: Scope Change & Client-Driven Risk | F3: External & Supply Chain Risk | G3: Economic & Market Conditions Risk (Weak factor) | H3: Regulatory & Administrative Risk | I3: Organizational Structure Risk (Weak factor) | J3: Planning & Scheduling Risk (Weak factor) | K3: Contractual & Estimation Risk (Weak factor) | L3: Qualification & Knowledge Risk (Weak factor) | N3: Commun | O3: Specific
B4: -0.50316 | C4: -0.08111 | D4: -0.07506 | E4: 0.022609 | F4: -0.54391 | G4: -0.1289 | H4: -0.06442 | I4: 0.075535 | J4: -0.05645 | K4: -0.06258 | L4: 0.265988 | N4: 0.666051 | O4: 0.333949
A5: 2.Monopoly of material by some suppliers | B5: -0.41288 | C5: 0.117371 | D5: -0.16713 | E5: -0.0988 | F5: -0.61786 | G5: -0.18374 | H5: 0.07491 | I5: 0.16891 | J5: 0.173656 | K5: -0.13134 | L5: 0.177381 | N5: 0.750471 | O5: 0.249529
A6: 3.Prices fluctuation | B6: -0.43584 | C6: 0.022585 | D6: -0.02703 | E6: 0.062301 | F6: -0.093 | G6: -0.62571 | H6: 0.186956 | I6: -0.03804 | J6: -0.10288 | K6: -0.02898 | L6: 0.080795 | N6: 0.649599 | O6: 0.350401
A7: 4.Types of material availability at local market | B7: -0.56568 | C7: 0.011497 | D7: -0.12429 | E7: -0.06408 | F7: -0.43016 | G7: -0.3293 | H7: 0.036395 | I7: -0.08709 | J7: -0.1645 | K7: -0.01806 | L7: 0.292366 | N7: 0.75493 | O7: 0.24507
A8: 5.Lack of consultant’s knowledge of available materials | B8: -0.46995 | C8: 0.40228 | D8: -0.0089 | E8: 0.173412 | F8: -0.3203 | G8: -0.16594 | H8: 0.019769 | I8: -0.01431 | J8: -0.24707 | K8: 0.051037 | L8: 0.118954 | N8: 0.621352 | O8: 0.378648
A9: 6.Low productivity | B9: -0.88026 | C9: 0.081796 | D9: 0.020737 | E9: 0.049099 | F9: -0.04497 | G9: 0.019716 | H9: -0.11684 | I9: -0.02084 | J9: -0.0059 | K9: 0.046577 | L9: -0.00235 | N9: 0.80309 | O9: 0.19691
A10: 7.Poor work execution | B10: -0.81808 | C10: 0.114834 | D10: -0.08558 | E10: 0.088338 | F10: -0.13629 | G10: -0.13761 | H10: -0.1609 | I10: -0.13405 | J10: -0.00339 | K10: 0.086854 | L10: 0.113839 | N10: 0.799461 | O10: 0.200539
A11: 8.Shortage of laborers | B11: -0.76843 | C11: 0.062224 | D11: -0.00698 | E11: 0.080365 | F11: -0.17051 | G11: 0.164328 | H11: -0.10132 | I11: 0.049737 | J11: -0.23647 | K11: -0.14247 | L11: 0.196063 | N11: 0.784342 | O11: 0.215658
A12: 9.Mistakes happens during construction phase | B12: -0.77131 | C12: 0.235885 | D12: 0.186317 | E12: 0.144642 | F12: -0.06676 | G12: -0.05951 | H12: -0.05966 | I12: 0.198053 | J12: -0.11541 | K12: 0.237075 | L12: 0.016127 | N12: 0.826771 | O12: 0.173229
A13: 10.Unavailability of equipment | B13: -0.63047 | C13: -0.02184 | D13: -0.28029 | E13: 0.173487 | F13: -0.18308 | G13: 0.046744 | H13: -0.13359 | I13: 0.322732 | J13: -0.32213 | K13: 0.087041 | L13: 0.081235 | N13: 0.782267 | O13: 0.217733
A14: 11.Lack of engineering experience | B14: -0.80172 | C14: 0.128503 | D14: -0.18926 | E14: -0.01407 | F14: -0.18041 | G14: 0.017436 | H14: -0.03559 | I14: -0.15762 | J14: 0.017985 | K14: 0.151406 | L14: -0.05413 | N14: 0.780427 | O14: 0.219573
A15: 12.Construction cost underestimation | B15: -0.74027 | C15: 0.168367 | D15: 0.128551 | E15: 0.287053 | F15: -0.0891 | G15: 0.032809 | H15: -0.01512 | I15: -0.19054 | J15: -0.21012 | K15: 0.174484 | L15: -0.13776 | N15: 0.814393 | O15: 0.185607
A16: 13.Poor site management | B16: -0.74264 | C16: 0.21495 | D16: -0.06782 | E16: 0.140655 | F16: -0.04355 | G16: -0.04793 | H16: -0.11525 | I16: -0.36704 | J16: -0.01153 | K16: 0.068608 | L16: -0.08167 | N16: 0.785805 | O16: 0.214195
... A52: Relevant working experience | B52: -0.14494 | C52: 0.052579 | D52: -0.06956 | E52: -0.24955 | F52: 0.344745 | G52: 0.53738 | H52: 0.009749 | I52: -0.1462 | J52: 0.065984 | K52: -0.19413 | L52: -0.0934 | N52: 0.570747 | O52: 0.429253
B53: 7.966685 | C53: 4.520117 | D53: 2.896789 | E53: 3.026431 | F53: 3.096682 | G53: 2.065145 | H53: 2.623041 | I53: 1.601217 | J53: 2.735681 | K53: 2.379437 | L53: 1.950787 | N53: 34.86201 | O53: 14.13799

Sheet Var screening
A1: Factor 6 was excluded due to mixed loadings combining economic conditions and respondent characteristics, resulting in weak conceptual clarity.
A2: Factor 8 was excluded as it primarily reflects a single organizational characteristic rather than a latent delay factor.
A3: Factor 9 was excluded due to relatively weak and dispersed loadings, limiting its interpretability as a distinct delay risk dimension.
A4: Factor 10 was excluded due to moderate loadings and lower explanatory strength compared to retained factors.
A5: Factor 11 was excluded as it captures respondent qualifications rather than project delay drivers, and therefore does not represent an operational risk factor.

Sheet Reduced factor solution
A1: Factor Analysis - Principal Component Extraction
B5: 1.Delay in delivering material to construction site | C5: 2.Monopoly of material by some suppliers | D5: 3.Prices fluctuation | E5: 4.Types of material availability at local market | F5: 5.Lack of consultant’s knowledge of available materials | G5: 6.Low productivity | H5: 7.Poor work execution | I5: 8.Shortage of laborers | J5: 9.Mistakes happens during construction phase | K5: 10.Unavailability of equipment | L5: 11.Lack of engineering experience | M5: 12.Construction cost underestimation | N5: 13.Poor site management | O5: 14.Delayed payment for completed work | P5: 15.Cash flow problem during construction | Q5: 16.High rate of interest | R5: 17.Contractor’s financial difficulties | S5: 19.Change design | T5: 20.Errors and omission in design | U5: 21.Incomplete design drawings and specifications at tendering stage | V5: 22.Delay in preparation and approval of drawing | W5: 23.Inaccurate quantity take-off | X5: 24.Long period from planning of project to construction | Y5: 25.Delays in issuing information to the contractor during construction stage | Z5: 26.No practical use of earned value management system | AA5: 27.Lack of cost planning/monitoring during pre and post contract stage | AB5: 28.Poor communication between client, consultant and contractor | AC5: 29.Insufficient coordination between local authority who is responsible about road projects and service authorities | AD5: 30.Delays in decisions making by the approval authorities | AE5: 31.Change schedule | AF5: 32.Stoppages because of work being rejected by consultant | AG5: 33.Lowest bid price | AH5: 34.Insufficient time for preparation of contract documents | AI5: 35.Discrepancies in contract documents | AJ5: 36.Underestimation of time for completion of project | AK5: 37.Extension of time with cost claims | AL5: 38.Scope and specification changes | AM5: 39.Changes in client requirements | AN5: 40.Frequency of variation orders and additional works | AO5: 41.Rework due to error in execution | AP5: 42.Weather conditions | AQ5: 43.Accidents during construction | AR5: 44.Delay in getting NOCs from different government authorities | AS5: Location of organization | AT5: Relevant working experience
A6: Mean | B6: 3.08 | C6: 2.99 | D6: 2.74 | E6: 2.92 | F6: 2.83 | G6: 3.45 | H6: 3.53 | I6: 3.41 | J6: 3.33 | K6: 3.42 | L6: 3.51 | M6: 3.79 | N6: 3.77 | O6: 3.61 | P6: 3.63 | Q6: 3.17 | R6: 3.58 | S6: 3.81 | T6: 3.47 | U6: 3.52 | V6: 3.62 | W6: 3.64 | X6: 3.48 | Y6: 3.25 | Z6: 3.06 | AA6: 3.46 | AB6: 3.32 | AC6: 3.55 | AD6: 4.03 | AE6: 3.28 | AF6: 3.1 | AG6: 3.28 | AH6: 3.18 | AI6: 3.19 | AJ6: 3.66 | AK6: 3.65 | AL6: 3.94 | AM6: 4.07 | AN6: 3.91 | AO6: 3.56 | AP6: 2.49 | AQ6: 2.7 | AR6: 3.66 | AS6: 2.15 | AT6: 4.05
A7: Std dev | B7: 1.261996 | C7: 1.334781 | D7: 1.117803 | E7: 1.058144 | F7: 1.255893 | G7: 1.092402 | H7: 1.191544 | I7: 1.114803 | J7: 1.208982 | K7: 1.171328 | L7: 1.18004 | M7: 1.203593 | N7: 1.220092 | O7: 0.993181 | P7: 1.123866 | Q7: 1.227536 | R7: 1.1653 | S7: 1.00634 | T7: 1.143285 | U7: 1.073714 | V7: 0.991543 | W7: 0.996794 | X7: 0.998965 | Y7: 1.010289 | Z7: 0.984215 | AA7: 0.976983 | AB7: 1.236769 | AC7: 1.066304 | AD7: 0.934051 | AE7: 1.030558 | AF7: 1.09874 | AG7: 1.22252 | AH7: 1.142251 | AI7: 1.047808 | AJ7: 0.992536 | AK7: 0.994766 | AL7: 0.902081 | AM7: 0.954237 | AN7: 0.910882 | AO7: 1.03884 | AP7: 1.026872 | AQ7: 1.132335 | AR7: 1.100218 | AS7: 0.824858 | AT7: 1.121673
A8: Skewness | B8: -0.35981 | C8: 0.012937 | D8: -0.17796 | E8: -0.19224 | F8: -0.08853 | G8: -0.72048 | H8: -0.77222 | I8: -0.60971 | J8: -0.5607 | K8: -0.55018 | L8: -0.76867 | M8: -0.84061 | N8: -0.96303 | O8: -0.41448 | P8: -0.70587 | Q8: -0.23326 | R8: -0.72541 | S8: -0.72531 | T8: -0.56682 | U8: -0.46137 | V8: -0.45528 | W8: -0.64329 | X8: -0.18765 | Y8: -0.15061 | Z8: -0.1132 | AA8: -0.44213 | AB8: -0.47709 | AC8: -0.45599 | AD8: -0.79229 | AE8: -0.35032 | AF8: -0.30751 | AG8: -0.2018 | AH8: -0.04753 | AI8: -0.0886 | AJ8: -0.72844 | AK8: -0.55498 | AL8: -0.82294 | AM8: -0.733 | AN8: -0.4986 | AO8: -0.52387 | AP8: 0.285851 | AQ8: 0.497504 | AR8: -0.68377 | AS8: -0.29413 | AT8: -1.25133
A9: Kurtosis | B9: -1.08886 | C9: -1.14576 | D9: -0.71607 | E9: -0.40074 | F9: -1.02825 | G9: -0.18631 | H9: -0.2154 | I9: -0.10683 | J9: -0.57079 | K9: -0.34221 | L9: -0.19563 | M9: -0.13374 | N9: 0.028493 | O9: -0.15998 | P9: -0.20726 | Q9: -0.86994 | R9: -0.3229 | S9: 0.025995 | T9: -0.55378 | U9: -0.5538 | V9: -0.48209 | W9: 0.327286 | X9: -0.52799 | Y9: -0.43982 | Z9: -0.09886 | AA9: -0.28377 | AB9: -0.70887 | AC9: -0.47317 | AD9: 0.308968 | AE9: -0.36556 | AF9: -0.73755 | AG9: -0.92286 | AH9: -0.87091 | AI9: -0.75921 | AJ9: 0.279245 | AK9: -0.05006 | AL9: 0.384649 | AM9: -0.44941 | AN9: -0.26897 | AO9: -0.13618 | AP9: -0.4768 | AQ9: -0.48746 | AR9: -0.14256 | AS9: -1.47084 | AT9: 0.986304
A11: Correlation Matrix
B13: 1.Delay in delivering material to construction site | C13: 2.Monopoly of material by some suppliers | D13: 3.Prices fluctuation | E13: 4.Types of material availability at local market | F13: 5.Lack of consultant’s knowledge of available materials | G13: 6.Low productivity | H13: 7.Poor work execution | I13: 8.Shortage of laborers | J13: 9.Mistakes happens during construction phase | K13: 10.Unavailability of equipment | L13: 11.Lack of engineering experience | M13: 12.Construction cost underestimation | N13: 13.Poor site management | O13: 14.Delayed payment for completed work | P13: 15.Cash flow problem during construction | Q13: 16.High rate of interest | R13: 17.Contractor’s financial difficulties | S13: 19.Change design | T13: 20.Errors and omission in design | U13: 21.Incomplete design drawings and specifications at tendering stage | V13: 22.Delay in preparation and approval of drawing | W13: 23.Inaccurate quantity take-off | X13: 24.Long period from planning of project to construction | Y13: 25.Delays in issuing information to the contractor during construction stage | Z13: 26.No practical use of earned value management system | AA13: 27.Lack of cost planning/monitoring during pre and post contract stage | AB13: 28.Poor communication between client, consultant and contractor | AC13: 29.Insufficient coordination between local authority who is responsible about road projects and service authorities | AD13: 30.Delays in decisions making by the approval authorities | AE13: 31.Change schedule | AF13: 32.Stoppages because of work being rejected by consultant | AG13: 33.Lowest bid price | AH13: 34.Insufficient time for preparation of contract documents | AI13: 35.Discrepancies in contract documents | AJ13: 36.Underestimation of time for completion of project | AK13: 37.Extension of time with cost claims | AL13: 38.Scope and specification changes | AM13: 39.Changes in client requirements | AN13: 40.Frequency of variation orders and additional works | AO13: 41.Rework due to error in execution | AP13: 42.Weather conditions | AQ13: 43.Accidents during construction | AR13: 44.Delay in getting NOCs from different government authorities | AS13: Location of organization | AT13: Relevant working experience
A14: 1.Delay in delivering material to construction site | B14: 1 | C14: 0.617447 | D14: 0.213695 | E14: 0.673332 | F14: 0.374378 | G14: 0.484591 | H14: 0.538329 | I14: 0.547602 | J14: 0.402341 | K14: 0.470701 | L14: 0.436309 | M14: 0.308012 | N14: 0.276926 | O14: 0.125762 | P14: 0.184925 | Q14: 0.058699 | R14: 0.086557 | S14: 0.15312 | T14: 0.074863 | U14: 0.029097 | V14: 0.088645 | W14: -0.13842 | X14: -0.07117 | Y14: 0.263414 | Z14: 0.150097 | AA14: 0.273813 | AB14: 0.324388 | AC14: 0.186236 | AD14: 0.106013 | AE14: 0.022708 | AF14: 0.367218 | AG14: 0.400073 | AH14: 0.240698 | AI14: 0.287874 | AJ14: 0.313114 | AK14: 0.323179 | AL14: 0.103723 | AM14: 0.181608 | AN14: 0.159553 | AO14: 0.261497 | AP14: 0.344058 | AQ14: 0.42143 | AR14: 0.340472 | AS14: -0.065 | AT14: -0.15217
A15: 2.Monopoly of material by some suppliers | B15: 0.617447 | C15: 1 | D15: 0.334336 | E15: 0.558668 | F15: 0.426873 | G15: 0.343882 | H15: 0.384931 | I15: 0.393506 | J15: 0.314199 | K15: 0.362904 | L15: 0.427641 | M15: 0.197617 | N15: 0.297861 | O15: 0.101421 | P15: 0.199332 | Q15: 0.146866 | R15: 0.147563 | S15: 0.303899 | T15: 0.221947 | U15: 0.044296 | V15: -0.04365 | W15: 0.015877 | X15: -0.05185 | Y15: 0.231034 | Z15: -0.0423 | AA15: 0.209817 | AB15: 0.180847 | AC15: 0.073655 | AD15: -0.1077 | AE15: -0.07324 | AF15: 0.307204 | AG15: 0.300923 | AH15: 0.17474 | AI15: 0.148534 | AJ15: 0.322445 | AK15: 0.317957 | AL15: -0.13152 | AM15: 0.10813 | AN15: 0.033642 | AO15: 0.179366 | AP15: 0.335591 | AQ15: 0.421812 | AR15: 0.350091 | AS15: 0.154389 | AT15: -0.18119
A16: 3.Prices fluctuation | B16: 0.213695 | C16: 0.334336 | D16: 1 | E16: 0.511606 | F16: 0.39448 | G16: 0.34846 | H16: 0.413956 | I16: 0.279592 | J16: 0.400803 | K16: 0.230993 | L16: 0.382316 | M16: 0.358718 | N16: 0.36283 | O16: -0.0595 | P16: 0.002948 | Q16: 0.061672 | R16: 0.004653 | S16: 0.265123 | T16: 0.089193 | U16: 0.131057 | V16: 0.023002 | W16: 0.045399 | X16: 0.108239 | Y16: 0.039962 | Z16: 0.25724 | AA16: 0.18405 | AB16: 0.180387 | AC16: 0.076737 | AD16: -0.11429 | AE16: 0.051891 | AF16: 0.14818 | AG16: 0.174717 | AH16: 0.110398 | AI16: 0.061732 | AJ16: 0.251131 | AK16: 0.088153 | AL16: 0.144634 | AM16: 0.205128 | AN16: -0.0201 | AO16: 0.223326 | AP16: 0.109573 | AQ16: 0.178412 | AR16: -0.00079 | AS16: 0.235288 | AT16: -0.25457
A17: 4.Types of material availability at local market | B17: 0.673332 | C17: 0.558668 | D17: 0.511606 | E17: 1 | F17: 0.55855 | G17: 0.527909 | H17: 0.625926 | I17: 0.531127 | J17: 0.392543 | K17: 0.462761 | L17: 0.515672 | M17: 0.360599 | N17: 0.448709 | O17: 0.099347 | P17: 0.17308 | Q17: 0.147487 | R17: 0.134703 | S17: 0.212299 | T17: 0.153376 | U17: 0.110675 | V17: 0.035865 | W17: 0.063933 | X17: -0.02161 | Y17: 0.30702 | Z17: 0.269866 | AA17: 0.390218 | AB17: 0.374996 | AC17: 0.146989 | AD17: 0.160056 | AE17: 0.153899 | AF17: 0.404253 | AG17: 0.415851 | AH17: 0.303602 | AI17: 0.278869 | AJ17: 0.341506 | AK17: 0.248039 | AL17: 0.120219 | AM17: 0.231206 | AN17: 0.024896 | AO17: 0.312467 | AP17: 0.389342 | AQ17: 0.430293 | AR17: 0.222421 | AS17: 0.05624 | AT17: -0.15982
A18: 5.Lack of consultant’s knowledge of available materials | B18: 0.374378 | C18: 0.426873 | D18: 0.39448 | E18: 0.55855 | F18: 1 | G18: 0.426822 | H18: 0.516328 | I18: 0.421754 | J18: 0.550363 | K18: 0.394762 | L18: 0.497702 | M18: 0.490624 | N18: 0.553822 | O18: 0.163971 | P18: 0.177539 | Q18: 0.433905 | R18: 0.051387 | S18: 0.467038 | T18: 0.437446 | U18: 0.410275 | V18: 0.285149 | W18: 0.348235 | X18: 0.042098 | Y18: 0.426336 | Z18: 0.454197 | AA18: 0.45199 | AB18: 0.434222 | AC18: 0.228668 | AD18: 0.088695 | AE18: 0.235763 | AF18: 0.500686 | AG18: 0.357036 | AH18: 0.414392 | AI18: 0.402695 | AJ18: 0.2871 | AK18: 0.274633 | AL18: 0.227963 | AM18: 0.335344 | AN18: 0.188694 | AO18: 0.315329 | AP18: 0.410886 | AQ18: 0.380858 | AR18: 0.2323 | AS18: 0.03796 | AT18: -0.18844
A19: 6.Low productivity | B19: 0.484591 | C19: 0.343882 | D19: 0.34846 | E19: 0.527909 | F19: 0.426822 | G19: 1 | H19: 0.82122 | I19: 0.724846 | J19: 0.702263 | K19: 0.546242 | L19: 0.65229 | M19: 0.660151 | N19: 0.675342 | O19: 0.08175 | P19: 0.098779 | Q19: 0.233492 | R19: 0.043609 | S19: 0.373471 | T19: 0.18297 | U19: 0.094957 | V19: 0.099699 | W19: 0.07354 | X19: -0.05932 | Y19: 0.403001 | Z19: 0.258229 | AA19: 0.444134 | AB19: 0.370043 | AC19: 0.382941 | AD19: 0.111805 | AE19: 0.093861 | AF19: 0.327582 | AG19: 0.161801 | AH19: 0.359979 | AI19: 0.366204 | AJ19: 0.456326 | AK19: 0.167462 | AL19: 0.203022 | AM19: 0.242078 | AN19: 0.170312 | AO19: 0.374298 | AP19: 0.281705 | AQ19: 0.233685 | AR19: 0.217358 | AS19: -0.1268 | AT19: 0.093833
A20: 7.Poor work execution | B20: 0.538329 | C20: 0.384931 | D20: 0.413956 | E20: 0.625926 | F20: 0.516328 | G20: 0.82122 | H20: 1 | I20: 0.606889 | J20: 0.681291 | K20: 0.54631 | L20: 0.67464 | M20: 0.594184 | N20: 0.692462 | O20: 0.199402 | P20: 0.18836 | Q20: 0.266013 | R20: 0.134551 | S20: 0.424654 | T20: 0.231783 | U20: 0.154811 | V20: 0.187002 | W20: 0.086875 | X20: 0.029888 | Y20: 0.424424 | Z20: 0.324708 | AA20: 0.536029 | AB20: 0.458468 | AC20: 0.36675 | AD20: 0.265599 | AE20: 0.112323 | AF20: 0.428292 | AG20: 0.327125 | AH20: 0.38895 | AI20: 0.463202 | AJ20: 0.483567 | AK20: 0.192141 | AL20: 0.231245 | AM20: 0.346915 | AN20: 0.166011 | AO20: 0.482768 | AP20: 0.306286 | AQ20: 0.300448 | AR20: 0.332622 | AS20: -0.08863 | AT20: -0.02331
A21: 8.Shortage of laborers | B21: 0.547602 | C21: 0.393506 | D21: 0.279592 | E21: 0.531127 | F21: 0.421754 | G21: 0.724846 | H21: 0.606889 | I21: 1 | J21: 0.637295 | K21: 0.692857 | L21: 0.610079 | M21: 0.660787 | N21: 0.543651 | O21: 0.24175 | P21: 0.160673 | Q21: 0.254432 | R21: 0.074707 | S21: 0.343841 | T21: 0.20507 | U21: 0.092432 | V21: 0.119919 | W21: -0.05228 | X21: -0.0863 | Y21: 0.355575 | Z21: 0.332783 | AA21: 0.318246 | AB21: 0.435951 | AC21: 0.309141 | AD21: 0.15158 | AE21: 0.264405 | AF21: 0.290272 | AG21: 0.314764 | AH21: 0.428882 | AI21: 0.331026 | AJ21: 0.245979 | AK21: 0.198476 | AL21: 0.259149 | AM21: 0.272815 | AN21: 0.196012 | AO21: 0.19772 | AP21: 0.359866 | AQ21: 0.31944 | AR21: 0.331813 | AS21: -0.12448 | AT21: 0.058905
A22: 9.Mistakes happens during construction phase | B22: 0.402341 | C22: 0.314199 | D22: 0.400803 | E22: 0.392543 | F22: 0.550363 | G22: 0.702263 | H22: 0.681291 | I22: 0.637295 | J22: 1 | K22: 0.602859 | L22: 0.640484 | M22: 0.716775 | N22: 0.57909 | O22: -0.06243 | P22: 0.05619 | Q22: 0.30667 | R22: -0.10843 | S22: 0.463957 | T22: 0.354787 | U22: 0.182947 | V22: 0.175382 | W22: 0.260035 | X22: 0.04027 | Y22: 0.337708 | Z22: 0.380576 | AA22: 0.475915 | AB22: 0.486931 | AC22: 0.362106 | AD22: 0.041629 | AE22: 0.166739 | AF22: 0.389531 | AG22: 0.217027 | AH22: 0.38808 | AI22: 0.440433 | AJ22: 0.510131 | AK22: 0.101647 | AL22: 0.173653 | AM22: 0.276445 | AN22: 0.244472 | AO22: 0.358397 | AP22: 0.346162 | AQ22: 0.320782 | AR22: 0.107286 | AS22: -0.03594 | AT22: -0.10373
A23: 10.Unavailability of equipment | B23: 0.470701 | C23: 0.362904 | D23: 0.230993 | E23: 0.462761 | F23: 0.394762 | G23: 0.546242 | H23: 0.54631 | I23: 0.692857 | J23: 0.602859 | K23: 1 | L23: 0.534699 | M23: 0.592702 | N23: 0.392132 | O23: 0.240034 | P23: 0.362282 | Q23: 0.338058 | R23: 0.334682 | S23: 0.201274 | T23: 0.231534 | U23: 0.19579 | V23: 0.196954 | W23: 0.135718 | X23: -0.09845 | Y23: 0.278545 | Z23: 0.355037 | AA23: 0.526397 | AB23: 0.641276 | AC23: 0.418262 | AD23: 0.066973 | AE23: 0.263137 | AF23: 0.326977 | AG23: 0.329632 | AH23: 0.398407 | AI23: 0.35683 | AJ23: 0.255843 | AK23: 0.242508 | AL23: 0.248417 | AM23: 0.36385 | AN23: 0.263656 | AO23: 0.258042 | AP23: 0.394698 | AQ23: 0.264021 | AR23: 0.369401 | AS23: -0.15021 | AT23: -0.07452
A24: 11.Lack of engineering experience | B24: 0.436309 | C24: 0.427641 | D24: 0.382316 | E24: 0.515672 | F24: 0.497702 | G24: 0.65229 | H24: 0.67464 | I24: 0.610079 | J24: 0.640484 | K24: 0.534699 | L24: 1 | M24: 0.673701 | N24: 0.742574 | O24: 0.15664 | P24: 0.231625 | Q24: 0.39417 | R24: 0.170229 | S24: 0.367693 | T24: 0.292584 | U24: 0.274944 | V24: -0.0177 | W24: 0.109076 | X24: 0.129685 | Y24: 0.366931 | Z24: 0.309221 | AA24: 0.457121 | AB24: 0.50896 | AC24: 0.334607 | AD24: 0.159702 | AE24: 0.073713 | AF24: 0.260559 | AG24: 0.187557 | AH24: 0.442714 | AI24: 0.486403 | AJ24: 0.426793 | AK24: 0.192961 | AL24: 0.017981 | AM24: 0.209146 | AN24: 0.124185 | AO24: 0.466641 | AP24: 0.383385 | AQ24: 0.435719 | AR24: 0.23868 | AS24: -0.10328 | AT24: 0.004912
A25: 12.Construction cost underestimation | B25: 0.308012 | C25: 0.197617 | D25: 0.358718 | E25: 0.360599 | F25: 0.490624 | G25: 0.660151 | H25: 0.594184 | I25: 0.660787 | J25: 0.716775 | K25: 0.592702 | L25: 0.673701 | M25: 1 | N25: 0.708867 | O25: 0.007546 | P25: 0.051844 | Q25: 0.37198 | R25: 0.010037 | S25: 0.439861 | T25: 0.249239 | U25: 0.302513 | V25: 0.224564 | W25: 0.195931 | X25: 0.089976 | Y25: 0.301563 | Z25: 0.385961 | AA25: 0.439367 | AB25: 0.446511 | AC25: 0.331241 | AD25: 0.086707 | AE25: 0.208261 | AF25: 0.304288 | AG25: 0.229953 | AH25: 0.461196 | AI25: 0.434186 | AJ25: 0.411536 | AK25: 0.065903 | AL25: 0.369358 | AM25: 0.420076 | AN25: 0.276308 | AO25: 0.392301 | AP25: 0.404163 | AQ25: 0.433821 | AR25: 0.187331 | AS25: -0.17828 | AT25: -0.03834
... A58: Relevant working experience | B58: -0.15217 | C58: -0.18119 | D58: -0.25457 | E58: -0.15982 | F58: -0.18844 | G58: 0.093833 | H58: -0.02331 | I58: 0.058905 | J58: -0.10373 | K58: -0.07452 | L58: 0.004912 | M58: -0.03834 | N58: 0.025722 | O58: 0.139253 | P58: -0.04215 | Q58: 0.075759 | R58: -0.0008 | S58: -0.02685 | T58: -0.10233 | U58: -0.10469 | V58: -0.10628 | W58: -0.12527 | X58: -0.0794 | Y58: 0.031313 | Z58: -0.05293 | AA58: -0.1027 | AB58: -0.09904 | AC58: -0.04329 | AD58: -0.00079 | AE58: -0.01927 | AF58: -0.03121 | AG58: -0.21396 | AH58: 0.018106 | AI58: 0.025474 | AJ58: -0.06804 | AK58: -0.0748 | AL58: -0.1039 | AM58: -0.12221 | AN58: -0.07477 | AO58: -0.04059 | AP58: -0.07443 | AQ58: -0.22453 | AR58: -0.02073 | AS58: -0.0357 | AT58: 1
B59: 4.246842 | C59: 3.320428 | D59: 2.255776 | E59: 5.220122 | F59: 6.172765 | G59: 6.357509 | H59: 7.491631 | I59: 6.09855 | J59: 6.69014 | K59: 6.1092 | L59: 6.853152 | M59: 6.741862 | N59: 6.359313 | O59: 2.56826 | P59: 3.511436 | Q59: 4.535595 | R59: 2.322142 | S59: 4.550833 | T59: 4.331501 | U59: 4.177802 | V59: 3.059908 | W59: 2.950592 | X59: 0.900143 | Y59: 5.193314 | Z59: 4.760238 | AA59: 6.929866 | AB59: 5.936491 | AC59: 3.2537 | AD59: 2.112584 | AE59: 2.955571 | AF59: 4.561587 | AG59: 2.182358 | AH59: 5.670787 | AI59: 5.345282 | AJ59: 3.381428 | AK59: 2.140692 | AL59: 2.573149 | AM59: 3.212254 | AN59: 2.3284 | AO59: 3.528989 | AP59: 5.028425 | AQ59: 3.41878 | AR59: 3.122772 | AS59: 0.699455 | AT59: 0.470446 | AU59: 185.6321
A61: Inverse of Correlation Matrix
B63: 1.Delay in delivering material to construction site | C63: 2.Monopoly of material by some suppliers | D63: 3.Prices fluctuation | E63: 4.Types of material availability at local market | F63: 5.Lack of consultant’s knowledge of available materials | G63: 6.Low productivity | H63: 7.Poor work execution | I63: 8.Shortage of laborers | J63: 9.Mistakes happens during construction phase | K63: 10.Unavailability of equipment | L63: 11.Lack of engineering experience | M63: 12.Construction cost underestimation | N63: 13.Poor site management | O63: 14.Delayed payment for completed work | P63: 15.Cash flow problem during construction | Q63: 16.High rate of interest | R63: 17.Contractor’s financial difficulties | S63: 19.Change design | T63: 20.Errors and omission in design | U63: 21.Incomplete design drawings and specifications at tendering stage | V63: 22.Delay in preparation and approval of drawing | W63: 23.Inaccurate quantity take-off | X63: 24.Long period from planning of project to construction | Y63: 25.Delays in issuing information to the contractor during construction stage | Z63: 26.No practical use of earned value management system | AA63: 27.Lack of cost planning/monitoring during pre and post contract stage | AB63: 28.Poor communication between client, consultant and contractor | AC63: 29.Insufficient coordination between local authority who is responsible about road projects and service authorities | AD63: 30.Delays in decisions making by the approval authorities | AE63: 31.Change schedule | AF63: 32.Stoppages because of work being rejected by consultant | AG63: 33.Lowest bid price | AH63: 34.Insufficient time for preparation of contract documents | AI63: 35.Discrepancies in contract documents | AJ63: 36.Underestimation of time for completion of project | AK63: 37.Extension of time with cost claims | AL63: 38.Scope and specification changes | AM63: 39.Changes in client requirements | AN63: 40.Frequency of variation orders and additional works | AO63: 41.Rework due to error in execution | AP63: 42.Weather conditions | AQ63: 43.Accidents during construction | AR63: 44.Delay in getting NOCs from different government authorities | AS63: Location of organization | AT63: Relevant working experience | AV63: sqrt(diag)
A64: 1.Delay in delivering material to construction site | B64: 4.625921 | C64: -1.60498 | D64: 0.907135 | E64: -1.57881 | F64: 0.323775 | G64: -0.91453 | H64: 0.069129 | I64: -0.37141 | J64: -0.94043 | K64: 0.013259 | L64: 0.138234 | M64: -0.27848 | N64: 1.159585 | O64: -0.13161 | P64: -0.56877 | Q64: 0.677967 | R64: 0.31961 | S64: 0.865304 | T64: 0.528233 | U64: -0.79227 | V64: -0.39179 | W64: 1.516412 | X64: -0.37385 | Y64: -0.76085 | Z64: -0.84446 | AA64: 0.912763 | AB64: 0.004959 | AC64: 0.217228 | AD64: -0.12589 | AE64: 0.505305 | AF64: -0.76892 | AG64: -0.38313 | AH64: 0.881286 | AI64: -0.75494 | AJ64: 0.022978 | AK64: -0.30264 | AL64: 0.43948 | AM64: -0.40812 | AN64: -0.17109 | AO64: -0.74407 | AP64: -0.59656 | AQ64: -0.08476 | AR64: 0.096106 | AS64: -0.01677 | AT64: 0.339915 | AV64: 2.150795
A65: 2.Monopoly of material by some suppliers | B65: -1.60498 | C65: 4.511733 | D65: -0.57771 | E65: -0.1915 | F65: -0.70926 | G65: 0.833987 | H65: -0.04411 | I65: -1.51711 | J65: 0.779811 | K65: 0.365234 | L65: -0.75284 | M65: 1.460216 | N65: -0.6556 | O65: 1.264017 | P65: -0.81139 | Q65: -0.48079 | R65: -0.6046 | S65: -1.32011 | T65: -0.09661 | U65: 0.711481 | V65: -0.35035 | W65: -0.35062 | X65: 0.43938 | Y65: 0.080503 | Z65: 1.182166 | AA65: -0.84953 | AB65: 0.305866 | AC65: -0.30408 | AD65: 1.459385 | AE65: -0.33022 | AF65: 0.391031 | AG65: -0.28063 | AH65: 0.600216 | AI65: 0.504272 | AJ65: -0.78341 | AK65: -0.24675 | AL65: 1.083862 | AM65: -0.62742 | AN65: -0.44779 | AO65: 0.424367 | AP65: 0.172614 | AQ65: -0.8386 | AR65: -0.79756 | AS65: -0.02881 | AT65: -0.06666 | AV65: 2.124084
A66: 3.Prices fluctuation | B66: 0.907135 | C66: -0.57771 | D66: 3.109929 | E66: -1.66103 | F66: 0.327171 | G66: -0.31571 | H66: -0.28972 | I66: 1.027586 | J66: -1.30162 | K66: 0.372767 | L66: -0.20362 | M66: -0.30366 | N66: -0.55848 | O66: 0.019217 | P66: -0.10953 | Q66: 0.194312 | R66: -0.09341 | S66: -0.06608 | T66: -0.03948 | U66: -0.25601 | V66: -0.36048 | W66: 0.823182 | X66: -0.48896 | Y66: 0.616299 | Z66: -1.14647 | AA66: 0.864546 | AB66: 0.038153 | AC66: -0.48252 | AD66: 0.830252 | AE66: -0.32029 | AF66: 0.469731 | AG66: -0.38584 | AH66: -0.18885 | AI66: 0.919197 | AJ66: 0.242458 | AK66: -0.2851 | AL66: -0.27993 | AM66: -0.02746 | AN66: 0.664487 | AO66: -0.36842 | AP66: -0.36634 | AQ66: 0.336384 | AR66: -0.21282 | AS66: -0.67946 | AT66: 0.366705 | AV66: 1.763499
A67: 4.Types of material availability at local market | B67: -1.57881 | C67: -0.1915 | D67: -1.66103 | E67: 5.617336 | F67: -1.69439 | G67: -0.57592 | H67: -1.71398 | I67: -1.64536 | J67: 3.386577 | K67: -0.84961 | L67: -0.30469 | M67: 1.068561 | N67: 0.220541 | O67: 0.986095 | P67: -1.28068 | Q67: 0.477747 | R67: 1.015232 | S67: -0.15402 | T67: 0.762063 | U67: -0.00939 | V67: 0.329767 | W67: -1.07748 | X67: 0.026848 | Y67: 0.272272 | Z67: 0.34532 | AA67: -0.5316 | AB67: -0.93533 | AC67: 0.909155 | AD67: -0.91411 | AE67: -0.43649 | AF67: 0.208718 | AG67: -0.56885 | AH67: 0.410843 | AI67: -0.16761 | AJ67: -0.97549 | AK67: 0.422785 | AL67: 0.20597 | AM67: 0.051635 | AN67: -0.23694 | AO67: 0.432188 | AP67: -0.48898 | AQ67: -0.61933 | AR67: 1.079331 | AS67: -0.18572 | AT67: -0.32771 | AV67: 2.370092
A68: 5.Lack of consultant’s knowledge of available materials | B68: 0.323775 | C68: -0.70926 | D68: 0.327171 | E68: -1.69439 | F68: 5.103568 | G68: -0.27625 | H68: 1.72632 | I68: 1.244343 | J68: -2.7026 | K68: 0.772456 | L68: 0.60618 | M68: -0.04691 | N68: -2.24351 | O68: -1.91369 | P68: 1.870248 | Q68: -0.47879 | R68: 0.009622 | S68: 0.561579 | T68: -0.37424 | U68: -0.5959 | V68: 0.355116 | W68: -0.37461 | X68: 0.539163 | Y68: -0.51849 | Z68: -1.53258 | AA68: 0.979668 | AB68: -0.60966 | AC68: 0.066727 | AD68: 0.581228 | AE68: 1.963879 | AF68: -1.56154 | AG68: -0.7147 | AH68: -0.40162 | AI68: -0.51819 | AJ68: 1.538942 | AK68: -1.01562 | AL68: -0.28128 | AM68: -1.33263 | AN68: 1.448314 | AO68: -0.12201 | AP68: -0.88989 | AQ68: 1.081937 | AR68: -0.31675 | AS68: -0.12666 | AT68: 0.788586 | AV68: 2.259108
A69: 6.Low productivity | B69: -0.91453 | C69: 0.833987 | D69: -0.31571 | E69: -0.57592 | F69: -0.27625 | G69: 8.320938 | H69: -4.41003 | I69: -2.98282 | J69: 0.166965 | K69: 0.512874 | L69: -0.02525 | M69: -0.52096 | N69: -0.81334 | O69: 1.045724 | P69: 0.323118 | Q69: -0.59721 | R69: -0.77647 | S69: -0.64543 | T69: -0.33213 | U69: 0.741114 | V69: -0.14175 | W69: -0.34826 | X69: 0.721003 | Y69: -0.03032 | Z69: 1.38112 | AA69: -1.62091 | AB69: 1.449 | AC69: -2.00337 | AD69: 0.894111 | AE69: -0.49227 | AF69: 0.253654 | AG69: 1.284022 | AH69: -0.88855 | AI69: 1.327661 | AJ69: -0.7039 | AK69: -0.58026 | AL69: -0.17904 | AM69: 1.329353 | AN69: -0.97622 | AO69: 0.46535 | AP69: 1.241074 | AQ69: -0.35684 | AR69: 0.687254 | AS69: 0.793827 | AT69: -0.65258 | AV69: 2.884604
A70: 7.Poor work execution | B70: 0.069129 | C70: -0.04411 | D70: -0.28972 | E70: -1.71398 | F70: 1.72632 | G70: -4.41003 | H70: 9.37512 | I70: 2.869223 | J70: -3.63457 | K70: -0.60926 | L70: -0.54696 | M70: 0.921514 | N70: -1.37712 | O70: -2.63529 | P70: 2.348471 | Q70: 0.45737 | R70: -0.80301 | S70: -0.49475 | T70: 0.2262 | U70: 0.421316 | V70: 0.032901 | W70: 0.804015 | X70: 0.384551 | Y70: -1.26632 | Z70: -0.98238 | AA70: 0.801344 | AB70: -0.46562 | AC70: 0.854821 | AD70: -0.87922 | AE70: 2.145484 | AF70: -2.17251 | AG70: -0.20272 | AH70: -0.30455 | AI70: -0.97464 | AJ70: 1.18967 | AK70: 0.052912 | AL70: -0.43057 | AM70: -2.09242 | AN70: 2.011137 | AO70: -1.17426 | AP70: -0.61573 | AQ70: 1.043487 | AR70: -0.80139 | AS70: 0.400349 | AT70: 0.807914 | AV70: 3.061882
A71: 8.Shortage of laborers | B71: -0.37141 | C71: -1.51711 | D71: 1.027586 | E71: -1.64536 | F71: 1.244343 | G71: -2.98282 | H71: 2.869223 | I71: 8.932024 | J71: -3.53198 | K71: -2.18747 | L71: -0.73443 | M71: -1.90137 | N71: -0.68466 | O71: -2.29013 | P71: 2.122472 | Q71: 1.394528 | R71: -0.90906 | S71: -0.5916 | T71: -1.20949 | U71: 1.611672 | V71: 0.470014 | W71: 1.190047 | X71: 0.240602 | Y71: -0.86784 | Z71: -2.11324 | AA71: 2.197905 | AB71: -0.08454 | AC71: 0.364439 | AD71: -0.9784 | AE71: 0.499655 | AF71: -0.44415 | AG71: 0.468763 | AH71: -2.45789 | AI71: 1.004388 | AJ71: 2.685573 | AK71: -0.57349 | AL71: -1.9134 | AM71: 0.373277 | AN71: 1.512512 | AO71: -0.20202 | AP71: -0.23627 | AQ71: 0.53156 | AR71: -0.34394 | AS71: -0.13538 | AT71: 0.134492 | AV71: 2.988649
A72: 9.Mistakes happens during construction phase | B72: -0.94043 | C72: 0.779811 | D72: -1.30162 | E72: 3.386577 | F72: -2.7026 | G72: 0.166965 | H72: -3.63457 | I72: -3.53198 | J72: 9.89475 | K72: -2.05245 | L72: -1.06777 | M72: 0.218041 | N72: 0.858558 | O72: 2.677148 | P72: -3.2272 | Q72: -0.37236 | R72: 3.146878 | S72: -1.27877 | T72: 0.58086 | U72: 1.169421 | V72: -0.71179 | W72: -1.61184 | X72: -0.67579 | Y72: 1.450412 | Z72: 1.276076 | AA72: -1.57138 | AB72: -0.86913 | AC72: -0.00249 | AD72: -0.24974 | AE72: -1.32495 | AF72: 0.661959 | AG72: 0.286454 | AH72: 1.00075 | AI72: -0.40981 | AJ72: -2.68499 | AK72: 0.528899 | AL72: 0.676764 | AM72: 1.206777 | AN72: -1.92266 | AO72: 1.247708 | AP72: 0.959486 | AQ72: -1.37896 | AR72: 1.692025 | AS72: -0.50908 | AT72: -0.40705 | AV72: 3.145592
A73: 10.Unavailability of equipment | B73: 0.013259 | C73: 0.365234 | D73: 0.372767 | E73: -0.84961 | F73: 0.772456 | G73: 0.512874 | H73: -0.60926 | I73: -2.18747 | J73: -2.05245 | K73: 6.510985 | L73: -0.12482 | M73: -1.94775 | N73: 1.18619 | O73: 0.1526 | P73: -0.48865 | Q73: -0.57989 | R73: -1.41156 | S73: 1.220977 | T73: -0.59132 | U73: 0.140252 | V73: 0.380882 | W73: -0.43114 | X73: 0.634601 | Y73: 0.347733 | Z73: 0.298584 | AA73: -1.31848 | AB73: -0.84144 | AC73: 0.106803 | AD73: 1.482717 | AE73: 0.045965 | AF73: 0.234553 | AG73: -1.03344 | AH73: 1.073027 | AI73: 0.201876 | AJ73: 0.932807 | AK73: -0.26438 | AL73: 0.628454 | AM73: -0.97987 | AN73: -0.28609 | AO73: -0.12624 | AP73: -1.10335 | AQ73: 1.206378 | AR73: -1.28902 | AS73: -0.04574 | AT73: 0.1095 | AV73: 2.551663
A74: 11.Lack of engineering experience | B74: 0.138234 | C74: -0.75284 | D74: -0.20362 | E74: -0.30469 | F74: 0.60618 | G74: -0.02525 | H74: -0.54696 | I74: -0.73443 | J74: -1.06777 | K74: -0.12482 | L74: 6.348883 | M74: -0.82619 | N74: -1.8727 | O74: -0.92839 | P74: 0.625139 | Q74: -0.58366 | R74: -0.23925 | S74: 0.788833 | T74: -0.01657 | U74: -2.16137 | V74: 1.317534 | W74: 0.698157 | X74: -0.33728 | Y74: -0.3045 | Z74: -0.54073 | AA74: 0.687666 | AB74: -0.47469 | AC74: -0.48777 | AD74: 0.114033 | AE74: 0.656458 | AF74: 0.716586 | AG74: -0.56097 | AH74: 0.547522 | AI74: -0.99143 | AJ74: -0.19263 | AK74: -0.04481 | AL74: 1.248267 | AM74: 0.303123 | AN74: 0.047467 | AO74: -0.95461 | AP74: -0.54103 | AQ74: -0.11491 | AR74: 0.532366 | AS74: 0.144421 | AT74: -0.03094 | AV74: 2.519699
A75: 12.Construction cost underestimation | B75: -0.27848 | C75: 1.460216 | D75: -0.30366 | E75: 1.068561 | F75: -0.04691 | G75: -0.52096 | H75: 0.921514 | I75: -1.90137 | J75: 0.218041 | K75: -1.94775 | L75: -0.82619 | M75: 7.75171 | N75: -2.74934 | O75: 1.130513 | P75: 0.063095 | Q75: -0.64317 | R75: 0.450312 | S75: -1.5041 | T75: 1.171993 | U75: -1.28303 | V75: -1.14731 | W75: 0.008014 | X75: -0.07209 | Y75: 0.455189 | Z75: 0.139246 | AA75: 0.51233 | AB75: -0.00993 | AC75: -0.69672 | AD75: 0.929092 | AE75: -0.16924 | AF75: 0.711181 | AG75: -0.85303 | AH75: 0.33745 | AI75: 0.301345 | AJ75: -2.07788 | AK75: 0.921813 | AL75: -0.39501 | AM75: -0.85011 | AN75: 0.923105 | AO75: -0.01803 | AP75: -0.60985 | AQ75: -1.37946 | AR75: 0.296105 | AS75: 0.614639 | AT75: -0.18663 | AV75: 2.784189
... A108: Relevant working experience | B108: 0.339915 | C108: -0.06666 | D108: 0.366705 | E108: -0.32771 | F108: 0.788586 | G108: -0.65258 | H108: 0.807914 | I108: 0.134492 | J108: -0.40705 | K108: 0.1095 | L108: -0.03094 | M108: -0.18663 | N108: -0.21703 | O108: -1.20118 | P108: 0.764596 | Q108: -0.04572 | R108: 0.019001 | S108: 0.0533 | T108: 0.406201 | U108: -0.09554 | V108: 0.404134 | W108: 0.059524 | X108: 0.026817 | Y108: -0.35075 | Z108: -0.43679 | AA108: 0.293306 | AB108: 0.008817 | AC108: 0.253307 | AD108: 0.003525 | AE108: 0.744755 | AF108: -0.95278 | AG108: 0.343385 | AH108: -0.15914 | AI108: -0.54648 | AJ108: 0.429139 | AK108: -0.08267 | AL108: 0.206751 | AM108: -0.62792 | AN108: 0.367123 | AO108: -0.0326 | AP108: -0.51416 | AQ108: 0.848795 | AR108: -0.0222 | AS108: -0.04615 | AT108: 1.803205 | AV108: 1.342835
A110: Partial Correlation Matrix
B112: 1.Delay in delivering material to construction site | C112: 2.Monopoly of material by some suppliers | D112: 3.Prices fluctuation | E112: 4.Types of material availability at local market | F112: 5.Lack of consultant’s knowledge of available materials | G112: 6.Low productivity | H112: 7.Poor work execution | I112: 8.Shortage of laborers | J112: 9.Mistakes happens during construction phase | K112: 10.Unavailability of equipment | L112: 11.Lack of engineering experience | M112: 12.Construction cost underestimation | N112: 13.Poor site management | O112: 14.Delayed payment for completed work | P112: 15.Cash flow problem during construction | Q112: 16.High rate of interest | R112: 17.Contractor’s financial difficulties | S112: 19.Change design | T112: 20.Errors and omission in design | U112: 21.Incomplete design drawings and specifications at tendering stage | V112: 22.Delay in preparation and approval of drawing | W112: 23.Inaccurate quantity take-off | X112: 24.Long period from planning of project to construction | Y112: 25.Delays in issuing information to the contractor during construction stage | Z112: 26.No practical use of earned value management system | AA112: 27.Lack of cost planning/monitoring during pre and post contract stage | AB112: 28.Poor communication between client, consultant and contractor | AC112: 29.Insufficient coordination between local authority who is responsible about road projects and service authorities | AD112: 30.Delays in decisions making by the approval authorities | AE112: 31.Change schedule | AF112: 32.Stoppages because of work being rejected by consultant | AG112: 33.Lowest bid price | AH112: 34.Insufficient time for preparation of contract documents | AI112: 35.Discrepancies in contract documents | AJ112: 36.Underestimation of time for completion of project | AK112: 37.Extension of time with cost claims | AL112: 38.Scope and specification changes | AM112: 39.Changes in client requirements | AN112: 40.Frequency of variation orders and additional works | AO112: 41.Rework due to error in execution | AP112: 42.Weather conditions | AQ112: 43.Accidents during construction | AR112: 44.Delay in getting NOCs from different government authorities | AS112: Location of organization | AT112: Relevant working experience
A113: 1.Delay in delivering material to construction site | B113: 1 | C113: 0.351317 | D113: -0.23916 | E113: 0.309717 | F113: -0.06664 | G113: 0.147406 | H113: -0.0105 | I113: 0.05778 | J113: 0.139003 | K113: -0.00242 | L113: -0.02551 | M113: 0.046505 | N113: -0.20881 | O113: 0.023703 | P113: 0.10184 | Q113: -0.16268 | R113: -0.07208 | S113: -0.17682 | T113: -0.11192 | U113: 0.145166 | V113: 0.099136 | W113: -0.34273 | X113: 0.117249 | Y113: 0.1758 | Z113: 0.187908 | AA113: -0.18395 | AB113: -0.00102 | AC113: -0.04817 | AD113: 0.031999 | AE113: -0.11573 | AF113: 0.151003 | AG113: 0.088106 | AH113: -0.15281 | AI113: 0.149694 | AJ113: -0.00465 | AK113: 0.078745 | AL113: -0.09851 | AM113: 0.084964 | AN113: 0.041774 | AO113: 0.193241 | AP113: 0.102608 | AQ113: 0.018384 | AR113: -0.02288 | AS113: 0.005476 | AT113: -0.11769
A114: 2.Monopoly of material by some suppliers | B114: 0.351317 | C114: 1 | D114: 0.154229 | E114: 0.038038 | F114: 0.147807 | G114: -0.13611 | H114: 0.006782 | I114: 0.238985 | J114: -0.11671 | K114: -0.06739 | L114: 0.140664 | M114: -0.24691 | N114: 0.119543 | O114: -0.23051 | P114: 0.147108 | Q114: 0.116816 | R114: 0.13806 | S114: 0.27315 | T114: 0.020728 | U114: -0.132 | V114: 0.089765 | W114: 0.080241 | X114: -0.13953 | Y114: -0.01883 | Z114: -0.26636 | AA114: 0.173364 | AB114: -0.06398 | AC114: 0.068271 | AD114: -0.37562 | AE114: 0.076578 | AF114: -0.07776 | AG114: 0.065346 | AH114: -0.10538 | AI114: -0.10125 | AJ114: 0.160522 | AK114: 0.065008 | AL114: -0.246 | AM114: 0.13226 | AN114: 0.110708 | AO114: -0.1116 | AP114: -0.03006 | AQ114: 0.184171 | AR114: 0.192271 | AS114: 0.009524 | AT114: 0.023369
A115: 3.Prices fluctuation | B115: -0.23916 | C115: 0.154229 | D115: 1 | E115: 0.397407 | F115: -0.08212 | G115: 0.062063 | H115: 0.053656 | I115: -0.19497 | J115: 0.234642 | K115: -0.08284 | L115: 0.045824 | M115: 0.061847 | N115: 0.122655 | O115: -0.00422 | P115: 0.023918 | Q115: -0.05686 | R115: 0.025692 | S115: 0.016468 | T115: 0.010201 | U115: 0.057209 | V115: 0.111246 | W115: -0.22691 | X115: 0.187032 | Y115: -0.17367 | Z115: 0.311139 | AA115: -0.2125 | AB115: -0.00961 | AC115: 0.130485 | AD115: -0.25739 | AE115: 0.089462 | AF115: -0.11251 | AG115: 0.108218 | AH115: 0.039938 | AI115: -0.22229 | AJ115: -0.05984 | AK115: 0.090471 | AL115: 0.076525 | AM115: 0.006972 | AN115: -0.19788 | AO115: 0.116694 | AP115: 0.076848 | AQ115: -0.08898 | AR115: 0.061797 | AS115: 0.270576 | AT115: -0.15485
A116: 4.Types of material availability at local market | B116: 0.309717 | C116: 0.038038 | D116: 0.397407 | E116: 1 | F116: 0.316454 | G116: 0.084239 | H116: 0.236185 | I116: 0.232285 | J116: -0.45425 | K116: 0.140485 | L116: 0.051021 | M116: -0.16193 | N116: -0.03604 | O116: -0.16116 | P116: 0.208092 | Q116: -0.10403 | R116: -0.20777 | S116: 0.028562 | T116: -0.14653 | U116: 0.001561 | V116: -0.07572 | W116: 0.220992 | X116: -0.00764 | Y116: -0.05709 | Z116: -0.06973 | AA116: 0.097224 | AB116: 0.175331 | AC116: -0.18293 | AD116: 0.210854 | AE116: 0.090716 | AF116: -0.0372 | AG116: 0.118714 | AH116: -0.06465 | AI116: 0.03016 | AJ116: 0.179133 | AK116: -0.09983 | AL116: -0.0419 | AM116: -0.00975 | AN116: 0.052499 | AO116: -0.10186 | AP116: 0.076321 | AQ116: 0.121897 | AR116: -0.23319 | AS116: 0.055028 | AT116: 0.102968
A117: 5.Lack of consultant’s knowledge of available materials | B117: -0.06664 | C117: 0.147807 | D117: -0.08212 | E117: 0.316454 | F117: 1 | G117: 0.042391 | H117: -0.24957 | I117: -0.1843 | J117: 0.380314 | K117: -0.134 | L117: -0.10649 | M117: 0.007459 | N117: 0.384633 | O117: 0.328134 | P117: -0.31882 | Q117: 0.109376 | R117: -0.00207 | S117: -0.10925 | T117: 0.075494 | U117: 0.103951 | V117: -0.08555 | W117: 0.080607 | X117: -0.16099 | Y117: 0.114055 | Z117: 0.324678 | AA117: -0.18797 | AB117: 0.119898 | AC117: -0.01409 | AD117: -0.14066 | AE117: -0.4282 | AF117: 0.291957 | AG117: 0.156477 | AH117: 0.066301 | AI117: 0.097822 | AJ117: -0.29649 | AK117: 0.251585 | AL117: 0.060024 | AM117: 0.264128 | AN117: -0.33667 | AO117: 0.030168 | AP117: 0.145721 | AQ117: -0.22341 | AR117: 0.071797 | AS117: 0.039373 | AT117: -0.25995
A118: 6.Low productivity | B118: 0.147406 | C118: -0.13611 | D118: 0.062063 | E118: 0.084239 | F118: 0.042391 | G118: 1 | H118: 0.499306 | I118: 0.345992 | J118: -0.0184 | K118: -0.06968 | L118: 0.003474 | M118: 0.064866 | N118: 0.109205 | O118: -0.14043 | P118: -0.04314 | Q118: 0.106845 | R118: 0.13056 | S118: 0.098339 | T118: 0.052471 | U118: -0.10125 | V118: 0.026743 | W118: 0.058688 | X118: -0.1686 | Y118: 0.005223 | Z118: -0.22915 | AA118: 0.24357 | AB118: -0.22317 | AC118: 0.331202 | AD118: -0.16946 | AE118: 0.08406 | AF118: -0.03714 | AG118: -0.22017 | AH118: 0.114877 | AI118: -0.19629 | AJ118: 0.106204 | AK118: 0.112572 | AL118: 0.029923 | AM118: -0.20635 | AN118: 0.177723 | AO118: -0.09011 | AP118: -0.15916 | AQ118: 0.057706 | AR118: -0.122 | AS118: -0.19326 | AT118: 0.168472
A119: 7.Poor work execution | B119: -0.0105 | C119: 0.006782 | D119: 0.053656 | E119: 0.236185 | F119: -0.24957 | G119: 0.499306 | H119: 1 | I119: -0.31355 | J119: 0.377366 | K119: 0.077982 | L119: 0.070896 | M119: -0.1081 | N119: 0.174197 | O119: 0.333394 | P119: -0.29538 | Q119: -0.07709 | R119: 0.127205 | S119: 0.071016 | T119: -0.03367 | U119: -0.05423 | V119: -0.00585 | W119: -0.12765 | X119: -0.08472 | Y119: 0.205528 | Z119: 0.153552 | AA119: -0.11344 | AB119: 0.067561 | AC119: -0.13314 | AD119: 0.156985 | AE119: -0.34515 | AF119: 0.299693 | AG119: 0.032748 | AH119: 0.037095 | AI119: 0.135751 | AJ119: -0.1691 | AK119: -0.00967 | AL119: 0.067793 | AM119: 0.305987 | AN119: -0.34493 | AO119: 0.21422 | AP119: 0.074392 | AQ119: -0.15898 | AR119: 0.134023 | AS119: -0.09182 | AT119: -0.1965
A120: 8.Shortage of laborers | B120: 0.05778 | C120: 0.238985 | D120: -0.19497 | E120: 0.232285 | F120: -0.1843 | G120: 0.345992 | H120: -0.31355 | I120: 1 | J120: 0.3757 | K120: 0.286843 | L120: 0.097527 | M120: 0.228503 | N120: 0.088726 | O120: 0.296826 | P120: -0.27349 | Q120: -0.24081 | R120: 0.147533 | S120: 0.086998 | T120: 0.184428 | U120: -0.21252 | V120: -0.08559 | W120: -0.19356 | X120: -0.0543 | Y120: 0.144305 | Z120: 0.338407 | AA120: -0.31878 | AB120: 0.012567 | AC120: -0.05815 | AD120: 0.178975 | AE120: -0.08235 | AF120: 0.062771 | AG120: -0.07758 | AH120: 0.306711 | AI120: -0.14332 | AJ120: -0.39109 | AK120: 0.107385 | AL120: 0.308644 | AM120: -0.05592 | AN120: -0.26577 | AO120: 0.037757 | AP120: 0.029245 | AQ120: -0.08297 | AR120: 0.058929 | AS120: 0.031812 | AT120: -0.03351
A121: 9.Mistakes happens during construction phase | B121: 0.139003 | C121: -0.11671 | D121: 0.234642 | E121: -0.45425 | F121: 0.380314 | G121: -0.0184 | H121: 0.377366 | I121: 0.3757 | J121: 1 | K121: 0.25571 | L121: 0.134718 | M121: -0.0249 | N121: -0.10571 | O121: -0.32968 | P121: 0.395095 | Q121: 0.061092 | R121: -0.48523 | S121: 0.17867 | T121: -0.08415 | U121: -0.14651 | V121: 0.123148 | W121: 0.249087 | X121: 0.144918 | Y121: -0.22914 | Z121: -0.19415 | AA121: 0.216536 | AB121: 0.122755 | AC121: 0.000378 | AD121: 0.043405 | AE121: 0.207478 | AF121: -0.08889 | AG121: -0.04504 | AH121: -0.11865 | AI121: 0.05556 | AJ121: 0.371499 | AK121: -0.09409 | AL121: -0.10372 | AM121: -0.17178 | AN121: 0.320982 | AO121: -0.22156 | AP121: -0.11284 | AQ121: 0.204498 | AR121: -0.27544 | AS121: 0.113655 | AT121: 0.096365
A122: 10.Unavailability of equipment | B122: -0.00242 | C122: -0.06739 | D122: -0.08284 | E122: 0.140485 | F122: -0.134 | G122: -0.06968 | H122: 0.077982 | I122: 0.286843 | J122: 0.25571 | K122: 1 | L122: 0.019415 | M122: 0.274165 | N122: -0.18005 | O122: -0.02317 | P122: 0.073748 | Q122: 0.117285 | R122: 0.268317 | S122: -0.2103 | T122: 0.105608 | U122: -0.02166 | V122: -0.08124 | W122: 0.082134 | X122: -0.16776 | Y122: -0.06772 | Z122: -0.056 | AA122: 0.223977 | AB122: 0.146506 | AC122: -0.01996 | AD122: -0.31768 | AE122: -0.00887 | AF122: -0.03883 | AG122: 0.200322 | AH122: -0.15683 | AI122: -0.03374 | AJ122: -0.15911 | AK122: 0.057983 | AL122: -0.11873 | AM122: 0.171944 | AN122: 0.058879 | AO122: 0.027634 | AP122: 0.15996 | AQ122: -0.22055 | AR122: 0.25868 | AS122: 0.012588 | AT122: -0.03196
A123: 11.Lack of engineering experience | B123: -0.02551 | C123: 0.140664 | D123: 0.045824 | E123: 0.051021 | F123: -0.10649 | G123: 0.003474 | H123: 0.070896 | I123: 0.097527 | J123: 0.134718 | K123: 0.019415 | L123: 1 | M123: 0.11777 | N123: 0.287855 | O123: 0.142725 | P123: -0.09554 | Q123: 0.119544 | R123: 0.046054 | S123: -0.13759 | T123: 0.002997 | U123: 0.33804 | V123: -0.28457 | W123: -0.13469 | X123: 0.090294 | Y123: 0.060056 | Z123: 0.102707 | AA123: -0.1183 | AB123: 0.0837 | AC123: 0.092318 | AD123: -0.02474 | AE123: -0.12833 | AF123: -0.12012 | AG123: 0.110117 | AH123: -0.08104 | AI123: 0.167803 | AJ123: 0.033273 | AK123: 0.009952 | AL123: -0.23883 | AM123: -0.05387 | AN123: -0.00989 | AO123: 0.211621 | AP123: 0.079432 | AQ123: 0.021274 | AR123: -0.10819 | AS123: -0.04025 | AT123: 0.009145
A124: 12.Construction cost underestimation | B124: 0.046505 | C124: -0.24691 | D124: 0.061847 | E124: -0.16193 | F124: 0.007459 | G124: 0.064866 | H124: -0.1081 | I124: 0.228503 | J124: -0.0249 | K124: 0.274165 | L124: 0.11777 | M124: 1 | N124: 0.382459 | O124: -0.15729 | P124: -0.00873 | Q124: 0.119218 | R124: -0.07845 | S124: 0.237432 | T124: -0.19183 | U124: 0.181604 | V124: 0.224266 | W124: -0.0014 | X124: 0.017465 | Y124: -0.08125 | Z124: -0.02394 | AA124: -0.07976 | AB124: 0.001584 | AC124: 0.119338 | AD124: -0.18244 | AE124: 0.029942 | AF124: -0.10789 | AG124: 0.151542 | AH124: -0.0452 | AI124: -0.04616 | AJ124: 0.324817 | AK124: -0.18528 | AL124: 0.068397 | AM124: 0.136715 | AN124: -0.17411 | AO124: 0.003618 | AP124: 0.08103 | AQ124: 0.231126 | AR124: -0.05446 | AS124: -0.15503 | AT124: 0.049918
... A157: Relevant working experience | B157: -0.11769 | C157: 0.023369 | D157: -0.15485 | E157: 0.102968 | F157: -0.25995 | G157: 0.168472 | H157: -0.1965 | I157: -0.03351 | J157: 0.096365 | K157: -0.03196 | L157: 0.009145 | M157: 0.049918 | N157: 0.062596 | O157: 0.346499 | P157: -0.21927 | Q157: 0.01757 | R157: -0.00686 | S157: -0.01744 | T157: -0.13785 | U157: 0.028038 | V157: -0.16379 | W157: -0.02155 | X157: -0.01347 | Y157: 0.129806 | Z157: 0.155674 | AA157: -0.09468 | AB157: -0.00292 | AC157: -0.08996 | AD157: -0.00144 | AE157: -0.27319 | AF157: 0.299689 | AG157: -0.12648 | AH157: 0.044197 | AI157: 0.173556 | AJ157: -0.13909 | AK157: 0.034451 | AL157: -0.07423 | AM157: 0.209376 | AN157: -0.14357 | AO157: 0.013563 | AP157: 0.141643 | AQ157: -0.29486 | AR157: 0.008465 | AS157: 0.024134 | AT157: 1
B158: 0.901023 | C158: 1.08719 | D158: 1.004421 | E158: 1.229429 | F158: 1.82203 | G158: 1.173791 | H158: 1.660451 | I158: 1.826746 | J158: 2.196911 | K158: 0.971739 | L158: 0.700925 | M158: 1.002959 | N158: 1.103414 | O158: 1.936138 | P158: 1.910428 | Q158: 0.72505 | R158: 1.180008 | S158: 0.886876 | T158: 1.000961 | U158: 1.579717 | V158: 0.998875 | W158: 1.001275 | X158: 0.681214 | Y158: 0.91576 | Z158: 1.395223 | AA158: 1.307835 | AB158: 0.867379 | AC158: 1.208314 | AD158: 1.107794 | AE158: 1.806218 | AF158: 1.735888 | AG158: 1.521076 | AH158: 1.885807 | AI158: 1.211524 | AJ158: 2.113708 | AK158: 1.241718 | AL158: 0.924878 | AM158: 1.245491 | AN158: 1.410425 | AO158: 0.848394 | AP158: 1.642164 | AQ158: 1.304326 | AR158: 0.726119 | AS158: 0.548806 | AT158: 0.886544 | AU158: 56.43696
A160: KMO
B162: 1.Delay in delivering material to construction site | C162: 2.Monopoly of material by some suppliers | D162: 3.Prices fluctuation | E162: 4.Types of material availability at local market | F162: 5.Lack of consultant’s knowledge of available materials | G162: 6.Low productivity | H162: 7.Poor work execution | I162: 8.Shortage of laborers | J162: 9.Mistakes happens during construction phase | K162: 10.Unavailability of equipment | L162: 11.Lack of engineering experience | M162: 12.Construction cost underestimation | N162: 13.Poor site management | O162: 14.Delayed payment for completed work | P162: 15.Cash flow problem during construction | Q162: 16.High rate of interest | R162: 17.Contractor’s financial difficulties | S162: 19.Change design | T162: 20.Errors and omission in design | U162: 21.Incomplete design drawings and specifications at tendering stage | V162: 22.Delay in preparation and approval of drawing | W162: 23.Inaccurate quantity take-off | X162: 24.Long period from planning of project to construction | Y162: 25.Delays in issuing information to the contractor during construction stage | Z162: 26.No practical use of earned value management system | AA162: 27.Lack of cost planning/monitoring during pre and post contract stage | AB162: 28.Poor communication between client, consultant and contractor | AC162: 29.Insufficient coordination between local authority who is responsible about road projects and service authorities | AD162: 30.Delays in decisions making by the approval authorities | AE162: 31.Change schedule | AF162: 32.Stoppages because of work being rejected by consultant | AG162: 33.Lowest bid price | AH162: 34.Insufficient time for preparation of contract documents | AI162: 35.Discrepancies in contract documents | AJ162: 36.Underestimation of time for completion of project | AK162: 37.Extension of time with cost claims | AL162: 38.Scope and specification changes | AM162: 39.Changes in client requirements | AN162: 40.Frequency of variation orders and additional works | AO162: 41.Rework due to error in execution | AP162: 42.Weather conditions | AQ162: 43.Accidents during construction | AR162: 44.Delay in getting NOCs from different government authorities | AS162: Location of organization | AT162: Relevant working experience | AW162: The
B163: 0.824972 | C163: 0.753338 | D163: 0.691914 | E163: 0.809378 | F163: 0.772098 | G163: 0.844145 | H163: 0.818571 | I163: 0.769504 | J163: 0.752796 | K163: 0.862767 | L163: 0.907212 | M163: 0.870499 | N163: 0.852143 | O163: 0.570167 | P163: 0.647644 | Q163: 0.862175 | R163: 0.663062 | S163: 0.836903 | T163: 0.812289 | U163: 0.725625 | V163: 0.753898 | W163: 0.746632 | X163: 0.569222 | Y163: 0.850098 | Z163: 0.773336 | AA163: 0.841238 | AB163: 0.872517 | AC163: 0.7292 | AD163: 0.656005 | AE163: 0.620685 | AF163: 0.724352 | AG163: 0.58928 | AH163: 0.750442 | AI163: 0.815227 | AJ163: 0.615349 | AK163: 0.63289 | AL163: 0.7356 | AM163: 0.720601 | AN163: 0.622762 | AO163: 0.806187 | AP163: 0.75382 | AQ163: 0.723841 | AR163: 0.811343 | AS163: 0.560343 | AT163: 0.346684 | AU163: 0.766856 | AW163: Kaiser-Meyer-Olkin (KMO) test measures sampling adequacy for factor analysis, ranging from 0 to 1, with values closer to 1 indicating that variables are adequately correlated to form distinct factors. A minimum KMO value of 0.5 to 0.6 is generally required, while values above 0.8 or 0.9 are considered excellent.
AW164: Purpose: The KMO test evaluates if the sample size is adequate and if the data is suitable for factorization by measuring the proportion of variance among variables that might be common.
A165: Eigenvalues and eigenvectors
B167: 13.24902 | C167: 4.109563 | D167: 3.009904 | E167: 2.521689 | F167: 2.041292 | G167: 1.626274 | H167: 1.60841 | I167: 1.45329 | J167: 1.36846 | K167: 1.199541 | L167: 1.091042 | M167: 1.036112 | N167: 1.006165 | O167: 0.834988 | P167: 0.807773 | Q167: 0.722339 | R167: 0.639153 | S167: 0.623906 | T167: 0.582281 | U167: 0.534664 | V167: 0.511961 | W167: 0.459355 | X167: 0.382607 | Y167: 0.340528 | Z167: 0.33643 | AA167: 0.298327 | AB167: 0.281388 | AC167: 0.26568 | AD167: 0.239051 | AE167: 0.210505 | AF167: 0.194898 | AG167: 0.171041 | AH167: 0.16796 | AI167: 0.149935 | AJ167: 0.141967 | AK167: 0.128508 | AL167: 0.104914 | AM167: 0.100296 | AN167: 0.087254 | AO167: 0.083429 | AP167: 0.076379 | AQ167: 0.066021 | AR167: 0.060467 | AS167: 0.043956 | AT167: 0.031277
B168: -0.1462 | C168: -0.21913 | D168: -0.1188 | E168: -0.18317 | F168: -0.17241 | G168: -0.0467 | H168: -0.04934 | I168: -0.04265 | J168: -0.04914 | K168: -0.02301 | L168: -0.1474 | M168: -0.01382 | N168: -0.21113 | O168: -0.05024 | P168: -0.12351 | Q168: -0.336 | R168: -0.06816 | S168: -0.22402 | T168: -0.00976 | U168: -0.13026 | V168: -0.18962 | W168: -0.16239 | X168: -0.09283 | Y168: -0.04812 | Z168: -0.08227 | AA168: -0.13259 | AB168: -0.11212 | AC168: -0.11063 | AD168: -0.10443 | AE168: -0.1755 | AF168: -0.1391 | AG168: -0.29838 | AH168: -0.12512 | AI168: -0.08404 | AJ168: -0.07509 | AK168: -0.26638 | AL168: -0.32352 | AM168: -0.20925 | AN168: -0.09395 | AO168: -0.00891 | AP168: -0.12259 | AQ168: -0.12052 | AR168: -0.02835 | AS168: -0.11077 | AT168: -0.05462
B169: -0.12174 | C169: -0.21088 | D169: 0.032194 | E169: -0.28227 | F169: -0.25225 | G169: 0.099234 | H169: 0.089243 | I169: -0.01382 | J169: 0.018017 | K169: 0.086115 | L169: -0.15686 | M169: -0.1091 | N169: 0.057095 | O169: 0.069535 | P169: -0.00072 | Q169: -0.15621 | R169: 0.033611 | S169: 0.176797 | T169: 0.09505 | U169: -0.18107 | V169: 0.175881 | W169: 0.134682 | X169: 0.131612 | Y169: 0.023395 | Z169: -0.32019 | AA169: -0.27012 | AB169: 0.049272 | AC169: -0.20858 | AD169: 0.09878 | AE169: -0.03835 | AF169: -0.01378 | AG169: 0.295345 | AH169: 0.142452 | AI169: -0.21402 | AJ169: 0.01304 | AK169: 0.092892 | AL169: 0.03431 | AM169: 0.160361 | AN169: -0.11403 | AO169: -0.21307 | AP169: 0.193667 | AQ169: 0.164929 | AR169: -0.06353 | AS169: 0.024503 | AT169: 0.104238
B170: -0.10038 | C170: -0.18412 | D170: 0.100408 | E170: 0.090611 | F170: -0.19064 | G170: 0.293464 | H170: -0.03077 | I170: 0.144276 | J170: -0.17504 | K170: -0.15155 | L170: 0.199439 | M170: 0.202272 | N170: 0.190363 | O170: 0.086181 | P170: 0.295334 | Q170: 0.109653 | R170: 0.16984 | S170: -0.04804 | T170: 0.118049 | U170: -0.03644 | V170: -0.04426 | W170: -0.19765 | X170: 0.373427 | Y170: -0.08547 | Z170: -0.05403 | AA170: 0.202473 | AB170: 0.179397 | AC170: -0.09867 | AD170: 0.050083 | AE170: -0.15927 | AF170: 0.111292 | AG170: -0.0544 | AH170: 0.119231 | AI170: 0.092528 | AJ170: -0.11672 | AK170: -0.09322 | AL170: -0.14662 | AM170: -0.1066 | AN170: 0.120438 | AO170: -0.14179 | AP170: -0.16513 | AQ170: 0.045538 | AR170: -0.08506 | AS170: -0.01095 | AT170: -0.06153
B171: -0.16842 | C171: -0.2109 | D171: -0.01297 | E171: -0.13575 | F171: -0.17098 | G171: 0.064525 | H171: -0.04833 | I171: 0.018063 | J171: -0.14037 | K171: -0.19889 | L171: 0.122819 | M171: 0.137472 | N171: -0.10628 | O171: -0.16155 | P171: 0.029508 | Q171: -0.16789 | R171: -0.23161 | S171: 0.012205 | T171: -0.05393 | U171: -0.01517 | V171: -0.09192 | W171: 0.153441 | X171: 0.248976 | Y171: 0.097804 | Z171: 0.046631 | AA171: 0.18673 | AB171: -0.05226 | AC171: 0.067919 | AD171: -0.13522 | AE171: 0.10659 | AF171: -0.07432 | AG171: 0.128022 | AH171: -0.36257 | AI171: 0.192136 | AJ171: 0.328873 | AK171: 0.210304 | AL171: 0.059669 | AM171: 0.07117 | AN171: 0.083713 | AO171: 0.130232 | AP171: 0.087126 | AQ171: 0.006816 | AR171: 0.250518 | AS171: -0.04682 | AT171: 0.174459
B172: -0.19469 | C172: -0.05263 | D172: 0.100582 | E172: 0.032345 | F172: -0.17559 | G172: 0.037408 | H172: -0.03373 | I172: -0.08142 | J172: 0.004212 | K172: -0.04093 | L172: 0.040342 | M172: -0.01169 | N172: 0.17519 | O172: -0.29875 | P172: 0.128413 | Q172: -0.07136 | R172: -0.08653 | S172: 0.389348 | T172: 0.182161 | U172: 0.106056 | V172: -0.04025 | W172: -0.05522 | X172: -0.33503 | Y172: 0.246415 | Z172: 0.115316 | AA172: 0.084287 | AB172: -0.26414 | AC172: 0.093238 | AD172: 0.087501 | AE172: -0.16657 | AF172: -0.03797 | AG172: 0.111395 | AH172: -0.05503 | AI172: 0.007304 | AJ172: -0.25605 | AK172: -0.0386 | AL172: 0.04579 | AM172: -0.18345 | AN172: 0.15866 | AO172: -0.00228 | AP172: 0.201903 | AQ172: 0.053683 | AR172: -0.07027 | AS172: -0.05221 | AT172: -0.22705
B173: -0.18718 | C173: -0.22253 | D173: -0.03932 | E173: 0.098678 | F173: 0.174391 | G173: 0.073033 | H173: 0.118276 | I173: -0.07461 | J173: 0.029606 | K173: -0.04417 | L173: -0.11672 | M173: 0.151607 | N173: -0.04832 | O173: 0.013852 | P173: -0.14005 | Q173: -0.05807 | R173: 0.097484 | S173: 0.027082 | T173: -0.19498 | U173: 0.099557 | V173: 0.063174 | W173: -0.12964 | X173: 0.195111 | Y173: 0.138984 | Z173: 0.115728 | AA173: -0.04633 | AB173: 0.039886 | AC173: 0.145318 | AD173: 0.119697 | AE173: 0.243854 | AF173: -0.01621 | AG173: 0.040459 | AH173: -0.13301 | AI173: -0.15143 | AJ173: -0.11088 | AK173: -0.32609 | AL173: -0.04659 | AM173: 0.125996 | AN173: 0.207238 | AO173: 0.220442 | AP173: 0.175186 | AQ173: 0.067198 | AR173: -0.39568 | AS173: 0.209083 | AT173: 0.171167
B174: -0.2091 | C174: -0.18401 | D174: -0.05116 | E174: 0.041705 | F174: 0.083975 | G174: 0.119398 | H174: 0.054173 | I174: 0.016564 | J174: 0.039612 | K174: -0.15989 | L174: -0.08859 | M174: 0.078849 | N174: -0.16028 | O174: -0.12619 | P174: -0.07665 | Q174: 0.125281 | R174: 0.085925 | S174: 0.004836 | T174: -0.03297 | U174: 0.099749 | V174: -0.06975 | W174: -0.04873 | X174: 0.06423 | Y174: 0.072889 | Z174: -0.08589 | AA174: 0.038779 | AB174: 0.141598 | AC174: 0.400413 | AD174: 0.013812 | AE174: 0.132248 | AF174: -0.15633 | AG174: -0.22848 | AH174: 0.211199 | AI174: -0.12378 | AJ174: -0.03794 | AK174: 0.107654 | AL174: 0.102073 | AM174: 0.095873 | AN174: -0.3747 | AO174: -0.165 | AP174: 0.117409 | AQ174: 0.127501 | AR174: 0.223918 | AS174: -0.08076 | AT174: -0.35151
B175: -0.18586 | C175: -0.18285 | D175: -0.13211 | E175: 0.034894 | F175: 0.049007 | G175: -0.05392 | H175: 0.116286 | I175: -0.23293 | J175: -0.02672 | K175: -0.00068 | L175: 0.110485 | M175: 0.092842 | N175: 0.093252 | O175: 0.194229 | P175: -0.0694 | Q175: -0.17847 | R175: 0.151697 | S175: -0.20474 | T175: -0.15384 | U175: -0.0126 | V175: -0.00591 | W175: 0.154698 | X175: -0.17399 | Y175: 0.216808 | Z175: 0.08228 | AA175: 0.085718 | AB175: -0.06474 | AC175: -0.17703 | AD175: 0.015218 | AE175: 0.064745 | AF175: 0.106517 | AG175: 0.245934 | AH175: 0.016912 | AI175: -0.08556 | AJ175: -0.08962 | AK175: 0.088557 | AL175: 0.074096 | AM175: 0.12864 | AN175: 0.106559 | AO175: -0.04052 | AP175: -0.43962 | AQ175: 0.036211 | AR175: 0.180032 | AS175: 0.145189 | AT175: -0.33637
B176: -0.19505 | C176: -0.18164 | D176: 0.084324 | E176: 0.18272 | F176: 0.094793 | G176: 0.027839 | H176: -0.03913 | I176: -0.09173 | J176: -0.03162 | K176: 0.088454 | L176: -0.09141 | M176: -0.06587 | N176: 0.148951 | O176: 0.038944 | P176: -0.11504 | Q176: 0.108299 | R176: 0.084388 | S176: -0.00435 | T176: -0.14585 | U176: -0.13068 | V176: -0.20107 | W176: -0.08925 | X176: -0.17162 | Y176: -0.22354 | Z176: -0.06844 | AA176: 0.105056 | AB176: 0.000964 | AC176: -0.00212 | AD176: 0.346255 | AE176: -0.11779 | AF176: -0.18903 | AG176: 0.007633 | AH176: 0.080454 | AI176: -0.00657 | AJ176: -0.1761 | AK176: 0.25865 | AL176: -0.13443 | AM176: -0.02552 | AN176: 0.079164 | AO176: 0.157104 | AP176: 0.059905 | AQ176: -0.01893 | AR176: 0.342119 | AS176: 0.02333 | AT176: 0.405396
B177: -0.19074 | C177: -0.08488 | D177: -0.15023 | E177: -0.00686 | F177: 0.027416 | G177: -0.04391 | H177: 0.058844 | I177: -0.08149 | J177: -0.3339 | K177: 0.175525 | L177: -0.01464 | M177: -0.05782 | N177: 0.110008 | O177: 0.230572 | P177: -0.19491 | Q177: 0.039612 | R177: 0.021138 | S177: -0.00197 | T177: 0.002393 | U177: 0.086529 | V177: -0.05235 | W177: 0.256436 | X177: -0.12068 | Y177: -0.10321 | Z177: 0.038831 | AA177: 0.153751 | AB177: 0.177897 | AC177: 0.186152 | AD177: -0.1036 | AE177: -0.21752 | AF177: 0.076372 | AG177: -0.1147 | AH177: -0.11658 | AI177: 0.100626 | AJ177: 0.062106 | AK177: 0.099471 | AL177: 0.042117 | AM177: 0.055451 | AN177: 0.09668 | AO177: -0.35755 | AP177: 0.22869 | AQ177: -0.281 | AR177: -0.29387 | AS177: -0.05451 | AT177: -0.01033
B178: -0.1994 | C178: -0.17475 | D178: 0.022769 | E178: -0.01029 | F178: 0.164769 | G178: 0.083182 | H178: 0.169104 | I178: 0.118545 | J178: 0.048195 | K178: 0.093323 | L178: 0.160754 | M178: -0.11258 | N178: 0.080622 | O178: -0.10511 | P178: 0.06374 | Q178: -0.04362 | R178: -0.07541 | S178: -0.13406 | T178: 0.098177 | U178: -0.1486 | V178: 0.067163 | W178: -0.00838 | X178: -0.07331 | Y178: -0.06638 | Z178: 0.192823 | AA178: -0.10082 | AB178: 0.092113 | AC178: 0.008855 | AD178: -0.08276 | AE178: -0.00644 | AF178: 0.120684 | AG178: -0.10513 | AH178: 0.228997 | AI178: -0.34974 | AJ178: 0.351346 | AK178: 0.251863 | AL178: 0.095665 | AM178: -0.31895 | AN178: 0.136842 | AO178: 0.281809 | AP178: 0.002496 | AQ178: 0.018102 | AR178: -0.16906 | AS178: -0.13976 | AT178: -0.04507
... B212: 0.029545 | C212: 0.023641 | D212: -0.04288 | E212: 0.004613 | F212: 0.328726 | G212: -0.13448 | H212: 0.373683 | I212: -0.17884 | J212: 0.165291 | K212: -0.1739 | L212: -0.09975 | M212: 0.270864 | N212: -0.03979 | O212: 0.199864 | P212: 0.072232 | Q212: -0.13976 | R212: -0.34077 | S212: 0.168274 | T212: 0.377607 | U212: -0.032 | V212: -0.25143 | W212: 0.111325 | X212: 0.129757 | Y212: -0.15664 | Z212: -0.00983 | AA212: 0.106345 | AB212: 0.074024 | AC212: -0.15433 | AD212: 0.090686 | AE212: -0.05824 | AF212: -0.01812 | AG212: 0.012954 | AH212: 0.077828 | AI212: 0.027828 | AJ212: -0.06582 | AK212: -0.02695 | AL212: -0.05871 | AM212: 0.008533 | AN212: -0.0034 | AO212: 0.040504 | AP212: 0.089484 | AQ212: -0.03069 | AR212: 0.027153 | AS212: -0.03467 | AT212: -0.07733
A214: Full Load Matrix
B216: 1 | C216: 2 | D216: 3 | E216: 4 | F216: 5 | G216: 6 | H216: 7 | I216: 8 | J216: 9 | K216: 10 | L216: 11 | M216: 12 | N216: 13 | O216: 14 | P216: 15 | Q216: 16 | R216: 17 | S216: 18 | T216: 19 | U216: 20 | V216: 21 | W216: 22 | X216: 23 | Y216: 24 | Z216: 25 | AA216: 26 | AB216: 27 | AC216: 28 | AD216: 29 | AE216: 30 | AF216: 31 | AG216: 32 | AH216: 33 | AI216: 34 | AJ216: 35 | AK216: 36 | AL216: 37 | AM216: 38 | AN216: 39 | AO216: 40 | AP216: 41 | AQ216: 42 | AR216: 43 | AS216: 44 | AT216: 45 | AV216: Commun
A217: 1.Delay in delivering material to construction site | B217: -0.53214 | C217: -0.44422 | D217: -0.20612 | E217: -0.29087 | F217: -0.24633 | G217: -0.05955 | H217: -0.06257 | I217: -0.05141 | J217: -0.05748 | K217: -0.0252 | L217: -0.15396 | M217: -0.01407 | N217: -0.21178 | O217: -0.04591 | P217: -0.11101 | Q217: -0.28557 | R217: -0.05449 | S217: -0.17695 | T217: -0.00745 | U217: -0.09525 | V217: -0.13568 | W217: -0.11006 | X217: -0.05742 | Y217: -0.02808 | Z217: -0.04772 | AA217: -0.07242 | AB217: -0.05948 | AC217: -0.05703 | AD217: -0.05106 | AE217: -0.08052 | AF217: -0.06141 | AG217: -0.1234 | AH217: -0.05128 | AI217: -0.03254 | AJ217: -0.02829 | AK217: -0.09549 | AL217: -0.10479 | AM217: -0.06627 | AN217: -0.02775 | AO217: -0.00257 | AP217: -0.03388 | AQ217: -0.03097 | AR217: -0.00697 | AS217: -0.02322 | AT217: -0.00966 | AV217: 1
A218: 2.Monopoly of material by some suppliers | B218: -0.44311 | C218: -0.4275 | D218: 0.055854 | E218: -0.44824 | F218: -0.3604 | G218: 0.126549 | H218: 0.11318 | I218: -0.01666 | J218: 0.021076 | K218: 0.094316 | L218: -0.16385 | M218: -0.11106 | N218: 0.057271 | O218: 0.063539 | P218: -0.00064 | Q218: -0.13277 | R218: 0.026871 | S218: 0.139648 | T218: 0.07253 | U218: -0.1324 | V218: 0.125845 | W218: 0.091281 | X218: 0.081409 | Y218: 0.013652 | Z218: -0.18572 | AA218: -0.14754 | AB218: 0.026137 | AC218: -0.10751 | AD218: 0.048296 | AE218: -0.0176 | AF218: -0.00608 | AG218: 0.122146 | AH218: 0.058381 | AI218: -0.08287 | AJ218: 0.004913 | AK218: 0.0333 | AL218: 0.011113 | AM218: 0.050786 | AN218: -0.03368 | AO218: -0.06154 | AP218: 0.053523 | AQ218: 0.042378 | AR218: -0.01562 | AS218: 0.005137 | AT218: 0.018435 | AV218: 1
A219: 3.Prices fluctuation | B219: -0.36537 | C219: -0.37325 | D219: 0.174199 | E219: 0.143889 | F219: -0.27238 | G219: 0.374241 | H219: -0.03902 | I219: 0.173928 | J219: -0.20477 | K219: -0.16599 | L219: 0.20832 | M219: 0.205892 | N219: 0.190949 | O219: 0.07875 | P219: 0.265435 | Q219: 0.093195 | R219: 0.135782 | S219: -0.03794 | T219: 0.09008 | U219: -0.02665 | V219: -0.03167 | W219: -0.13396 | X219: 0.230984 | Y219: -0.04988 | Z219: -0.03134 | AA219: 0.110589 | AB219: 0.095163 | AC219: -0.05086 | AD219: 0.024487 | AE219: -0.07307 | AF219: 0.049132 | AG219: -0.0225 | AH219: 0.048864 | AI219: 0.035828 | AJ219: -0.04398 | AK219: -0.03342 | AL219: -0.04749 | AM219: -0.03376 | AN219: 0.035576 | AO219: -0.04096 | AP219: -0.04564 | AQ219: 0.011701 | AR219: -0.02092 | AS219: -0.0023 | AT219: -0.01088 | AV219: 1
A220: 4.Types of material availability at local market | B220: -0.61304 | C220: -0.42753 | D220: -0.0225 | E220: -0.21557 | F220: -0.24429 | G220: 0.082286 | H220: -0.06129 | I220: 0.021776 | J220: -0.16421 | K220: -0.21784 | L220: 0.128288 | M220: 0.139932 | N220: -0.10661 | O220: -0.14762 | P220: 0.026521 | Q220: -0.14269 | R220: -0.18517 | S220: 0.009641 | T220: -0.04115 | U220: -0.01109 | V220: -0.06577 | W220: 0.103995 | X220: 0.154004 | Y220: 0.057073 | Z220: 0.027047 | AA220: 0.101991 | AB220: -0.02772 | AC220: 0.035008 | AD220: -0.06611 | AE220: 0.048904 | AF220: -0.03281 | AG220: 0.052946 | AH220: -0.14859 | AI220: 0.074398 | AJ220: 0.123914 | AK220: 0.07539 | AL220: 0.019327 | AM220: 0.022539 | AN220: 0.024728 | AO220: 0.037616 | AP220: 0.024079 | AQ220: 0.001751 | AR220: 0.061602 | AS220: -0.00982 | AT220: 0.030853 | AV220: 1
A221: 5.Lack of consultant’s knowledge of available materials | B221: -0.70866 | C221: -0.10669 | D221: 0.174501 | E221: 0.051363 | F221: -0.25088 | G221: 0.047704 | H221: -0.04277 | I221: -0.09815 | J221: 0.004928 | K221: -0.04483 | L221: 0.042138 | M221: -0.0119 | N221: 0.17573 | O221: -0.27299 | P221: 0.115412 | Q221: -0.06065 | R221: -0.06918 | S221: 0.307537 | T221: 0.139002 | U221: 0.077549 | V221: -0.0288 | W221: -0.03743 | X221: -0.20723 | Y221: 0.143795 | Z221: 0.066886 | AA221: 0.046037 | AB221: -0.14011 | AC221: 0.048059 | AD221: 0.042782 | AE221: -0.07642 | AF221: -0.01676 | AG221: 0.04607 | AH221: -0.02255 | AI221: 0.002828 | AJ221: -0.09648 | AK221: -0.01384 | AL221: 0.014832 | AM221: -0.0581 | AN221: 0.046866 | AO221: -0.00066 | AP221: 0.055799 | AQ221: 0.013794 | AR221: -0.01728 | AS221: -0.01095 | AT221: -0.04015 | AV221: 1
A222: 6.Low productivity | B222: -0.68133 | C222: -0.45111 | D222: -0.06822 | E222: 0.156699 | F222: 0.249159 | G222: 0.093136 | H222: 0.150002 | I222: -0.08994 | J222: 0.034633 | K222: -0.04838 | L222: -0.12191 | M222: 0.15432 | N222: -0.04847 | O222: 0.012658 | P222: -0.12587 | Q222: -0.04935 | R222: 0.077936 | S222: 0.021392 | T222: -0.14879 | U222: 0.072797 | V222: 0.045202 | W222: -0.08786 | X222: 0.120686 | Y222: 0.081104 | Z222: 0.067125 | AA222: -0.02531 | AB222: 0.021158 | AC222: 0.074903 | AD222: 0.058523 | AE222: 0.111882 | AF222: -0.00716 | AG222: 0.016733 | AH222: -0.05451 | AI222: -0.05863 | AJ222: -0.04178 | AK222: -0.1169 | AL222: -0.01509 | AM222: 0.039902 | AN222: 0.061216 | AO222: 0.063673 | AP222: 0.048416 | AQ222: 0.017266 | AR222: -0.0973 | AS222: 0.043836 | AT222: 0.030271 | AV222: 1
A223: 7.Poor work execution | B223: -0.7611 | C223: -0.37303 | D223: -0.08875 | E223: 0.066228 | F223: 0.119979 | G223: 0.152263 | H223: 0.068704 | I223: 0.019968 | J223: 0.046339 | K223: -0.17512 | L223: -0.09253 | M223: 0.08026 | N223: -0.16077 | O223: -0.11531 | P223: -0.06889 | Q223: 0.106477 | R223: 0.068695 | S223: 0.00382 | T223: -0.02516 | U223: 0.072937 | V223: -0.04991 | W223: -0.03303 | X223: 0.03973 | Y223: 0.042534 | Z223: -0.04982 | AA223: 0.021181 | AB223: 0.075112 | AC223: 0.20639 | AD223: 0.006753 | AE223: 0.060676 | AF223: -0.06902 | AG223: -0.09449 | AH223: 0.086556 | AI223: -0.04793 | AJ223: -0.01429 | AK223: 0.038592 | AL223: 0.033062 | AM223: 0.030363 | AN223: -0.11068 | AO223: -0.04766 | AP223: 0.032448 | AQ223: 0.032761 | AR223: 0.055061 | AS223: -0.01693 | AT223: -0.06216 | AV223: 1
A224: 8.Shortage of laborers | B224: -0.6765 | C224: -0.37068 | D224: -0.22921 | E224: 0.055412 | F224: 0.070018 | G224: -0.06876 | H224: 0.147477 | I224: -0.28081 | J224: -0.03125 | K224: -0.00075 | L224: 0.115404 | M224: 0.094504 | N224: 0.093539 | O224: 0.177482 | P224: -0.06237 | Q224: -0.15168 | R224: 0.121277 | S224: -0.16172 | T224: -0.11739 | U224: -0.00921 | V224: -0.00423 | W224: 0.104848 | X224: -0.10762 | Y224: 0.126518 | Z224: 0.047725 | AA224: 0.046819 | AB224: -0.03434 | AC224: -0.09125 | AD224: 0.007441 | AE224: 0.029706 | AF224: 0.047024 | AG224: 0.101711 | AH224: 0.006931 | AI224: -0.03313 | AJ224: -0.03377 | AK224: 0.031746 | AL224: 0.024 | AM224: 0.04074 | AN224: 0.031476 | AO224: -0.0117 | AP224: -0.1215 | AQ224: 0.009304 | AR224: 0.04427 | AS224: 0.03044 | AT224: -0.05949 | AV224: 1
A225: 9.Mistakes happens during construction phase | B225: -0.70997 | C225: -0.36822 | D225: 0.146294 | E225: 0.290156 | F225: 0.135434 | G225: 0.035502 | H225: -0.04962 | I225: -0.11058 | J225: -0.03699 | K225: 0.096878 | L225: -0.09548 | M225: -0.06705 | N225: 0.149409 | O225: 0.035586 | P225: -0.10339 | Q225: 0.092044 | R225: 0.067466 | S225: -0.00344 | T225: -0.1113 | U225: -0.09556 | V225: -0.14387 | W225: -0.06049 | X225: -0.10616 | Y225: -0.13045 | Z225: -0.0397 | AA225: 0.057381 | AB225: 0.000511 | AC225: -0.00109 | AD225: 0.169294 | AE225: -0.05404 | AF225: -0.08345 | AG225: 0.003157 | AH225: 0.032972 | AI225: -0.00254 | AJ225: -0.06635 | AK225: 0.092721 | AL225: -0.04354 | AM225: -0.00808 | AN225: 0.023384 | AO225: 0.045378 | AP225: 0.016556 | AQ225: -0.00486 | AR225: 0.084127 | AS225: 0.004891 | AT225: 0.071695 | AV225: 1
A226: 10.Unavailability of equipment | B226: -0.69426 | C226: -0.17207 | D226: -0.26064 | E226: -0.01089 | F226: 0.03917 | G226: -0.056 | H226: 0.074628 | I226: -0.09824 | J226: -0.3906 | K226: 0.192242 | L226: -0.01529 | M226: -0.05886 | N226: 0.110347 | O226: 0.210691 | P226: -0.17517 | Q226: 0.033666 | R226: 0.016899 | S226: -0.00156 | T226: 0.001826 | U226: 0.063271 | V226: -0.03746 | W226: 0.173801 | X226: -0.07465 | Y226: -0.06023 | Z226: 0.022523 | AA226: 0.083978 | AB226: 0.094367 | AC226: 0.095951 | AD226: -0.05065 | AE226: -0.0998 | AF226: 0.033716 | AG226: -0.04744 | AH226: -0.04778 | AI226: 0.038964 | AJ226: 0.023401 | AK226: 0.035658 | AL226: 0.013642 | AM226: 0.017561 | AN226: 0.028558 | AO226: -0.10327 | AP226: 0.063203 | AQ226: -0.0722 | AR226: -0.07226 | AS226: -0.01143 | AT226: -0.00183 | AV226: 1
A227: 11.Lack of engineering experience | B227: -0.72581 | C227: -0.35426 | D227: 0.039502 | E227: -0.01635 | F227: 0.235412 | G227: 0.106078 | H227: 0.214463 | I227: 0.142909 | J227: 0.05638 | K227: 0.10221 | L227: 0.167913 | M227: -0.1146 | N227: 0.08087 | O227: -0.09604 | P227: 0.057287 | Q227: -0.03708 | R227: -0.06028 | S227: -0.10589 | T227: 0.074916 | U227: -0.10866 | V227: 0.048056 | W227: -0.00568 | X227: -0.04535 | Y227: -0.03874 | Z227: 0.111842 | AA227: -0.05506 | AB227: 0.048862 | AC227: 0.004564 | AD227: -0.04046 | AE227: -0.00295 | AF227: 0.053279 | AG227: -0.04348 | AH227: 0.09385 | AI227: -0.13542 | AJ227: 0.132382 | AK227: 0.090288 | AL227: 0.030986 | AM227: -0.10101 | AN227: 0.040422 | AO227: 0.081398 | AP227: 0.00069 | AQ227: 0.004651 | AR227: -0.04157 | AS227: -0.0293 | AT227: -0.00797 | AV227: 1
A228: 12.Construction cost underestimation | B228: -0.71994 | C228: -0.27265 | D228: 0.025744 | E228: 0.383086 | F228: 0.13805 | G228: -0.06913 | H228: 0.022934 | I228: 0.011396 | J228: 0.079925 | K228: 0.191368 | L228: 0.190976 | M228: 0.00179 | N228: 0.036916 | O228: 0.126622 | P228: -0.03497 | Q228: 0.026389 | R228: 0.112099 | S228: -0.00882 | T228: 0.063714 | U228: 0.11938 | V228: -0.00539 | W228: 0.066681 | X228: -0.00901 | Y228: -0.06676 | Z228: 0.0939 | AA228: -0.11691 | AB228: -0.06564 | AC228: -0.1185 | AD228: -0.09166 | AE228: -0.04007 | AF228: -0.02127 | AG228: -0.04181 | AH228: -0.05669 | AI228: 0.095215 | AJ228: 0.029959 | AK228: -0.06615 | AL228: 0.016592 | AM228: -0.00911 | AN228: -0.04932 | AO228: -0.01656 | AP228: 0.038122 | AQ228: 0.14259 | AR228: 0.021379 | AS228: -0.02469 | AT228: 0.01257 | AV228: 1
... A261: Relevant working experience | B261: 0.10754 | C261: 0.047924 | D261: -0.07439 | E261: 0.007325 | F261: 0.469663 | G261: -0.17149 | H261: 0.473916 | I261: -0.2156 | J261: 0.193359 | K261: -0.19046 | L261: -0.10419 | M261: 0.275711 | N261: -0.03991 | O261: 0.182631 | P261: 0.06492 | Q261: -0.11878 | R261: -0.27244 | S261: 0.132916 | T261: 0.288142 | U261: -0.0234 | V261: -0.1799 | W261: 0.075451 | X261: 0.080261 | Y261: -0.09141 | Z261: -0.0057 | AA261: 0.058085 | AB261: 0.039267 | AC261: -0.07955 | AD261: 0.044339 | AE261: -0.02672 | AF261: -0.008 | AG261: 0.005357 | AH261: 0.031896 | AI261: 0.010775 | AJ261: -0.0248 | AK261: -0.00966 | AL261: -0.01902 | AM261: 0.002702 | AN261: -0.001 | AO261: 0.011699 | AP261: 0.024731 | AQ261: -0.00789 | AR261: 0.006677 | AS261: -0.00727 | AT261: -0.01368 | AV261: 1
A263: Scree Plot
B265: eValue | C265: % | D265: Cum %
B266: 13.24902 | C266: 0.2944 | D266: 0.2944
B267: 4.109563 | C267: 0.0913 | D267: 0.3857
B268: 3.009904 | C268: 0.0669 | D268: 0.4526
B269: 2.521689 | C269: 0.056 | D269: 0.5087
B270: 2.041292 | C270: 0.0454 | D270: 0.554
B271: 1.626274 | C271: 0.0361 | D271: 0.5902
B272: 1.60841 | C272: 0.0357 | D272: 0.6259
B273: 1.45329 | C273: 0.0323 | D273: 0.6582
B274: 1.36846 | C274: 0.0304 | D274: 0.6886
B275: 1.199541 | C275: 0.0267 | D275: 0.7153
B276: 1.091042 | C276: 0.0242 | D276: 0.7395
B277: 1.036112 | C277: 0.023 | D277: 0.7625
...

Sheet Factor interpretation
A1: Factor Matrix (rotated Varimax)
B3: Construction & Operational Risk | C3: Design & Planning Risk | D3: Financial & Administrative Risk | E3: Scope Change Risk | F3: Supply Chain & Resource Risk | G3: Contractual & External Conditions Risk | I3: Commun | J3: Specific
A4: 1.Delay in delivering material to construction site | B4: -0.42743 | C4: -0.217 | D4: -0.20707 | E4: 0.004154 | F4: -0.61737 | G4: -0.13413 | I4: 0.671813 | J4: 0.328187
A5: 2.Monopoly of material by some suppliers | B5: -0.29489 | C5: 0.035137 | D5: -0.14306 | E5: -0.19042 | F5: -0.76181 | G5: -0.06141 | I5: 0.729048 | J5: 0.270952
A6: 3.Prices fluctuation | B6: -0.43014 | C6: 0.289559 | D6: 0.173324 | E6: 0.100275 | F6: -0.43497 | G6: 0.199858 | I6: 0.538106 | J6: 0.461894
A7: 4.Types of material availability at local market | B7: -0.50993 | C7: 0.013875 | D7: -0.13142 | E7: -0.0054 | F7: -0.61768 | G7: -0.11387 | I7: 0.672023 | J7: 0.327977
A8: 5.Lack of consultant’s knowledge of available materials | B8: -0.45379 | C8: 0.309829 | D8: -0.04435 | E8: 0.225343 | F8: -0.41591 | G8: -0.29024 | I8: 0.611881 | J8: 0.388119
A9: 6.Low productivity | B9: -0.86181 | C9: -0.01856 | D9: -0.05572 | E9: 0.052252 | F9: -0.11351 | G9: -0.07665 | I9: 0.767663 | J9: 0.232337
A10: 7.Poor work execution | B10: -0.81165 | C10: 0.062538 | D10: -0.17007 | E10: 0.097767 | F10: -0.24337 | G10: -0.08871 | I10: 0.768264 | J10: 0.231736
A11: 8.Shortage of laborers | B11: -0.69791 | C11: -0.16785 | D11: -0.16827 | E11: 0.166463 | F11: -0.24097 | G11: -0.17595 | I11: 0.660296 | J11: 0.339704
A12: 9.Mistakes happens during construction phase | B12: -0.80615 | C12: 0.151749 | D12: 0.121543 | E12: 0.144758 | F12: -0.12515 | G12: -0.20136 | I12: 0.764842 | J12: 0.235158
A13: 10.Unavailability of equipment | B13: -0.57933 | C13: -0.09021 | D13: -0.31335 | E13: 0.213045 | F13: -0.21609 | G13: -0.22428 | I13: 0.584325 | J13: 0.415675
A14: 11.Lack of engineering experience | B14: -0.79104 | C14: 0.099912 | D14: -0.14681 | E14: -0.06235 | F14: -0.17178 | G14: -0.17356 | I14: 0.720801 | J14: 0.279199
A15: 12.Construction cost underestimation | B15: -0.77285 | C15: 0.068882 | D15: 0.080759 | E15: 0.296076 | F15: -0.03753 | G15: -0.25742 | I15: 0.763904 | J15: 0.236096
... A48: Relevant working experience | B48: -0.06545 | C48: -0.19444 | D48: -0.06086 | E48: -0.17684 | F48: 0.429176 | G48: -0.09046 | I48: 0.269441 | J48: 0.730559
B49: 7.872626 | C49: 3.535375 | D49: 4.244592 | E49: 3.37707 | F49: 3.261012 | G49: 4.267069 | I49: 26.55774 | J49: 18.44226

Sheet Cleaned dataset
A1: 1.Delay in delivering material to construction site | B1: 2.Monopoly of material by some suppliers | C1: 3.Prices fluctuation | D1: 4.Types of material availability at local market | E1: 5.Lack of consultant’s knowledge of available materials | F1: 6.Low productivity | G1: 7.Poor work execution | H1: 8.Shortage of laborers | I1: 9.Mistakes happens during construction phase | J1: 10.Unavailability of equipment | K1: 11.Lack of engineering experience | L1: 12.Construction cost underestimation | M1: 13.Poor site management | N1: 14.Delayed payment for completed work | O1: 15.Cash flow problem during construction | P1: 16.High rate of interest | Q1: 17.Contractor’s financial difficulties | R1: 19.Change design | S1: 20.Errors and omission in design | T1: 21.Incomplete design drawings and specifications at tendering stage | U1: 22.Delay in preparation and approval of drawing | V1: 23.Inaccurate quantity take-off | W1: 24.Long period from planning of project to construction | X1: 25.Delays in issuing information to the contractor during construction stage | Y1: 26.No practical use of earned value management system | Z1: 27.Lack of cost planning/monitoring during pre and post contract stage | AA1: 28.Poor communication between client, consultant and contractor | AB1: 29.Insufficient coordination between local authority who is responsible about road projects and service authorities | AC1: 30.Delays in decisions making by the approval authorities | AD1: 31.Change schedule | AE1: 32.Stoppages because of work being rejected by consultant | AF1: 33.Lowest bid price | AG1: 34.Insufficient time for preparation of contract documents | AH1: 35.Discrepancies in contract documents | AI1: 36.Underestimation of time for completion of project | AJ1: 37.Extension of time with cost claims | AK1: 38.Scope and specification changes | AL1: 39.Changes in client requirements | AM1: 40.Frequency of variation orders and additional works | AN1: 41.Rework due to error in execution | AO1: 42.Weather conditions | AP1: 43.Accidents during construction | AQ1: 44.Delay in getting NOCs from different government authorities | AR1: Location of organization | AS1: Relevant working experience
A2: 1 | B2: 1 | C2: 1 | D2: 1 | E2: 1 | F2: 1 | G2: 1 | H2: 1 | I2: 1 | J2: 1 | K2: 1 | L2: 1 | M2: 1 | N2: 1 | O2: 1 | P2: 1 | Q2: 1 | R2: 3 | S2: 3 | T2: 3 | U2: 4 | V2: 4 | W2: 3 | X2: 3 | Y2: 2 | Z2: 1 | AA2: 2 | AB2: 4 | AC2: 4 | AD2: 1 | AE2: 1 | AF2: 2 | AG2: 2 | AH2: 2 | AI2: 2 | AJ2: 2 | AK2: 3 | AL2: 3 | AM2: 3 | AN2: 1 | AO2: 2 | AP2: 2 | AQ2: 3 | AR2: 3 | AS2: 5
A3: 2 | B3: 5 | C3: 3 | D3: 2 | E3: 3 | F3: 2 | G3: 2 | H3: 2 | I3: 3 | J3: 2 | K3: 2 | L3: 2 | M3: 2 | N3: 2 | O3: 2 | P3: 1 | Q3: 4 | R3: 5 | S3: 5 | T3: 4 | U3: 4 | V3: 4 | W3: 5 | X3: 3 | Y3: 3 | Z3: 3 | AA3: 4 | AB3: 4 | AC3: 3 | AD3: 4 | AE3: 4 | AF3: 5 | AG3: 3 | AH3: 4 | AI3: 4 | AJ3: 4 | AK3: 3 | AL3: 3 | AM3: 4 | AN3: 3 | AO3: 1 | AP3: 1 | AQ3: 4 | AR3: 3 | AS3: 3
A4: 1 | B4: 2 | C4: 1 | D4: 1 | E4: 2 | F4: 2 | G4: 1 | H4: 2 | I4: 1 | J4: 1 | K4: 2 | L4: 1 | M4: 3 | N4: 3 | O4: 3 | P4: 2 | Q4: 2 | R4: 2 | S4: 2 | T4: 2 | U4: 2 | V4: 3 | W4: 2 | X4: 3 | Y4: 1 | Z4: 2 | AA4: 1 | AB4: 3 | AC4: 4 | AD4: 3 | AE4: 1 | AF4: 2 | AG4: 2 | AH4: 2 | AI4: 2 | AJ4: 4 | AK4: 2 | AL4: 2 | AM4: 2 | AN4: 2 | AO4: 1 | AP4: 1 | AQ4: 4 | AR4: 2 | AS4: 4
A5: 2 | B5: 2 | C5: 3 | D5: 3 | E5: 2 | F5: 2 | G5: 3 | H5: 4 | I5: 4 | J5: 4 | K5: 2 | L5: 5 | M5: 2 | N5: 2 | O5: 1 | P5: 1 | Q5: 1 | R5: 4 | S5: 4 | T5: 4 | U5: 4 | V5: 4 | W5: 3 | X5: 2 | Y5: 2 | Z5: 2 | AA5: 2 | AB5: 3 | AC5: 3 | AD5: 2 | AE5: 2 | AF5: 2 | AG5: 3 | AH5: 2 | AI5: 4 | AJ5: 4 | AK5: 4 | AL5: 4 | AM5: 4 | AN5: 3 | AO5: 4 | AP5: 3 | AQ5: 3 | AR5: 3 | AS5: 4
A6: 1 | B6: 2 | C6: 1 | D6: 1 | E6: 2 | F6: 2 | G6: 1 | H6: 2 | I6: 1 | J6: 1 | K6: 2 | L6: 1 | M6: 2 | N6: 4 | O6: 4 | P6: 2 | Q6: 2 | R6: 2 | S6: 2 | T6: 2 | U6: 2 | V6: 3 | W6: 2 | X6: 4 | Y6: 3 | Z6: 2 | AA6: 1 | AB6: 3 | AC6: 4 | AD6: 3 | AE6: 1 | AF6: 2 | AG6: 2 | AH6: 2 | AI6: 2 | AJ6: 4 | AK6: 2 | AL6: 2 | AM6: 2 | AN6: 2 | AO6: 1 | AP6: 1 | AQ6: 4 | AR6: 2 | AS6: 4
A7: 1 | B7: 1 | C7: 1 | D7: 1 | E7: 1 | F7: 2 | G7: 2 | H7: 2 | I7: 1 | J7: 1 | K7: 1 | L7: 2 | M7: 1 | N7: 4 | O7: 4 | P7: 4 | Q7: 4 | R7: 4 | S7: 4 | T7: 4 | U7: 4 | V7: 4 | W7: 4 | X7: 2 | Y7: 2 | Z7: 2 | AA7: 1 | AB7: 1 | AC7: 3 | AD7: 3 | AE7: 4 | AF7: 2 | AG7: 2 | AH7: 2 | AI7: 2 | AJ7: 2 | AK7: 3 | AL7: 2 | AM7: 3 | AN7: 3 | AO7: 2 | AP7: 2 | AQ7: 2 | AR7: 3 | AS7: 5
A8: 1 | B8: 1 | C8: 1 | D8: 1 | E8: 1 | F8: 1 | G8: 1 | H8: 1 | I8: 1 | J8: 1 | K8: 1 | L8: 1 | M8: 1 | N8: 4 | O8: 4 | P8: 4 | Q8: 4 | R8: 4 | S8: 4 | T8: 4 | U8: 4 | V8: 4 | W8: 4 | X8: 2 | Y8: 2 | Z8: 2 | AA8: 1 | AB8: 2 | AC8: 4 | AD8: 3 | AE8: 4 | AF8: 2 | AG8: 2 | AH8: 2 | AI8: 2 | AJ8: 4 | AK8: 4 | AL8: 3 | AM8: 4 | AN8: 4 | AO8: 2 | AP8: 2 | AQ8: 2 | AR8: 3 | AS8: 5
A9: 1 | B9: 1 | C9: 1 | D9: 1 | E9: 1 | F9: 1 | G9: 1 | H9: 1 | I9: 1 | J9: 1 | K9: 1 | L9: 1 | M9: 1 | N9: 3 | O9: 3 | P9: 3 | Q9: 4 | R9: 4 | S9: 4 | T9: 4 | U9: 4 | V9: 4 | W9: 4 | X9: 2 | Y9: 2 | Z9: 2 | AA9: 1 | AB9: 1 | AC9: 3 | AD9: 3 | AE9: 4 | AF9: 2 | AG9: 2 | AH9: 2 | AI9: 2 | AJ9: 2 | AK9: 3 | AL9: 2 | AM9: 3 | AN9: 3 | AO9: 2 | AP9: 2 | AQ9: 2 | AR9: 3 | AS9: 5
A10: 1 | B10: 1 | C10: 1 | D10: 1 | E10: 1 | F10: 1 | G10: 1 | H10: 1 | I10: 1 | J10: 1 | K10: 1 | L10: 1 | M10: 1 | N10: 4 | O10: 4 | P10: 4 | Q10: 4 | R10: 4 | S10: 4 | T10: 4 | U10: 4 | V10: 4 | W10: 4 | X10: 2 | Y10: 2 | Z10: 2 | AA10: 1 | AB10: 2 | AC10: 4 | AD10: 3 | AE10: 4 | AF10: 2 | AG10: 2 | AH10: 2 | AI10: 2 | AJ10: 2 | AK10: 4 | AL10: 3 | AM10: 4 | AN10: 4 | AO10: 2 | AP10: 2 | AQ10: 2 | AR10: 3 | AS10: 5
A11: 1 | B11: 1 | C11: 1 | D11: 1 | E11: 1 | F11: 1 | G11: 1 | H11: 1 | I11: 1 | J11: 1 | K11: 1 | L11: 1 | M11: 1 | N11: 4 | O11: 4 | P11: 4 | Q11: 4 | R11: 4 | S11: 4 | T11: 4 | U11: 4 | V11: 4 | W11: 4 | X11: 2 | Y11: 2 | Z11: 2 | AA11: 1 | AB11: 1 | AC11: 3 | AD11: 3 | AE11: 4 | AF11: 2 | AG11: 2 | AH11: 2 | AI11: 2 | AJ11: 2 | AK11: 3 | AL11: 2 | AM11: 3 | AN11: 3 | AO11: 2 | AP11: 2 | AQ11: 2 | AR11: 3 | AS11: 5
A12: 2 | B12: 4 | C12: 4 | D12: 1 | E12: 1 | F12: 5 | G12: 1 | H12: 4 | I12: 5 | J12: 3 | K12: 2 | L12: 5 | M12: 2 | N12: 1 | O12: 1 | P12: 1 | Q12: 1 | R12: 5 | S12: 2 | T12: 3 | U12: 4 | V12: 3 | W12: 2 | X12: 2 | Y12: 1 | Z12: 2 | AA12: 1 | AB12: 5 | AC12: 1 | AD12: 1 | AE12: 1 | AF12: 1 | AG12: 1 | AH12: 1 | AI12: 3 | AJ12: 3 | AK12: 4 | AL12: 4 | AM12: 4 | AN12: 1 | AO12: 1 | AP12: 1 | AQ12: 1 | AR12: 3 | AS12: 4
